Workbook

Sheet Summary
A1: WCAG evaluation results — condition comparison
A4: Overall accuracy by condition
A5: Condition | B5: Key | C5: Records | D5: Correct | E5: Accuracy | F5: Pass recall | G5: Fail recall | H5: Inapplicable recall | I5: Avg time (s) | J5: Avg issues | K5: Avg tool calls
A6: axe | B6: A | C6: =COUNTA(A_axe!$A$2:$A$538) -> 537 | D6: =SUM(A_axe!$I$2:$I$538) -> 237 | E6: =IFERROR(D6/C6,"") -> 0.44134078 | F6: =IFERROR(COUNTIFS(A_axe!$G$2:$G$538,"passed",A_axe!$I$2:$I$538,1)/COUNTIF(A_axe!$G$2:$G$538,"passed"),"") -> 0.95 | G6: =IFERROR(COUNTIFS(A_axe!$G$2:$G$538,"failed",A_axe!$I$2:$I$538,1)/COUNTIF(A_axe!$G$2:$G$538,"failed"),"") -> 0.37288136 | H6: =IFERROR(COUNTIFS(A_axe!$G$2:$G$538,"inapplicable",A_axe!$I$2:$I$538,1)/COUNTIF(A_axe!$G$2:$G$538,"inapplicable"),"") -> 0 | I6: =AVERAGE(A_axe!$P$2:$P$538) -> 12.687169 | J6: =AVERAGE(A_axe!$L$2:$L$538) -> 0.15083799 | K6: =AVERAGE(A_axe!$M$2:$M$538) -> 1
A7: persona_llm | B7: B | C7: =COUNTA(B_persona_llm!$A$2:$A$538) -> 537 | D7: =SUM(B_persona_llm!$I$2:$I$538) -> 381 | E7: =IFERROR(D7/C7,"") -> 0.70949721 | F7: =IFERROR(COUNTIFS(B_persona_llm!$G$2:$G$538,"passed",B_persona_llm!$I$2:$I$538,1)/COUNTIF(B_persona_llm!$G$2:$G$538,"passed"),"") -> 0.60555556 | G7: =IFERROR(COUNTIFS(B_persona_llm!$G$2:$G$538,"failed",B_persona_llm!$I$2:$I$538,1)/COUNTIF(B_persona_llm!$G$2:$G$538,"failed"),"") -> 0.94350282 | H7: =IFERROR(COUNTIFS(B_persona_llm!$G$2:$G$538,"inapplicable",B_persona_llm!$I$2:$I$538,1)/COUNTIF(B_persona_llm!$G$2:$G$538,"inapplicable"),"") -> 0.58333333 | I7: =AVERAGE(B_persona_llm!$P$2:$P$538) -> 7.538175 | J7: =AVERAGE(B_persona_llm!$L$2:$L$538) -> 1.1620112 | K7: =AVERAGE(B_persona_llm!$M$2:$M$538) -> 0
A8: persona_agent | B8: C | C8: =COUNTA(C_persona_agent!$A$2:$A$538) -> 537 | D8: =SUM(C_persona_agent!$I$2:$I$538) -> 284 | E8: =IFERROR(D8/C8,"") -> 0.52886406 | F8: =IFERROR(COUNTIFS(C_persona_agent!$G$2:$G$538,"passed",C_persona_agent!$I$2:$I$538,1)/COUNTIF(C_persona_agent!$G$2:$G$538,"passed"),"") -> 0.39444444 | G8: =IFERROR(COUNTIFS(C_persona_agent!$G$2:$G$538,"failed",C_persona_agent!$I$2:$I$538,1)/COUNTIF(C_persona_agent!$G$2:$G$538,"failed"),"") -> 0.86440678 | H8: =IFERROR(COUNTIFS(C_persona_agent!$G$2:$G$538,"inapplicable",C_persona_agent!$I$2:$I$538,1)/COUNTIF(C_persona_agent!$G$2:$G$538,"inapplicable"),"") -> 0.33333333 | I8: =AVERAGE(C_persona_agent!$P$2:$P$538) -> 28.47581 | J8: =AVERAGE(C_persona_agent!$L$2:$L$538) -> 0.84729981 | K8: =AVERAGE(C_persona_agent!$M$2:$M$538) -> 4.3389199
A9: vanilla_llm | B9: D | C9: =COUNTA(D_vanilla_llm!$A$2:$A$538) -> 537 | D9: =SUM(D_vanilla_llm!$I$2:$I$538) -> 370 | E9: =IFERROR(D9/C9,"") -> 0.68901304 | F9: =IFERROR(COUNTIFS(D_vanilla_llm!$G$2:$G$538,"passed",D_vanilla_llm!$I$2:$I$538,1)/COUNTIF(D_vanilla_llm!$G$2:$G$538,"passed"),"") -> 0.71111111 | G9: =IFERROR(COUNTIFS(D_vanilla_llm!$G$2:$G$538,"failed",D_vanilla_llm!$I$2:$I$538,1)/COUNTIF(D_vanilla_llm!$G$2:$G$538,"failed"),"") -> 0.96045198 | H9: =IFERROR(COUNTIFS(D_vanilla_llm!$G$2:$G$538,"inapplicable",D_vanilla_llm!$I$2:$I$538,1)/COUNTIF(D_vanilla_llm!$G$2:$G$538,"inapplicable"),"") -> 0.4 | I9: =AVERAGE(D_vanilla_llm!$P$2:$P$538) -> 9.8285847 | J9: =AVERAGE(D_vanilla_llm!$L$2:$L$538) -> 0.99255121 | K9: =AVERAGE(D_vanilla_llm!$M$2:$M$538) -> 0
A10: vanilla_agent | B10: E | C10: =COUNTA(E_vanilla_agent!$A$2:$A$538) -> 537 | D10: =SUM(E_vanilla_agent!$I$2:$I$538) -> 302 | E10: =IFERROR(D10/C10,"") -> 0.56238361 | F10: =IFERROR(COUNTIFS(E_vanilla_agent!$G$2:$G$538,"passed",E_vanilla_agent!$I$2:$I$538,1)/COUNTIF(E_vanilla_agent!$G$2:$G$538,"passed"),"") -> 0.39444444 | G10: =IFERROR(COUNTIFS(E_vanilla_agent!$G$2:$G$538,"failed",E_vanilla_agent!$I$2:$I$538,1)/COUNTIF(E_vanilla_agent!$G$2:$G$538,"failed"),"") -> 0.93220339 | H10: =IFERROR(COUNTIFS(E_vanilla_agent!$G$2:$G$538,"inapplicable",E_vanilla_agent!$I$2:$I$538,1)/COUNTIF(E_vanilla_agent!$G$2:$G$538,"inapplicable"),"") -> 0.36666667 | I10: =AVERAGE(E_vanilla_agent!$P$2:$P$538) -> 31.454879 | J10: =AVERAGE(E_vanilla_agent!$L$2:$L$538) -> 1.2290503 | K10: =AVERAGE(E_vanilla_agent!$M$2:$M$538) -> 4.4078212
A13: Confusion matrix — counts of evaluated label per expected label
A14: Condition | B14: Expected | C14: eval: passed | D14: eval: failed | E14: eval: inapplicable | F14: eval: error | G14: Total
A15: axe | B15: passed | C15: =COUNTIFS(A_axe!$G$2:$G$538,"passed",A_axe!$H$2:$H$538,"passed") -> 171 | D15: =COUNTIFS(A_axe!$G$2:$G$538,"passed",A_axe!$H$2:$H$538,"failed") -> 9 | E15: =COUNTIFS(A_axe!$G$2:$G$538,"passed",A_axe!$H$2:$H$538,"inapplicable") -> 0 | F15: =COUNTIFS(A_axe!$G$2:$G$538,"passed",A_axe!$H$2:$H$538,"error") -> 0 | G15: =SUM(C15:F15) -> 180
A16: axe | B16: failed | C16: =COUNTIFS(A_axe!$G$2:$G$538,"failed",A_axe!$H$2:$H$538,"passed") -> 111 | D16: =COUNTIFS(A_axe!$G$2:$G$538,"failed",A_axe!$H$2:$H$538,"failed") -> 66 | E16: =COUNTIFS(A_axe!$G$2:$G$538,"failed",A_axe!$H$2:$H$538,"inapplicable") -> 0 | F16: =COUNTIFS(A_axe!$G$2:$G$538,"failed",A_axe!$H$2:$H$538,"error") -> 0 | G16: =SUM(C16:F16) -> 177
A17: axe | B17: inapplicable | C17: =COUNTIFS(A_axe!$G$2:$G$538,"inapplicable",A_axe!$H$2:$H$538,"passed") -> 180 | D17: =COUNTIFS(A_axe!$G$2:$G$538,"inapplicable",A_axe!$H$2:$H$538,"failed") -> 0 | E17: =COUNTIFS(A_axe!$G$2:$G$538,"inapplicable",A_axe!$H$2:$H$538,"inapplicable") -> 0 | F17: =COUNTIFS(A_axe!$G$2:$G$538,"inapplicable",A_axe!$H$2:$H$538,"error") -> 0 | G17: =SUM(C17:F17) -> 180
A18: persona_llm | B18: passed | C18: =COUNTIFS(B_persona_llm!$G$2:$G$538,"passed",B_persona_llm!$H$2:$H$538,"passed") -> 109 | D18: =COUNTIFS(B_persona_llm!$G$2:$G$538,"passed",B_persona_llm!$H$2:$H$538,"failed") -> 46 | E18: =COUNTIFS(B_persona_llm!$G$2:$G$538,"passed",B_persona_llm!$H$2:$H$538,"inapplicable") -> 23 | F18: =COUNTIFS(B_persona_llm!$G$2:$G$538,"passed",B_persona_llm!$H$2:$H$538,"error") -> 2 | G18: =SUM(C18:F18) -> 180
A19: persona_llm | B19: failed | C19: =COUNTIFS(B_persona_llm!$G$2:$G$538,"failed",B_persona_llm!$H$2:$H$538,"passed") -> 6 | D19: =COUNTIFS(B_persona_llm!$G$2:$G$538,"failed",B_persona_llm!$H$2:$H$538,"failed") -> 167 | E19: =COUNTIFS(B_persona_llm!$G$2:$G$538,"failed",B_persona_llm!$H$2:$H$538,"inapplicable") -> 4 | F19: =COUNTIFS(B_persona_llm!$G$2:$G$538,"failed",B_persona_llm!$H$2:$H$538,"error") -> 0 | G19: =SUM(C19:F19) -> 177
A20: persona_llm | B20: inapplicable | C20: =COUNTIFS(B_persona_llm!$G$2:$G$538,"inapplicable",B_persona_llm!$H$2:$H$538,"passed") -> 54 | D20: =COUNTIFS(B_persona_llm!$G$2:$G$538,"inapplicable",B_persona_llm!$H$2:$H$538,"failed") -> 21 | E20: =COUNTIFS(B_persona_llm!$G$2:$G$538,"inapplicable",B_persona_llm!$H$2:$H$538,"inapplicable") -> 105 | F20: =COUNTIFS(B_persona_llm!$G$2:$G$538,"inapplicable",B_persona_llm!$H$2:$H$538,"error") -> 0 | G20: =SUM(C20:F20) -> 180
A21: persona_agent | B21: passed | C21: =COUNTIFS(C_persona_agent!$G$2:$G$538,"passed",C_persona_agent!$H$2:$H$538,"passed") -> 71 | D21: =COUNTIFS(C_persona_agent!$G$2:$G$538,"passed",C_persona_agent!$H$2:$H$538,"failed") -> 105 | E21: =COUNTIFS(C_persona_agent!$G$2:$G$538,"passed",C_persona_agent!$H$2:$H$538,"inapplicable") -> 4 | F21: =COUNTIFS(C_persona_agent!$G$2:$G$538,"passed",C_persona_agent!$H$2:$H$538,"error") -> 0 | G21: =SUM(C21:F21) -> 180
A22: persona_agent | B22: failed | C22: =COUNTIFS(C_persona_agent!$G$2:$G$538,"failed",C_persona_agent!$H$2:$H$538,"passed") -> 22 | D22: =COUNTIFS(C_persona_agent!$G$2:$G$538,"failed",C_persona_agent!$H$2:$H$538,"failed") -> 153 | E22: =COUNTIFS(C_persona_agent!$G$2:$G$538,"failed",C_persona_agent!$H$2:$H$538,"inapplicable") -> 2 | F22: =COUNTIFS(C_persona_agent!$G$2:$G$538,"failed",C_persona_agent!$H$2:$H$538,"error") -> 0 | G22: =SUM(C22:F22) -> 177
A23: persona_agent | B23: inapplicable | C23: =COUNTIFS(C_persona_agent!$G$2:$G$538,"inapplicable",C_persona_agent!$H$2:$H$538,"passed") -> 66 | D23: =COUNTIFS(C_persona_agent!$G$2:$G$538,"inapplicable",C_persona_agent!$H$2:$H$538,"failed") -> 54 | E23: =COUNTIFS(C_persona_agent!$G$2:$G$538,"inapplicable",C_persona_agent!$H$2:$H$538,"inapplicable") -> 60 | F23: =COUNTIFS(C_persona_agent!$G$2:$G$538,"inapplicable",C_persona_agent!$H$2:$H$538,"error") -> 0 | G23: =SUM(C23:F23) -> 180
A24: vanilla_llm | B24: passed | C24: =COUNTIFS(D_vanilla_llm!$G$2:$G$538,"passed",D_vanilla_llm!$H$2:$H$538,"passed") -> 128 | D24: =COUNTIFS(D_vanilla_llm!$G$2:$G$538,"passed",D_vanilla_llm!$H$2:$H$538,"failed") -> 45 | E24: =COUNTIFS(D_vanilla_llm!$G$2:$G$538,"passed",D_vanilla_llm!$H$2:$H$538,"inapplicable") -> 7 | F24: =COUNTIFS(D_vanilla_llm!$G$2:$G$538,"passed",D_vanilla_llm!$H$2:$H$538,"error") -> 0 | G24: =SUM(C24:F24) -> 180
A25: vanilla_llm | B25: failed | C25: =COUNTIFS(D_vanilla_llm!$G$2:$G$538,"failed",D_vanilla_llm!$H$2:$H$538,"passed") -> 4 | D25: =COUNTIFS(D_vanilla_llm!$G$2:$G$538,"failed",D_vanilla_llm!$H$2:$H$538,"failed") -> 170 | E25: =COUNTIFS(D_vanilla_llm!$G$2:$G$538,"failed",D_vanilla_llm!$H$2:$H$538,"inapplicable") -> 3 | F25: =COUNTIFS(D_vanilla_llm!$G$2:$G$538,"failed",D_vanilla_llm!$H$2:$H$538,"error") -> 0 | G25: =SUM(C25:F25) -> 177
A26: vanilla_llm | B26: inapplicable | C26: =COUNTIFS(D_vanilla_llm!$G$2:$G$538,"inapplicable",D_vanilla_llm!$H$2:$H$538,"passed") -> 51 | D26: =COUNTIFS(D_vanilla_llm!$G$2:$G$538,"inapplicable",D_vanilla_llm!$H$2:$H$538,"failed") -> 57 | E26: =COUNTIFS(D_vanilla_llm!$G$2:$G$538,"inapplicable",D_vanilla_llm!$H$2:$H$538,"inapplicable") -> 72 | F26: =COUNTIFS(D_vanilla_llm!$G$2:$G$538,"inapplicable",D_vanilla_llm!$H$2:$H$538,"error") -> 0 | G26: =SUM(C26:F26) -> 180
A27: vanilla_agent | B27: passed | C27: =COUNTIFS(E_vanilla_agent!$G$2:$G$538,"passed",E_vanilla_agent!$H$2:$H$538,"passed") -> 71 | D27: =COUNTIFS(E_vanilla_agent!$G$2:$G$538,"passed",E_vanilla_agent!$H$2:$H$538,"failed") -> 109 | E27: =COUNTIFS(E_vanilla_agent!$G$2:$G$538,"passed",E_vanilla_agent!$H$2:$H$538,"inapplicable") -> 0 | F27: =COUNTIFS(E_vanilla_agent!$G$2:$G$538,"passed",E_vanilla_agent!$H$2:$H$538,"error") -> 0 | G27: =SUM(C27:F27) -> 180
A28: vanilla_agent | B28: failed | C28: =COUNTIFS(E_vanilla_agent!$G$2:$G$538,"failed",E_vanilla_agent!$H$2:$H$538,"passed") -> 12 | D28: =COUNTIFS(E_vanilla_agent!$G$2:$G$538,"failed",E_vanilla_agent!$H$2:$H$538,"failed") -> 165 | E28: =COUNTIFS(E_vanilla_agent!$G$2:$G$538,"failed",E_vanilla_agent!$H$2:$H$538,"inapplicable") -> 0 | F28: =COUNTIFS(E_vanilla_agent!$G$2:$G$538,"failed",E_vanilla_agent!$H$2:$H$538,"error") -> 0 | G28: =SUM(C28:F28) -> 177
A29: vanilla_agent | B29: inapplicable | C29: =COUNTIFS(E_vanilla_agent!$G$2:$G$538,"inapplicable",E_vanilla_agent!$H$2:$H$538,"passed") -> 42 | D29: =COUNTIFS(E_vanilla_agent!$G$2:$G$538,"inapplicable",E_vanilla_agent!$H$2:$H$538,"failed") -> 72 | E29: =COUNTIFS(E_vanilla_agent!$G$2:$G$538,"inapplicable",E_vanilla_agent!$H$2:$H$538,"inapplicable") -> 66 | F29: =COUNTIFS(E_vanilla_agent!$G$2:$G$538,"inapplicable",E_vanilla_agent!$H$2:$H$538,"error") -> 0 | G29: =SUM(C29:F29) -> 180
A32: Accuracy by persona
A33: Persona | B33: axe | C33: persona_llm | D33: persona_agent | E33: vanilla_llm | F33: vanilla_agent
A34: ade | B34: =IFERROR(COUNTIFS(A_axe!$E$2:$E$538,"ade",A_axe!$I$2:$I$538,1)/COUNTIF(A_axe!$E$2:$E$538,"ade"),"") -> 0.43333333 | C34: =IFERROR(COUNTIFS(B_persona_llm!$E$2:$E$538,"ade",B_persona_llm!$I$2:$I$538,1)/COUNTIF(B_persona_llm!$E$2:$E$538,"ade"),"") -> 0.78888889 | D34: =IFERROR(COUNTIFS(C_persona_agent!$E$2:$E$538,"ade",C_persona_agent!$I$2:$I$538,1)/COUNTIF(C_persona_agent!$E$2:$E$538,"ade"),"") -> 0.53333333 | E34: =IFERROR(COUNTIFS(D_vanilla_llm!$E$2:$E$538,"ade",D_vanilla_llm!$I$2:$I$538,1)/COUNTIF(D_vanilla_llm!$E$2:$E$538,"ade"),"") -> 0.77777778 | F34: =IFERROR(COUNTIFS(E_vanilla_agent!$E$2:$E$538,"ade",E_vanilla_agent!$I$2:$I$538,1)/COUNTIF(E_vanilla_agent!$E$2:$E$538,"ade"),"") -> 0.63333333
A35: elias | B35: =IFERROR(COUNTIFS(A_axe!$E$2:$E$538,"elias",A_axe!$I$2:$I$538,1)/COUNTIF(A_axe!$E$2:$E$538,"elias"),"") -> 0.46666667 | C35: =IFERROR(COUNTIFS(B_persona_llm!$E$2:$E$538,"elias",B_persona_llm!$I$2:$I$538,1)/COUNTIF(B_persona_llm!$E$2:$E$538,"elias"),"") -> 0.84444444 | D35: =IFERROR(COUNTIFS(C_persona_agent!$E$2:$E$538,"elias",C_persona_agent!$I$2:$I$538,1)/COUNTIF(C_persona_agent!$E$2:$E$538,"elias"),"") -> 0.37777778 | E35: =IFERROR(COUNTIFS(D_vanilla_llm!$E$2:$E$538,"elias",D_vanilla_llm!$I$2:$I$538,1)/COUNTIF(D_vanilla_llm!$E$2:$E$538,"elias"),"") -> 0.81111111 | F35: =IFERROR(COUNTIFS(E_vanilla_agent!$E$2:$E$538,"elias",E_vanilla_agent!$I$2:$I$538,1)/COUNTIF(E_vanilla_agent!$E$2:$E$538,"elias"),"") -> 0.33333333
A36: ian | B36: =IFERROR(COUNTIFS(A_axe!$E$2:$E$538,"ian",A_axe!$I$2:$I$538,1)/COUNTIF(A_axe!$E$2:$E$538,"ian"),"") -> 0.43333333 | C36: =IFERROR(COUNTIFS(B_persona_llm!$E$2:$E$538,"ian",B_persona_llm!$I$2:$I$538,1)/COUNTIF(B_persona_llm!$E$2:$E$538,"ian"),"") -> 0.6 | D36: =IFERROR(COUNTIFS(C_persona_agent!$E$2:$E$538,"ian",C_persona_agent!$I$2:$I$538,1)/COUNTIF(C_persona_agent!$E$2:$E$538,"ian"),"") -> 0.5 | E36: =IFERROR(COUNTIFS(D_vanilla_llm!$E$2:$E$538,"ian",D_vanilla_llm!$I$2:$I$538,1)/COUNTIF(D_vanilla_llm!$E$2:$E$538,"ian"),"") -> 0.63333333 | F36: =IFERROR(COUNTIFS(E_vanilla_agent!$E$2:$E$538,"ian",E_vanilla_agent!$I$2:$I$538,1)/COUNTIF(E_vanilla_agent!$E$2:$E$538,"ian"),"") -> 0.6
A37: lakshmi | B37: =IFERROR(COUNTIFS(A_axe!$E$2:$E$538,"lakshmi",A_axe!$I$2:$I$538,1)/COUNTIF(A_axe!$E$2:$E$538,"lakshmi"),"") -> 0.51724138 | C37: =IFERROR(COUNTIFS(B_persona_llm!$E$2:$E$538,"lakshmi",B_persona_llm!$I$2:$I$538,1)/COUNTIF(B_persona_llm!$E$2:$E$538,"lakshmi"),"") -> 0.73563218 | D37: =IFERROR(COUNTIFS(C_persona_agent!$E$2:$E$538,"lakshmi",C_persona_agent!$I$2:$I$538,1)/COUNTIF(C_persona_agent!$E$2:$E$538,"lakshmi"),"") -> 0.66666667 | E37: =IFERROR(COUNTIFS(D_vanilla_llm!$E$2:$E$538,"lakshmi",D_vanilla_llm!$I$2:$I$538,1)/COUNTIF(D_vanilla_llm!$E$2:$E$538,"lakshmi"),"") -> 0.63218391 | F37: =IFERROR(COUNTIFS(E_vanilla_agent!$E$2:$E$538,"lakshmi",E_vanilla_agent!$I$2:$I$538,1)/COUNTIF(E_vanilla_agent!$E$2:$E$538,"lakshmi"),"") -> 0.66666667
A38: sophie | B38: =IFERROR(COUNTIFS(A_axe!$E$2:$E$538,"sophie",A_axe!$I$2:$I$538,1)/COUNTIF(A_axe!$E$2:$E$538,"sophie"),"") -> 0.4 | C38: =IFERROR(COUNTIFS(B_persona_llm!$E$2:$E$538,"sophie",B_persona_llm!$I$2:$I$538,1)/COUNTIF(B_persona_llm!$E$2:$E$538,"sophie"),"") -> 0.66666667 | D38: =IFERROR(COUNTIFS(C_persona_agent!$E$2:$E$538,"sophie",C_persona_agent!$I$2:$I$538,1)/COUNTIF(C_persona_agent!$E$2:$E$538,"sophie"),"") -> 0.45555556 | E38: =IFERROR(COUNTIFS(D_vanilla_llm!$E$2:$E$538,"sophie",D_vanilla_llm!$I$2:$I$538,1)/COUNTIF(D_vanilla_llm!$E$2:$E$538,"sophie"),"") -> 0.71111111 | F38: =IFERROR(COUNTIFS(E_vanilla_agent!$E$2:$E$538,"sophie",E_vanilla_agent!$I$2:$I$538,1)/COUNTIF(E_vanilla_agent!$E$2:$E$538,"sophie"),"") -> 0.54444444
A39: stefan | B39: =IFERROR(COUNTIFS(A_axe!$E$2:$E$538,"stefan",A_axe!$I$2:$I$538,1)/COUNTIF(A_axe!$E$2:$E$538,"stefan"),"") -> 0.4 | C39: =IFERROR(COUNTIFS(B_persona_llm!$E$2:$E$538,"stefan",B_persona_llm!$I$2:$I$538,1)/COUNTIF(B_persona_llm!$E$2:$E$538,"stefan"),"") -> 0.62222222 | D39: =IFERROR(COUNTIFS(C_persona_agent!$E$2:$E$538,"stefan",C_persona_agent!$I$2:$I$538,1)/COUNTIF(C_persona_agent!$E$2:$E$538,"stefan"),"") -> 0.64444444 | E39: =IFERROR(COUNTIFS(D_vanilla_llm!$E$2:$E$538,"stefan",D_vanilla_llm!$I$2:$I$538,1)/COUNTIF(D_vanilla_llm!$E$2:$E$538,"stefan"),"") -> 0.56666667 | F39: =IFERROR(COUNTIFS(E_vanilla_agent!$E$2:$E$538,"stefan",E_vanilla_agent!$I$2:$I$538,1)/COUNTIF(E_vanilla_agent!$E$2:$E$538,"stefan"),"") -> 0.6
A42: Accuracy by WCAG criterion
A43: WCAG criterion | B43: Records (per condition) | C43: axe | D43: persona_llm | E43: persona_agent | F43: vanilla_llm | G43: vanilla_agent
A44: 1.1.1 | B44: =COUNTIF(A_axe!$F$2:$F$538,"1.1.1") -> 18 | C44: =IFERROR(COUNTIFS(A_axe!$F$2:$F$538,"1.1.1",A_axe!$I$2:$I$538,1)/COUNTIF(A_axe!$F$2:$F$538,"1.1.1"),"") -> 0.66666667 | D44: =IFERROR(COUNTIFS(B_persona_llm!$F$2:$F$538,"1.1.1",B_persona_llm!$I$2:$I$538,1)/COUNTIF(B_persona_llm!$F$2:$F$538,"1.1.1"),"") -> 0.83333333 | E44: =IFERROR(COUNTIFS(C_persona_agent!$F$2:$F$538,"1.1.1",C_persona_agent!$I$2:$I$538,1)/COUNTIF(C_persona_agent!$F$2:$F$538,"1.1.1"),"") -> 0.66666667 | F44: =IFERROR(COUNTIFS(D_vanilla_llm!$F$2:$F$538,"1.1.1",D_vanilla_llm!$I$2:$I$538,1)/COUNTIF(D_vanilla_llm!$F$2:$F$538,"1.1.1"),"") -> 0.83333333 | G44: =IFERROR(COUNTIFS(E_vanilla_agent!$F$2:$F$538,"1.1.1",E_vanilla_agent!$I$2:$I$538,1)/COUNTIF(E_vanilla_agent!$F$2:$F$538,"1.1.1"),"") -> 0.72222222
A45: 1.3.1 | B45: =COUNTIF(A_axe!$F$2:$F$538,"1.3.1") -> 36 | C45: =IFERROR(COUNTIFS(A_axe!$F$2:$F$538,"1.3.1",A_axe!$I$2:$I$538,1)/COUNTIF(A_axe!$F$2:$F$538,"1.3.1"),"") -> 0.66666667 | D45: =IFERROR(COUNTIFS(B_persona_llm!$F$2:$F$538,"1.3.1",B_persona_llm!$I$2:$I$538,1)/COUNTIF(B_persona_llm!$F$2:$F$538,"1.3.1"),"") -> 0.83333333 | E45: =IFERROR(COUNTIFS(C_persona_agent!$F$2:$F$538,"1.3.1",C_persona_agent!$I$2:$I$538,1)/COUNTIF(C_persona_agent!$F$2:$F$538,"1.3.1"),"") -> 0.75 | F45: =IFERROR(COUNTIFS(D_vanilla_llm!$F$2:$F$538,"1.3.1",D_vanilla_llm!$I$2:$I$538,1)/COUNTIF(D_vanilla_llm!$F$2:$F$538,"1.3.1"),"") -> 0.69444444 | G45: =IFERROR(COUNTIFS(E_vanilla_agent!$F$2:$F$538,"1.3.1",E_vanilla_agent!$I$2:$I$538,1)/COUNTIF(E_vanilla_agent!$F$2:$F$538,"1.3.1"),"") -> 0.97222222
A46: 1.3.5 | B46: =COUNTIF(A_axe!$F$2:$F$538,"1.3.5") -> 18 | C46: =IFERROR(COUNTIFS(A_axe!$F$2:$F$538,"1.3.5",A_axe!$I$2:$I$538,1)/COUNTIF(A_axe!$F$2:$F$538,"1.3.5"),"") -> 0.66666667 | D46: =IFERROR(COUNTIFS(B_persona_llm!$F$2:$F$538,"1.3.5",B_persona_llm!$I$2:$I$538,1)/COUNTIF(B_persona_llm!$F$2:$F$538,"1.3.5"),"") -> 1 | E46: =IFERROR(COUNTIFS(C_persona_agent!$F$2:$F$538,"1.3.5",C_persona_agent!$I$2:$I$538,1)/COUNTIF(C_persona_agent!$F$2:$F$538,"1.3.5"),"") -> 0.38888889 | F46: =IFERROR(COUNTIFS(D_vanilla_llm!$F$2:$F$538,"1.3.5",D_vanilla_llm!$I$2:$I$538,1)/COUNTIF(D_vanilla_llm!$F$2:$F$538,"1.3.5"),"") -> 0.83333333 | G46: =IFERROR(COUNTIFS(E_vanilla_agent!$F$2:$F$538,"1.3.5",E_vanilla_agent!$I$2:$I$538,1)/COUNTIF(E_vanilla_agent!$F$2:$F$538,"1.3.5"),"") -> 0.33333333
A47: 1.4.3 | B47: =COUNTIF(A_axe!$F$2:$F$538,"1.4.3") -> 18 | C47: =IFERROR(COUNTIFS(A_axe!$F$2:$F$538,"1.4.3",A_axe!$I$2:$I$538,1)/COUNTIF(A_axe!$F$2:$F$538,"1.4.3"),"") -> 0.33333333 | D47: =IFERROR(COUNTIFS(B_persona_llm!$F$2:$F$538,"1.4.3",B_persona_llm!$I$2:$I$538,1)/COUNTIF(B_persona_llm!$F$2:$F$538,"1.4.3"),"") -> 0.83333333 | E47: =IFERROR(COUNTIFS(C_persona_agent!$F$2:$F$538,"1.4.3",C_persona_agent!$I$2:$I$538,1)/COUNTIF(C_persona_agent!$F$2:$F$538,"1.4.3"),"") -> 0.44444444 | F47: =IFERROR(COUNTIFS(D_vanilla_llm!$F$2:$F$538,"1.4.3",D_vanilla_llm!$I$2:$I$538,1)/COUNTIF(D_vanilla_llm!$F$2:$F$538,"1.4.3"),"") -> 0.83333333 | G47: =IFERROR(COUNTIFS(E_vanilla_agent!$F$2:$F$538,"1.4.3",E_vanilla_agent!$I$2:$I$538,1)/COUNTIF(E_vanilla_agent!$F$2:$F$538,"1.4.3"),"") -> 0.33333333
A48: 1.4.12 | B48: =COUNTIF(A_axe!$F$2:$F$538,"1.4.12") -> 36 | C48: =IFERROR(COUNTIFS(A_axe!$F$2:$F$538,"1.4.12",A_axe!$I$2:$I$538,1)/COUNTIF(A_axe!$F$2:$F$538,"1.4.12"),"") -> 0.5 | D48: =IFERROR(COUNTIFS(B_persona_llm!$F$2:$F$538,"1.4.12",B_persona_llm!$I$2:$I$538,1)/COUNTIF(B_persona_llm!$F$2:$F$538,"1.4.12"),"") -> 0.83333333 | E48: =IFERROR(COUNTIFS(C_persona_agent!$F$2:$F$538,"1.4.12",C_persona_agent!$I$2:$I$538,1)/COUNTIF(C_persona_agent!$F$2:$F$538,"1.4.12"),"") -> 0.55555556 | F48: =IFERROR(COUNTIFS(D_vanilla_llm!$F$2:$F$538,"1.4.12",D_vanilla_llm!$I$2:$I$538,1)/COUNTIF(D_vanilla_llm!$F$2:$F$538,"1.4.12"),"") -> 0.72222222 | G48: =IFERROR(COUNTIFS(E_vanilla_agent!$F$2:$F$538,"1.4.12",E_vanilla_agent!$I$2:$I$538,1)/COUNTIF(E_vanilla_agent!$F$2:$F$538,"1.4.12"),"") -> 0.66666667
A49: 2.1.1 | B49: =COUNTIF(A_axe!$F$2:$F$538,"2.1.1") -> 36 | C49: =IFERROR(COUNTIFS(A_axe!$F$2:$F$538,"2.1.1",A_axe!$I$2:$I$538,1)/COUNTIF(A_axe!$F$2:$F$538,"2.1.1"),"") -> 0.41666667 | D49: =IFERROR(COUNTIFS(B_persona_llm!$F$2:$F$538,"2.1.1",B_persona_llm!$I$2:$I$538,1)/COUNTIF(B_persona_llm!$F$2:$F$538,"2.1.1"),"") -> 0.97222222 | E49: =IFERROR(COUNTIFS(C_persona_agent!$F$2:$F$538,"2.1.1",C_persona_agent!$I$2:$I$538,1)/COUNTIF(C_persona_agent!$F$2:$F$538,"2.1.1"),"") -> 0.77777778 | F49: =IFERROR(COUNTIFS(D_vanilla_llm!$F$2:$F$538,"2.1.1",D_vanilla_llm!$I$2:$I$538,1)/COUNTIF(D_vanilla_llm!$F$2:$F$538,"2.1.1"),"") -> 0.77777778 | G49: =IFERROR(COUNTIFS(E_vanilla_agent!$F$2:$F$538,"2.1.1",E_vanilla_agent!$I$2:$I$538,1)/COUNTIF(E_vanilla_agent!$F$2:$F$538,"2.1.1"),"") -> 0.83333333
A50: 2.2.1 | B50: =COUNTIF(A_axe!$F$2:$F$538,"2.2.1") -> 36 | C50: =IFERROR(COUNTIFS(A_axe!$F$2:$F$538,"2.2.1",A_axe!$I$2:$I$538,1)/COUNTIF(A_axe!$F$2:$F$538,"2.2.1"),"") -> 0.66666667 | D50: =IFERROR(COUNTIFS(B_persona_llm!$F$2:$F$538,"2.2.1",B_persona_llm!$I$2:$I$538,1)/COUNTIF(B_persona_llm!$F$2:$F$538,"2.2.1"),"") -> 0.5 | E50: =IFERROR(COUNTIFS(C_persona_agent!$F$2:$F$538,"2.2.1",C_persona_agent!$I$2:$I$538,1)/COUNTIF(C_persona_agent!$F$2:$F$538,"2.2.1"),"") -> 0.38888889 | F50: =IFERROR(COUNTIFS(D_vanilla_llm!$F$2:$F$538,"2.2.1",D_vanilla_llm!$I$2:$I$538,1)/COUNTIF(D_vanilla_llm!$F$2:$F$538,"2.2.1"),"") -> 0.58333333 | G50: =IFERROR(COUNTIFS(E_vanilla_agent!$F$2:$F$538,"2.2.1",E_vanilla_agent!$I$2:$I$538,1)/COUNTIF(E_vanilla_agent!$F$2:$F$538,"2.2.1"),"") -> 0.33333333
A51: 2.2.2 | B51: =COUNTIF(A_axe!$F$2:$F$538,"2.2.2") -> 54 | C51: =IFERROR(COUNTIFS(A_axe!$F$2:$F$538,"2.2.2",A_axe!$I$2:$I$538,1)/COUNTIF(A_axe!$F$2:$F$538,"2.2.2"),"") -> 0.5 | D51: =IFERROR(COUNTIFS(B_persona_llm!$F$2:$F$538,"2.2.2",B_persona_llm!$I$2:$I$538,1)/COUNTIF(B_persona_llm!$F$2:$F$538,"2.2.2"),"") -> 0.74074074 | E51: =IFERROR(COUNTIFS(C_persona_agent!$F$2:$F$538,"2.2.2",C_persona_agent!$I$2:$I$538,1)/COUNTIF(C_persona_agent!$F$2:$F$538,"2.2.2"),"") -> 0.61111111 | F51: =IFERROR(COUNTIFS(D_vanilla_llm!$F$2:$F$538,"2.2.2",D_vanilla_llm!$I$2:$I$538,1)/COUNTIF(D_vanilla_llm!$F$2:$F$538,"2.2.2"),"") -> 0.77777778 | G51: =IFERROR(COUNTIFS(E_vanilla_agent!$F$2:$F$538,"2.2.2",E_vanilla_agent!$I$2:$I$538,1)/COUNTIF(E_vanilla_agent!$F$2:$F$538,"2.2.2"),"") -> 0.51851852
A52: 2.4.1 | B52: =COUNTIF(A_axe!$F$2:$F$538,"2.4.1") -> 18 | C52: =IFERROR(COUNTIFS(A_axe!$F$2:$F$538,"2.4.1",A_axe!$I$2:$I$538,1)/COUNTIF(A_axe!$F$2:$F$538,"2.4.1"),"") -> 0.33333333 | D52: =IFERROR(COUNTIFS(B_persona_llm!$F$2:$F$538,"2.4.1",B_persona_llm!$I$2:$I$538,1)/COUNTIF(B_persona_llm!$F$2:$F$538,"2.4.1"),"") -> 0.5 | E52: =IFERROR(COUNTIFS(C_persona_agent!$F$2:$F$538,"2.4.1",C_persona_agent!$I$2:$I$538,1)/COUNTIF(C_persona_agent!$F$2:$F$538,"2.4.1"),"") -> 0.5 | F52: =IFERROR(COUNTIFS(D_vanilla_llm!$F$2:$F$538,"2.4.1",D_vanilla_llm!$I$2:$I$538,1)/COUNTIF(D_vanilla_llm!$F$2:$F$538,"2.4.1"),"") -> 0.44444444 | G52: =IFERROR(COUNTIFS(E_vanilla_agent!$F$2:$F$538,"2.4.1",E_vanilla_agent!$I$2:$I$538,1)/COUNTIF(E_vanilla_agent!$F$2:$F$538,"2.4.1"),"") -> 0.33333333
A53: 2.4.3 | B53: =COUNTIF(A_axe!$F$2:$F$538,"2.4.3") -> 18 | C53: =IFERROR(COUNTIFS(A_axe!$F$2:$F$538,"2.4.3",A_axe!$I$2:$I$538,1)/COUNTIF(A_axe!$F$2:$F$538,"2.4.3"),"") -> 0.33333333 | D53: =IFERROR(COUNTIFS(B_persona_llm!$F$2:$F$538,"2.4.3",B_persona_llm!$I$2:$I$538,1)/COUNTIF(B_persona_llm!$F$2:$F$538,"2.4.3"),"") -> 0.66666667 | E53: =IFERROR(COUNTIFS(C_persona_agent!$F$2:$F$538,"2.4.3",C_persona_agent!$I$2:$I$538,1)/COUNTIF(C_persona_agent!$F$2:$F$538,"2.4.3"),"") -> 0.5 | F53: =IFERROR(COUNTIFS(D_vanilla_llm!$F$2:$F$538,"2.4.3",D_vanilla_llm!$I$2:$I$538,1)/COUNTIF(D_vanilla_llm!$F$2:$F$538,"2.4.3"),"") -> 0.83333333 | G53: =IFERROR(COUNTIFS(E_vanilla_agent!$F$2:$F$538,"2.4.3",E_vanilla_agent!$I$2:$I$538,1)/COUNTIF(E_vanilla_agent!$F$2:$F$538,"2.4.3"),"") -> 0.5
A54: 2.4.5 | B54: =COUNTIF(A_axe!$F$2:$F$538,"2.4.5") -> 18 | C54: =IFERROR(COUNTIFS(A_axe!$F$2:$F$538,"2.4.5",A_axe!$I$2:$I$538,1)/COUNTIF(A_axe!$F$2:$F$538,"2.4.5"),"") -> 0.33333333 | D54: =IFERROR(COUNTIFS(B_persona_llm!$F$2:$F$538,"2.4.5",B_persona_llm!$I$2:$I$538,1)/COUNTIF(B_persona_llm!$F$2:$F$538,"2.4.5"),"") -> 0.66666667 | E54: =IFERROR(COUNTIFS(C_persona_agent!$F$2:$F$538,"2.4.5",C_persona_agent!$I$2:$I$538,1)/COUNTIF(C_persona_agent!$F$2:$F$538,"2.4.5"),"") -> 0.5 | F54: =IFERROR(COUNTIFS(D_vanilla_llm!$F$2:$F$538,"2.4.5",D_vanilla_llm!$I$2:$I$538,1)/COUNTIF(D_vanilla_llm!$F$2:$F$538,"2.4.5"),"") -> 0.66666667 | G54: =IFERROR(COUNTIFS(E_vanilla_agent!$F$2:$F$538,"2.4.5",E_vanilla_agent!$I$2:$I$538,1)/COUNTIF(E_vanilla_agent!$F$2:$F$538,"2.4.5"),"") -> 0.66666667
A55: 2.4.6 | B55: =COUNTIF(A_axe!$F$2:$F$538,"2.4.6") -> 36 | C55: =IFERROR(COUNTIFS(A_axe!$F$2:$F$538,"2.4.6",A_axe!$I$2:$I$538,1)/COUNTIF(A_axe!$F$2:$F$538,"2.4.6"),"") -> 0.33333333 | D55: =IFERROR(COUNTIFS(B_persona_llm!$F$2:$F$538,"2.4.6",B_persona_llm!$I$2:$I$538,1)/COUNTIF(B_persona_llm!$F$2:$F$538,"2.4.6"),"") -> 0.5 | E55: =IFERROR(COUNTIFS(C_persona_agent!$F$2:$F$538,"2.4.6",C_persona_agent!$I$2:$I$538,1)/COUNTIF(C_persona_agent!$F$2:$F$538,"2.4.6"),"") -> 0.33333333 | F55: =IFERROR(COUNTIFS(D_vanilla_llm!$F$2:$F$538,"2.4.6",D_vanilla_llm!$I$2:$I$538,1)/COUNTIF(D_vanilla_llm!$F$2:$F$538,"2.4.6"),"") -> 0.41666667 | G55: =IFERROR(COUNTIFS(E_vanilla_agent!$F$2:$F$538,"2.4.6",E_vanilla_agent!$I$2:$I$538,1)/COUNTIF(E_vanilla_agent!$F$2:$F$538,"2.4.6"),"") -> 0.33333333
A56: 2.4.7 | B56: =COUNTIF(A_axe!$F$2:$F$538,"2.4.7") -> 18 | C56: =IFERROR(COUNTIFS(A_axe!$F$2:$F$538,"2.4.7",A_axe!$I$2:$I$538,1)/COUNTIF(A_axe!$F$2:$F$538,"2.4.7"),"") -> 0.33333333 | D56: =IFERROR(COUNTIFS(B_persona_llm!$F$2:$F$538,"2.4.7",B_persona_llm!$I$2:$I$538,1)/COUNTIF(B_persona_llm!$F$2:$F$538,"2.4.7"),"") -> 0.83333333 | E56: =IFERROR(COUNTIFS(C_persona_agent!$F$2:$F$538,"2.4.7",C_persona_agent!$I$2:$I$538,1)/COUNTIF(C_persona_agent!$F$2:$F$538,"2.4.7"),"") -> 0.5 | F56: =IFERROR(COUNTIFS(D_vanilla_llm!$F$2:$F$538,"2.4.7",D_vanilla_llm!$I$2:$I$538,1)/COUNTIF(D_vanilla_llm!$F$2:$F$538,"2.4.7"),"") -> 0.72222222 | G56: =IFERROR(COUNTIFS(E_vanilla_agent!$F$2:$F$538,"2.4.7",E_vanilla_agent!$I$2:$I$538,1)/COUNTIF(E_vanilla_agent!$F$2:$F$538,"2.4.7"),"") -> 0.66666667
A57: 2.4.8 | B57: =COUNTIF(A_axe!$F$2:$F$538,"2.4.8") -> 36 | C57: =IFERROR(COUNTIFS(A_axe!$F$2:$F$538,"2.4.8",A_axe!$I$2:$I$538,1)/COUNTIF(A_axe!$F$2:$F$538,"2.4.8"),"") -> 0.33333333 | D57: =IFERROR(COUNTIFS(B_persona_llm!$F$2:$F$538,"2.4.8",B_persona_llm!$I$2:$I$538,1)/COUNTIF(B_persona_llm!$F$2:$F$538,"2.4.8"),"") -> 0.55555556 | E57: =IFERROR(COUNTIFS(C_persona_agent!$F$2:$F$538,"2.4.8",C_persona_agent!$I$2:$I$538,1)/COUNTIF(C_persona_agent!$F$2:$F$538,"2.4.8"),"") -> 0.33333333 | F57: =IFERROR(COUNTIFS(D_vanilla_llm!$F$2:$F$538,"2.4.8",D_vanilla_llm!$I$2:$I$538,1)/COUNTIF(D_vanilla_llm!$F$2:$F$538,"2.4.8"),"") -> 0.63888889 | G57: =IFERROR(COUNTIFS(E_vanilla_agent!$F$2:$F$538,"2.4.8",E_vanilla_agent!$I$2:$I$538,1)/COUNTIF(E_vanilla_agent!$F$2:$F$538,"2.4.8"),"") -> 0.38888889
A58: 2.5.5 | B58: =COUNTIF(A_axe!$F$2:$F$538,"2.5.5") -> 18 | C58: =IFERROR(COUNTIFS(A_axe!$F$2:$F$538,"2.5.5",A_axe!$I$2:$I$538,1)/COUNTIF(A_axe!$F$2:$F$538,"2.5.5"),"") -> 0.33333333 | D58: =IFERROR(COUNTIFS(B_persona_llm!$F$2:$F$538,"2.5.5",B_persona_llm!$I$2:$I$538,1)/COUNTIF(B_persona_llm!$F$2:$F$538,"2.5.5"),"") -> 1 | E58: =IFERROR(COUNTIFS(C_persona_agent!$F$2:$F$538,"2.5.5",C_persona_agent!$I$2:$I$538,1)/COUNTIF(C_persona_agent!$F$2:$F$538,"2.5.5"),"") -> 0.55555556 | F58: =IFERROR(COUNTIFS(D_vanilla_llm!$F$2:$F$538,"2.5.5",D_vanilla_llm!$I$2:$I$538,1)/COUNTIF(D_vanilla_llm!$F$2:$F$538,"2.5.5"),"") -> 0.83333333 | G58: =IFERROR(COUNTIFS(E_vanilla_agent!$F$2:$F$538,"2.5.5",E_vanilla_agent!$I$2:$I$538,1)/COUNTIF(E_vanilla_agent!$F$2:$F$538,"2.5.5"),"") -> 0.83333333
A59: 3.1.4 | B59: =COUNTIF(A_axe!$F$2:$F$538,"3.1.4") -> 54 | C59: =IFERROR(COUNTIFS(A_axe!$F$2:$F$538,"3.1.4",A_axe!$I$2:$I$538,1)/COUNTIF(A_axe!$F$2:$F$538,"3.1.4"),"") -> 0.33333333 | D59: =IFERROR(COUNTIFS(B_persona_llm!$F$2:$F$538,"3.1.4",B_persona_llm!$I$2:$I$538,1)/COUNTIF(B_persona_llm!$F$2:$F$538,"3.1.4"),"") -> 0.62962963 | E59: =IFERROR(COUNTIFS(C_persona_agent!$F$2:$F$538,"3.1.4",C_persona_agent!$I$2:$I$538,1)/COUNTIF(C_persona_agent!$F$2:$F$538,"3.1.4"),"") -> 0.61111111 | F59: =IFERROR(COUNTIFS(D_vanilla_llm!$F$2:$F$538,"3.1.4",D_vanilla_llm!$I$2:$I$538,1)/COUNTIF(D_vanilla_llm!$F$2:$F$538,"3.1.4"),"") -> 0.61111111 | G59: =IFERROR(COUNTIFS(E_vanilla_agent!$F$2:$F$538,"3.1.4",E_vanilla_agent!$I$2:$I$538,1)/COUNTIF(E_vanilla_agent!$F$2:$F$538,"3.1.4"),"") -> 0.57407407
A60: 3.1.5 | B60: =COUNTIF(A_axe!$F$2:$F$538,"3.1.5") -> 18 | C60: =IFERROR(COUNTIFS(A_axe!$F$2:$F$538,"3.1.5",A_axe!$I$2:$I$538,1)/COUNTIF(A_axe!$F$2:$F$538,"3.1.5"),"") -> 0.33333333 | D60: =IFERROR(COUNTIFS(B_persona_llm!$F$2:$F$538,"3.1.5",B_persona_llm!$I$2:$I$538,1)/COUNTIF(B_persona_llm!$F$2:$F$538,"3.1.5"),"") -> 0.5 | E60: =IFERROR(COUNTIFS(C_persona_agent!$F$2:$F$538,"3.1.5",C_persona_agent!$I$2:$I$538,1)/COUNTIF(C_persona_agent!$F$2:$F$538,"3.1.5"),"") -> 0.5 | F60: =IFERROR(COUNTIFS(D_vanilla_llm!$F$2:$F$538,"3.1.5",D_vanilla_llm!$I$2:$I$538,1)/COUNTIF(D_vanilla_llm!$F$2:$F$538,"3.1.5"),"") -> 0.66666667 | G60: =IFERROR(COUNTIFS(E_vanilla_agent!$F$2:$F$538,"3.1.5",E_vanilla_agent!$I$2:$I$538,1)/COUNTIF(E_vanilla_agent!$F$2:$F$538,"3.1.5"),"") -> 0.5
A61: 3.3.1 | B61: =COUNTIF(A_axe!$F$2:$F$538,"3.3.1") -> 18 | C61: =IFERROR(COUNTIFS(A_axe!$F$2:$F$538,"3.3.1",A_axe!$I$2:$I$538,1)/COUNTIF(A_axe!$F$2:$F$538,"3.3.1"),"") -> 0.33333333 | D61: =IFERROR(COUNTIFS(B_persona_llm!$F$2:$F$538,"3.3.1",B_persona_llm!$I$2:$I$538,1)/COUNTIF(B_persona_llm!$F$2:$F$538,"3.3.1"),"") -> 0.83333333 | E61: =IFERROR(COUNTIFS(C_persona_agent!$F$2:$F$538,"3.3.1",C_persona_agent!$I$2:$I$538,1)/COUNTIF(C_persona_agent!$F$2:$F$538,"3.3.1"),"") -> 0.33333333 | F61: =IFERROR(COUNTIFS(D_vanilla_llm!$F$2:$F$538,"3.3.1",D_vanilla_llm!$I$2:$I$538,1)/COUNTIF(D_vanilla_llm!$F$2:$F$538,"3.3.1"),"") -> 1 | G61: =IFERROR(COUNTIFS(E_vanilla_agent!$F$2:$F$538,"3.3.1",E_vanilla_agent!$I$2:$I$538,1)/COUNTIF(E_vanilla_agent!$F$2:$F$538,"3.3.1"),"") -> 0.55555556
A62: 3.3.2 | B62: =COUNTIF(A_axe!$F$2:$F$538,"3.3.2") -> 18 | C62: =IFERROR(COUNTIFS(A_axe!$F$2:$F$538,"3.3.2",A_axe!$I$2:$I$538,1)/COUNTIF(A_axe!$F$2:$F$538,"3.3.2"),"") -> 0.33333333 | D62: =IFERROR(COUNTIFS(B_persona_llm!$F$2:$F$538,"3.3.2",B_persona_llm!$I$2:$I$538,1)/COUNTIF(B_persona_llm!$F$2:$F$538,"3.3.2"),"") -> 0.66666667 | E62: =IFERROR(COUNTIFS(C_persona_agent!$F$2:$F$538,"3.3.2",C_persona_agent!$I$2:$I$538,1)/COUNTIF(C_persona_agent!$F$2:$F$538,"3.3.2"),"") -> 0.61111111 | F62: =IFERROR(COUNTIFS(D_vanilla_llm!$F$2:$F$538,"3.3.2",D_vanilla_llm!$I$2:$I$538,1)/COUNTIF(D_vanilla_llm!$F$2:$F$538,"3.3.2"),"") -> 0.72222222 | G62: =IFERROR(COUNTIFS(E_vanilla_agent!$F$2:$F$538,"3.3.2",E_vanilla_agent!$I$2:$I$538,1)/COUNTIF(E_vanilla_agent!$F$2:$F$538,"3.3.2"),"") -> 0.66666667
A63: 4.1.2 | B63: =COUNTIF(A_axe!$F$2:$F$538,"4.1.2") -> 15 | C63: =IFERROR(COUNTIFS(A_axe!$F$2:$F$538,"4.1.2",A_axe!$I$2:$I$538,1)/COUNTIF(A_axe!$F$2:$F$538,"4.1.2"),"") -> 0.6 | D63: =IFERROR(COUNTIFS(B_persona_llm!$F$2:$F$538,"4.1.2",B_persona_llm!$I$2:$I$538,1)/COUNTIF(B_persona_llm!$F$2:$F$538,"4.1.2"),"") -> 0.4 | E63: =IFERROR(COUNTIFS(C_persona_agent!$F$2:$F$538,"4.1.2",C_persona_agent!$I$2:$I$538,1)/COUNTIF(C_persona_agent!$F$2:$F$538,"4.1.2"),"") -> 0.4 | F63: =IFERROR(COUNTIFS(D_vanilla_llm!$F$2:$F$538,"4.1.2",D_vanilla_llm!$I$2:$I$538,1)/COUNTIF(D_vanilla_llm!$F$2:$F$538,"4.1.2"),"") -> 0.4 | G63: =IFERROR(COUNTIFS(E_vanilla_agent!$F$2:$F$538,"4.1.2",E_vanilla_agent!$I$2:$I$538,1)/COUNTIF(E_vanilla_agent!$F$2:$F$538,"4.1.2"),"") -> 0.4

Sheet A_axe
A1: snippet_id | B1: condition | C1: condition_key | D1: model | E1: persona | F1: wcag_criterion | G1: expected | H1: evaluated | I1: correct | J1: repetition | K1: severity | L1: issue_count | M1: tool_call_count | N1: tools_called | O1: iteration_count | P1: total_time_seconds | Q1: input_tokens | R1: output_tokens | S1: testcase_title | T1: rule_id | U1: rule_name | V1: corpus_source | W1: rule_url | X1: html_path | Y1: overall_assessment | Z1: issues_detail
A2: 033e04cced5973596d9aa724feacb027d23b4c53 | B2: axe | C2: A | D2: n/a | E2: ade | F2: 2.1.1 | G2: inapplicable | H2: passed | I2: =IF(EXACT(G2,H2),1,0) -> 0 | J2: 0 | K2: N/A | L2: 0 | M2: 1 | N2: axe-core | O2: 1 | P2: 4.7 | S2: Inapplicable Example 2 | T2: akn7bn | U2: Iframe with interactive elements is not excluded from tab-order | W2: https://www.w3.org/WAI/content-assets/wcag-act-rules/testcases/akn7bn/033e04cced5973596d9aa724feacb027d23b4c53.html | X2: corpus1\ade\2.1.1\inapplicable\033e04cced5973596d9aa724feacb027d23b4c53.html | Y2: Found 2 rule violation(s) affecting 2 element(s).
A3: 033e04cced5973596d9aa724feacb027d23b4c53 | B3: axe | C3: A | D3: n/a | E3: ade | F3: 2.1.1 | G3: inapplicable | H3: passed | I3: =IF(EXACT(G3,H3),1,0) -> 0 | J3: 1 | K3: N/A | L3: 0 | M3: 1 | N3: axe-core | O3: 1 | P3: 4.48 | S3: Inapplicable Example 2 | T3: akn7bn | U3: Iframe with interactive elements is not excluded from tab-order | W3: https://www.w3.org/WAI/content-assets/wcag-act-rules/testcases/akn7bn/033e04cced5973596d9aa724feacb027d23b4c53.html | X3: corpus1\ade\2.1.1\inapplicable\033e04cced5973596d9aa724feacb027d23b4c53.html | Y3: Found 2 rule violation(s) affecting 2 element(s).
A4: 033e04cced5973596d9aa724feacb027d23b4c53 | B4: axe | C4: A | D4: n/a | E4: ade | F4: 2.1.1 | G4: inapplicable | H4: passed | I4: =IF(EXACT(G4,H4),1,0) -> 0 | J4: 2 | K4: N/A | L4: 0 | M4: 1 | N4: axe-core | O4: 1 | P4: 5 | S4: Inapplicable Example 2 | T4: akn7bn | U4: Iframe with interactive elements is not excluded from tab-order | W4: https://www.w3.org/WAI/content-assets/wcag-act-rules/testcases/akn7bn/033e04cced5973596d9aa724feacb027d23b4c53.html | X4: corpus1\ade\2.1.1\inapplicable\033e04cced5973596d9aa724feacb027d23b4c53.html | Y4: Found 2 rule violation(s) affecting 2 element(s).
A5: 17a371c470316dc29e424101065ebfe9f7b2e990 | B5: axe | C5: A | D5: n/a | E5: ade | F5: 2.1.1 | G5: inapplicable | H5: passed | I5: =IF(EXACT(G5,H5),1,0) -> 0 | J5: 0 | K5: N/A | L5: 0 | M5: 1 | N5: axe-core | O5: 1 | P5: 4.5 | S5: Inapplicable Example 5 | T5: akn7bn | U5: Iframe with interactive elements is not excluded from tab-order | W5: https://www.w3.org/WAI/content-assets/wcag-act-rules/testcases/akn7bn/17a371c470316dc29e424101065ebfe9f7b2e990.html | X5: corpus1\ade\2.1.1\inapplicable\17a371c470316dc29e424101065ebfe9f7b2e990.html | Y5: Found 2 rule violation(s) affecting 2 element(s).
A6: 17a371c470316dc29e424101065ebfe9f7b2e990 | B6: axe | C6: A | D6: n/a | E6: ade | F6: 2.1.1 | G6: inapplicable | H6: passed | I6: =IF(EXACT(G6,H6),1,0) -> 0 | J6: 1 | K6: N/A | L6: 0 | M6: 1 | N6: axe-core | O6: 1 | P6: 4.53 | S6: Inapplicable Example 5 | T6: akn7bn | U6: Iframe with interactive elements is not excluded from tab-order | W6: https://www.w3.org/WAI/content-assets/wcag-act-rules/testcases/akn7bn/17a371c470316dc29e424101065ebfe9f7b2e990.html | X6: corpus1\ade\2.1.1\inapplicable\17a371c470316dc29e424101065ebfe9f7b2e990.html | Y6: Found 2 rule violation(s) affecting 2 element(s).
A7: 17a371c470316dc29e424101065ebfe9f7b2e990 | B7: axe | C7: A | D7: n/a | E7: ade | F7: 2.1.1 | G7: inapplicable | H7: passed | I7: =IF(EXACT(G7,H7),1,0) -> 0 | J7: 2 | K7: N/A | L7: 0 | M7: 1 | N7: axe-core | O7: 1 | P7: 3.53 | S7: Inapplicable Example 5 | T7: akn7bn | U7: Iframe with interactive elements is not excluded from tab-order | W7: https://www.w3.org/WAI/content-assets/wcag-act-rules/testcases/akn7bn/17a371c470316dc29e424101065ebfe9f7b2e990.html | X7: corpus1\ade\2.1.1\inapplicable\17a371c470316dc29e424101065ebfe9f7b2e990.html | Y7: Found 2 rule violation(s) affecting 2 element(s).
A8: 1e3939d9f8e0f78f9c564ec6feb12cc5635c0acb | B8: axe | C8: A | D8: n/a | E8: ade | F8: 2.1.1 | G8: passed | H8: passed | I8: =IF(EXACT(G8,H8),1,0) -> 1 | J8: 0 | K8: N/A | L8: 0 | M8: 1 | N8: axe-core | O8: 1 | P8: 5.64 | S8: Passed Example 1 | T8: akn7bn | U8: Iframe with interactive elements is not excluded from tab-order | W8: https://www.w3.org/WAI/content-assets/wcag-act-rules/testcases/akn7bn/1e3939d9f8e0f78f9c564ec6feb12cc5635c0acb.html | X8: corpus1\ade\2.1.1\passed\1e3939d9f8e0f78f9c564ec6feb12cc5635c0acb.html | Y8: Found 3 rule violation(s) affecting 3 element(s).
A9: 1e3939d9f8e0f78f9c564ec6feb12cc5635c0acb | B9: axe | C9: A | D9: n/a | E9: ade | F9: 2.1.1 | G9: passed | H9: passed | I9: =IF(EXACT(G9,H9),1,0) -> 1 | J9: 1 | K9: N/A | L9: 0 | M9: 1 | N9: axe-core | O9: 1 | P9: 4.67 | S9: Passed Example 1 | T9: akn7bn | U9: Iframe with interactive elements is not excluded from tab-order | W9: https://www.w3.org/WAI/content-assets/wcag-act-rules/testcases/akn7bn/1e3939d9f8e0f78f9c564ec6feb12cc5635c0acb.html | X9: corpus1\ade\2.1.1\passed\1e3939d9f8e0f78f9c564ec6feb12cc5635c0acb.html | Y9: Found 3 rule violation(s) affecting 3 element(s).
A10: 1e3939d9f8e0f78f9c564ec6feb12cc5635c0acb | B10: axe | C10: A | D10: n/a | E10: ade | F10: 2.1.1 | G10: passed | H10: passed | I10: =IF(EXACT(G10,H10),1,0) -> 1 | J10: 2 | K10: N/A | L10: 0 | M10: 1 | N10: axe-core | O10: 1 | P10: 4.45 | S10: Passed Example 1 | T10: akn7bn | U10: Iframe with interactive elements is not excluded from tab-order | W10: https://www.w3.org/WAI/content-assets/wcag-act-rules/testcases/akn7bn/1e3939d9f8e0f78f9c564ec6feb12cc5635c0acb.html | X10: corpus1\ade\2.1.1\passed\1e3939d9f8e0f78f9c564ec6feb12cc5635c0acb.html | Y10: Found 3 rule violation(s) affecting 3 element(s).
A11: 270a22a8e4ce4d9f073e1484a0d807705207a1d7 | B11: axe | C11: A | D11: n/a | E11: ade | F11: 2.1.1 | G11: passed | H11: passed | I11: =IF(EXACT(G11,H11),1,0) -> 1 | J11: 0 | K11: N/A | L11: 0 | M11: 1 | N11: axe-core | O11: 1 | P11: 4.24 | S11: Passed Example 2 | T11: 0ssw9k | U11: Scrollable content can be reached with sequential focus navigation | W11: https://www.w3.org/WAI/content-assets/wcag-act-rules/testcases/0ssw9k/270a22a8e4ce4d9f073e1484a0d807705207a1d7.html | X11: corpus1\ade\2.1.1\passed\270a22a8e4ce4d9f073e1484a0d807705207a1d7.html | Y11: Found 2 rule violation(s) affecting 2 element(s).
A12: 270a22a8e4ce4d9f073e1484a0d807705207a1d7 | B12: axe | C12: A | D12: n/a | E12: ade | F12: 2.1.1 | G12: passed | H12: passed | I12: =IF(EXACT(G12,H12),1,0) -> 1 | J12: 1 | K12: N/A | L12: 0 | M12: 1 | N12: axe-core | O12: 1 | P12: 4.17 | S12: Passed Example 2 | T12: 0ssw9k | U12: Scrollable content can be reached with sequential focus navigation | W12: https://www.w3.org/WAI/content-assets/wcag-act-rules/testcases/0ssw9k/270a22a8e4ce4d9f073e1484a0d807705207a1d7.html | X12: corpus1\ade\2.1.1\passed\270a22a8e4ce4d9f073e1484a0d807705207a1d7.html | Y12: Found 2 rule violation(s) affecting 2 element(s).
A13: 270a22a8e4ce4d9f073e1484a0d807705207a1d7 | B13: axe | C13: A | D13: n/a | E13: ade | F13: 2.1.1 | G13: passed | H13: passed | I13: =IF(EXACT(G13,H13),1,0) -> 1 | J13: 2 | K13: N/A | L13: 0 | M13: 1 | N13: axe-core | O13: 1 | P13: 4.12 | S13: Passed Example 2 | T13: 0ssw9k | U13: Scrollable content can be reached with sequential focus navigation | W13: https://www.w3.org/WAI/content-assets/wcag-act-rules/testcases/0ssw9k/270a22a8e4ce4d9f073e1484a0d807705207a1d7.html | X13: corpus1\ade\2.1.1\passed\270a22a8e4ce4d9f073e1484a0d807705207a1d7.html | Y13: Found 2 rule violation(s) affecting 2 element(s).
A14: 5fa34d0a7eea03109cd12c0e7c21fce793c268db | B14: axe | C14: A | D14: n/a | E14: ade | F14: 2.1.1 | G14: failed | H14: failed | I14: =IF(EXACT(G14,H14),1,0) -> 1 | J14: 0 | K14: serious | L14: 1 | M14: 1 | N14: axe-core | O14: 1 | P14: 4.66 | S14: Failed Example 1 | T14: 0ssw9k | U14: Scrollable content can be reached with sequential focus navigation | W14: https://www.w3.org/WAI/content-assets/wcag-act-rules/testcases/0ssw9k/5fa34d0a7eea03109cd12c0e7c21fce793c268db.html | X14: corpus1\ade\2.1.1\failed\5fa34d0a7eea03109cd12c0e7c21fce793c268db.html | Y14: Found 3 rule violation(s) affecting 3 element(s). | Z14: [wcag2a, wcag211] Ensure elements that have scrollable content are accessible by keyboard Scrollable region must have keyboard access
A15: 5fa34d0a7eea03109cd12c0e7c21fce793c268db | B15: axe | C15: A | D15: n/a | E15: ade | F15: 2.1.1 | G15: failed | H15: failed | I15: =IF(EXACT(G15,H15),1,0) -> 1 | J15: 1 | K15: serious | L15: 1 | M15: 1 | N15: axe-core | O15: 1 | P15: 4.16 | S15: Failed Example 1 | T15: 0ssw9k | U15: Scrollable content can be reached with sequential focus navigation | W15: https://www.w3.org/WAI/content-assets/wcag-act-rules/testcases/0ssw9k/5fa34d0a7eea03109cd12c0e7c21fce793c268db.html | X15: corpus1\ade\2.1.1\failed\5fa34d0a7eea03109cd12c0e7c21fce793c268db.html | Y15: Found 3 rule violation(s) affecting 3 element(s). | Z15: [wcag2a, wcag211] Ensure elements that have scrollable content are accessible by keyboard Scrollable region must have keyboard access
A16: 5fa34d0a7eea03109cd12c0e7c21fce793c268db | B16: axe | C16: A | D16: n/a | E16: ade | F16: 2.1.1 | G16: failed | H16: failed | I16: =IF(EXACT(G16,H16),1,0) -> 1 | J16: 2 | K16: serious | L16: 1 | M16: 1 | N16: axe-core | O16: 1 | P16: 4.15 | S16: Failed Example 1 | T16: 0ssw9k | U16: Scrollable content can be reached with sequential focus navigation | W16: https://www.w3.org/WAI/content-assets/wcag-act-rules/testcases/0ssw9k/5fa34d0a7eea03109cd12c0e7c21fce793c268db.html | X16: corpus1\ade\2.1.1\failed\5fa34d0a7eea03109cd12c0e7c21fce793c268db.html | Y16: Found 3 rule violation(s) affecting 3 element(s). | Z16: [wcag2a, wcag211] Ensure elements that have scrollable content are accessible by keyboard Scrollable region must have keyboard access
A17: 62673162e22ee1e95e962522b1d1c3b549dbfc49 | B17: axe | C17: A | D17: n/a | E17: ade | F17: 2.1.1 | G17: failed | H17: passed | I17: =IF(EXACT(G17,H17),1,0) -> 0 | J17: 0 | K17: N/A | L17: 0 | M17: 1 | N17: axe-core | O17: 1 | P17: 5.24 | S17: Failed Example 1 | T17: akn7bn | U17: Iframe with interactive elements is not excluded from tab-order | W17: https://www.w3.org/WAI/content-assets/wcag-act-rules/testcases/akn7bn/62673162e22ee1e95e962522b1d1c3b549dbfc49.html | X17: corpus1\ade\2.1.1\failed\62673162e22ee1e95e962522b1d1c3b549dbfc49.html | Y17: Found 2 rule violation(s) affecting 2 element(s).
A18: 62673162e22ee1e95e962522b1d1c3b549dbfc49 | B18: axe | C18: A | D18: n/a | E18: ade | F18: 2.1.1 | G18: failed | H18: passed | I18: =IF(EXACT(G18,H18),1,0) -> 0 | J18: 1 | K18: N/A | L18: 0 | M18: 1 | N18: axe-core | O18: 1 | P18: 5.33 | S18: Failed Example 1 | T18: akn7bn | U18: Iframe with interactive elements is not excluded from tab-order | W18: https://www.w3.org/WAI/content-assets/wcag-act-rules/testcases/akn7bn/62673162e22ee1e95e962522b1d1c3b549dbfc49.html | X18: corpus1\ade\2.1.1\failed\62673162e22ee1e95e962522b1d1c3b549dbfc49.html | Y18: Found 2 rule violation(s) affecting 2 element(s).
A19: 62673162e22ee1e95e962522b1d1c3b549dbfc49 | B19: axe | C19: A | D19: n/a | E19: ade | F19: 2.1.1 | G19: failed | H19: passed | I19: =IF(EXACT(G19,H19),1,0) -> 0 | J19: 2 | K19: N/A | L19: 0 | M19: 1 | N19: axe-core | O19: 1 | P19: 5.2 | S19: Failed Example 1 | T19: akn7bn | U19: Iframe with interactive elements is not excluded from tab-order | W19: https://www.w3.org/WAI/content-assets/wcag-act-rules/testcases/akn7bn/62673162e22ee1e95e962522b1d1c3b549dbfc49.html | X19: corpus1\ade\2.1.1\failed\62673162e22ee1e95e962522b1d1c3b549dbfc49.html | Y19: Found 2 rule violation(s) affecting 2 element(s).
A20: 0bf30cdf02ff26dfca5aa705b7023227da221e05 | B20: axe | C20: A | D20: n/a | E20: ade | F20: 2.2.1 | G20: inapplicable | H20: passed | I20: =IF(EXACT(G20,H20),1,0) -> 0 | J20: 0 | K20: N/A | L20: 0 | M20: 1 | N20: axe-core | O20: 1 | P20: 4.62 | S20: Inapplicable Example 7 | T20: bc659a | U20: Meta element has no refresh delay | W20: https://www.w3.org/WAI/content-assets/wcag-act-rules/testcases/bc659a/0bf30cdf02ff26dfca5aa705b7023227da221e05.html | X20: corpus1\ade\2.2.1\inapplicable\0bf30cdf02ff26dfca5aa705b7023227da221e05.html | Y20: Found 4 rule violation(s) affecting 4 element(s).
A21: 0bf30cdf02ff26dfca5aa705b7023227da221e05 | B21: axe | C21: A | D21: n/a | E21: ade | F21: 2.2.1 | G21: inapplicable | H21: passed | I21: =IF(EXACT(G21,H21),1,0) -> 0 | J21: 1 | K21: N/A | L21: 0 | M21: 1 | N21: axe-core | O21: 1 | P21: 4.54 | S21: Inapplicable Example 7 | T21: bc659a | U21: Meta element has no refresh delay | W21: https://www.w3.org/WAI/content-assets/wcag-act-rules/testcases/bc659a/0bf30cdf02ff26dfca5aa705b7023227da221e05.html | X21: corpus1\ade\2.2.1\inapplicable\0bf30cdf02ff26dfca5aa705b7023227da221e05.html | Y21: Found 4 rule violation(s) affecting 4 element(s).
A22: 0bf30cdf02ff26dfca5aa705b7023227da221e05 | B22: axe | C22: A | D22: n/a | E22: ade | F22: 2.2.1 | G22: inapplicable | H22: passed | I22: =IF(EXACT(G22,H22),1,0) -> 0 | J22: 2 | K22: N/A | L22: 0 | M22: 1 | N22: axe-core | O22: 1 | P22: 4.31 | S22: Inapplicable Example 7 | T22: bc659a | U22: Meta element has no refresh delay | W22: https://www.w3.org/WAI/content-assets/wcag-act-rules/testcases/bc659a/0bf30cdf02ff26dfca5aa705b7023227da221e05.html | X22: corpus1\ade\2.2.1\inapplicable\0bf30cdf02ff26dfca5aa705b7023227da221e05.html | Y22: Found 4 rule violation(s) affecting 4 element(s).
A23: 48a600254c0883cd5a72471420b1ac5a532ca6c3 | B23: axe | C23: A | D23: n/a | E23: ade | F23: 2.2.1 | G23: inapplicable | H23: passed | I23: =IF(EXACT(G23,H23),1,0) -> 0 | J23: 0 | K23: N/A | L23: 0 | M23: 1 | N23: axe-core | O23: 1 | P23: 4.61 | S23: Inapplicable Example 1 | T23: bc659a | U23: Meta element has no refresh delay | W23: https://www.w3.org/WAI/content-assets/wcag-act-rules/testcases/bc659a/48a600254c0883cd5a72471420b1ac5a532ca6c3.html | X23: corpus1\ade\2.2.1\inapplicable\48a600254c0883cd5a72471420b1ac5a532ca6c3.html | Y23: Found 4 rule violation(s) affecting 4 element(s).
A24: 48a600254c0883cd5a72471420b1ac5a532ca6c3 | B24: axe | C24: A | D24: n/a | E24: ade | F24: 2.2.1 | G24: inapplicable | H24: passed | I24: =IF(EXACT(G24,H24),1,0) -> 0 | J24: 1 | K24: N/A | L24: 0 | M24: 1 | N24: axe-core | O24: 1 | P24: 4.87 | S24: Inapplicable Example 1 | T24: bc659a | U24: Meta element has no refresh delay | W24: https://www.w3.org/WAI/content-assets/wcag-act-rules/testcases/bc659a/48a600254c0883cd5a72471420b1ac5a532ca6c3.html | X24: corpus1\ade\2.2.1\inapplicable\48a600254c0883cd5a72471420b1ac5a532ca6c3.html | Y24: Found 4 rule violation(s) affecting 4 element(s).
A25: 48a600254c0883cd5a72471420b1ac5a532ca6c3 | B25: axe | C25: A | D25: n/a | E25: ade | F25: 2.2.1 | G25: inapplicable | H25: passed | I25: =IF(EXACT(G25,H25),1,0) -> 0 | J25: 2 | K25: N/A | L25: 0 | M25: 1 | N25: axe-core | O25: 1 | P25: 4.78 | S25: Inapplicable Example 1 | T25: bc659a | U25: Meta element has no refresh delay | W25: https://www.w3.org/WAI/content-assets/wcag-act-rules/testcases/bc659a/48a600254c0883cd5a72471420b1ac5a532ca6c3.html | X25: corpus1\ade\2.2.1\inapplicable\48a600254c0883cd5a72471420b1ac5a532ca6c3.html | Y25: Found 4 rule violation(s) affecting 4 element(s).
A26: 49d79a4e4e4a994a8eb7cf2eaf59c99d2251cac5 | B26: axe | C26: A | D26: n/a | E26: ade | F26: 2.2.1 | G26: passed | H26: passed | I26: =IF(EXACT(G26,H26),1,0) -> 1 | J26: 0 | K26: N/A | L26: 0 | M26: 1 | N26: axe-core | O26: 1 | P26: 5.81 | S26: Passed Example 1 | T26: bc659a | U26: Meta element has no refresh delay | W26: https://www.w3.org/WAI/content-assets/wcag-act-rules/testcases/bc659a/49d79a4e4e4a994a8eb7cf2eaf59c99d2251cac5.html | X26: corpus1\ade\2.2.1\passed\49d79a4e4e4a994a8eb7cf2eaf59c99d2251cac5.html | Y26: Found 1 rule violation(s) affecting 1 element(s).
A27: 49d79a4e4e4a994a8eb7cf2eaf59c99d2251cac5 | B27: axe | C27: A | D27: n/a | E27: ade | F27: 2.2.1 | G27: passed | H27: passed | I27: =IF(EXACT(G27,H27),1,0) -> 1 | J27: 1 | K27: N/A | L27: 0 | M27: 1 | N27: axe-core | O27: 1 | P27: 5.82 | S27: Passed Example 1 | T27: bc659a | U27: Meta element has no refresh delay | W27: https://www.w3.org/WAI/content-assets/wcag-act-rules/testcases/bc659a/49d79a4e4e4a994a8eb7cf2eaf59c99d2251cac5.html | X27: corpus1\ade\2.2.1\passed\49d79a4e4e4a994a8eb7cf2eaf59c99d2251cac5.html | Y27: Found 1 rule violation(s) affecting 1 element(s).
A28: 49d79a4e4e4a994a8eb7cf2eaf59c99d2251cac5 | B28: axe | C28: A | D28: n/a | E28: ade | F28: 2.2.1 | G28: passed | H28: passed | I28: =IF(EXACT(G28,H28),1,0) -> 1 | J28: 2 | K28: N/A | L28: 0 | M28: 1 | N28: axe-core | O28: 1 | P28: 6.12 | S28: Passed Example 1 | T28: bc659a | U28: Meta element has no refresh delay | W28: https://www.w3.org/WAI/content-assets/wcag-act-rules/testcases/bc659a/49d79a4e4e4a994a8eb7cf2eaf59c99d2251cac5.html | X28: corpus1\ade\2.2.1\passed\49d79a4e4e4a994a8eb7cf2eaf59c99d2251cac5.html | Y28: Found 1 rule violation(s) affecting 1 element(s).
A29: 56857820788db21498e95a5cbba65d59a9a2b892 | B29: axe | C29: A | D29: n/a | E29: ade | F29: 2.2.1 | G29: failed | H29: failed | I29: =IF(EXACT(G29,H29),1,0) -> 1 | J29: 0 | K29: critical | L29: 1 | M29: 1 | N29: axe-core | O29: 1 | P29: 3.51 | S29: Failed Example 1 | T29: bc659a | U29: Meta element has no refresh delay | W29: https://www.w3.org/WAI/content-assets/wcag-act-rules/testcases/bc659a/56857820788db21498e95a5cbba65d59a9a2b892.html | X29: corpus1\ade\2.2.1\failed\56857820788db21498e95a5cbba65d59a9a2b892.html | Y29: Found 5 rule violation(s) affecting 5 element(s). | Z29: [wcag2a, wcag221] Ensures <meta http-equiv="refresh"> is not used for delayed refresh Delayed refresh under 20 hours must not be used
A30: 56857820788db21498e95a5cbba65d59a9a2b892 | B30: axe | C30: A | D30: n/a | E30: ade | F30: 2.2.1 | G30: failed | H30: failed | I30: =IF(EXACT(G30,H30),1,0) -> 1 | J30: 1 | K30: critical | L30: 1 | M30: 1 | N30: axe-core | O30: 1 | P30: 3.51 | S30: Failed Example 1 | T30: bc659a | U30: Meta element has no refresh delay | W30: https://www.w3.org/WAI/content-assets/wcag-act-rules/testcases/bc659a/56857820788db21498e95a5cbba65d59a9a2b892.html | X30: corpus1\ade\2.2.1\failed\56857820788db21498e95a5cbba65d59a9a2b892.html | Y30: Found 5 rule violation(s) affecting 5 element(s). | Z30: [wcag2a, wcag221] Ensures <meta http-equiv="refresh"> is not used for delayed refresh Delayed refresh under 20 hours must not be used
A31: 56857820788db21498e95a5cbba65d59a9a2b892 | B31: axe | C31: A | D31: n/a | E31: ade | F31: 2.2.1 | G31: failed | H31: failed | I31: =IF(EXACT(G31,H31),1,0) -> 1 | J31: 2 | K31: critical | L31: 1 | M31: 1 | N31: axe-core | O31: 1 | P31: 3.51 | S31: Failed Example 1 | T31: bc659a | U31: Meta element has no refresh delay | W31: https://www.w3.org/WAI/content-assets/wcag-act-rules/testcases/bc659a/56857820788db21498e95a5cbba65d59a9a2b892.html | X31: corpus1\ade\2.2.1\failed\56857820788db21498e95a5cbba65d59a9a2b892.html | Y31: Found 5 rule violation(s) affecting 5 element(s). | Z31: [wcag2a, wcag221] Ensures <meta http-equiv="refresh"> is not used for delayed refresh Delayed refresh under 20 hours must not be used
A32: 5d4d5b214459c8a0779600ab39a5668003271c62 | B32: axe | C32: A | D32: n/a | E32: ade | F32: 2.2.1 | G32: failed | H32: failed | I32: =IF(EXACT(G32,H32),1,0) -> 1 | J32: 0 | K32: critical | L32: 1 | M32: 1 | N32: axe-core | O32: 1 | P32: 3.51 | S32: Failed Example 4 | T32: bc659a | U32: Meta element has no refresh delay | W32: https://www.w3.org/WAI/content-assets/wcag-act-rules/testcases/bc659a/5d4d5b214459c8a0779600ab39a5668003271c62.html | X32: corpus1\ade\2.2.1\failed\5d4d5b214459c8a0779600ab39a5668003271c62.html | Y32: Found 5 rule violation(s) affecting 5 element(s). | Z32: [wcag2a, wcag221] Ensures <meta http-equiv="refresh"> is not used for delayed refresh Delayed refresh under 20 hours must not be used
A33: 5d4d5b214459c8a0779600ab39a5668003271c62 | B33: axe | C33: A | D33: n/a | E33: ade | F33: 2.2.1 | G33: failed | H33: failed | I33: =IF(EXACT(G33,H33),1,0) -> 1 | J33: 1 | K33: critical | L33: 1 | M33: 1 | N33: axe-core | O33: 1 | P33: 3.51 | S33: Failed Example 4 | T33: bc659a | U33: Meta element has no refresh delay | W33: https://www.w3.org/WAI/content-assets/wcag-act-rules/testcases/bc659a/5d4d5b214459c8a0779600ab39a5668003271c62.html | X33: corpus1\ade\2.2.1\failed\5d4d5b214459c8a0779600ab39a5668003271c62.html | Y33: Found 5 rule violation(s) affecting 5 element(s). | Z33: [wcag2a, wcag221] Ensures <meta http-equiv="refresh"> is not used for delayed refresh Delayed refresh under 20 hours must not be used
A34: 5d4d5b214459c8a0779600ab39a5668003271c62 | B34: axe | C34: A | D34: n/a | E34: ade | F34: 2.2.1 | G34: failed | H34: failed | I34: =IF(EXACT(G34,H34),1,0) -> 1 | J34: 2 | K34: critical | L34: 1 | M34: 1 | N34: axe-core | O34: 1 | P34: 3.51 | S34: Failed Example 4 | T34: bc659a | U34: Meta element has no refresh delay | W34: https://www.w3.org/WAI/content-assets/wcag-act-rules/testcases/bc659a/5d4d5b214459c8a0779600ab39a5668003271c62.html | X34: corpus1\ade\2.2.1\failed\5d4d5b214459c8a0779600ab39a5668003271c62.html | Y34: Found 5 rule violation(s) affecting 5 element(s). | Z34: [wcag2a, wcag221] Ensures <meta http-equiv="refresh"> is not used for delayed refresh Delayed refresh under 20 hours must not be used
A35: b5ca868de7980f6944142ecdb849f47ad2cdfb5c | B35: axe | C35: A | D35: n/a | E35: ade | F35: 2.2.1 | G35: passed | H35: passed | I35: =IF(EXACT(G35,H35),1,0) -> 1 | J35: 0 | K35: N/A | L35: 0 | M35: 1 | N35: axe-core | O35: 1 | P35: 3.6 | S35: Passed Example 3 | T35: bc659a | U35: Meta element has no refresh delay | W35: https://www.w3.org/WAI/content-assets/wcag-act-rules/testcases/bc659a/b5ca868de7980f6944142ecdb849f47ad2cdfb5c.html | X35: corpus1\ade\2.2.1\passed\b5ca868de7980f6944142ecdb849f47ad2cdfb5c.html | Y35: Found 3 rule violation(s) affecting 3 element(s).
A36: b5ca868de7980f6944142ecdb849f47ad2cdfb5c | B36: axe | C36: A | D36: n/a | E36: ade | F36: 2.2.1 | G36: passed | H36: passed | I36: =IF(EXACT(G36,H36),1,0) -> 1 | J36: 1 | K36: N/A | L36: 0 | M36: 1 | N36: axe-core | O36: 1 | P36: 3.53 | S36: Passed Example 3 | T36: bc659a | U36: Meta element has no refresh delay | W36: https://www.w3.org/WAI/content-assets/wcag-act-rules/testcases/bc659a/b5ca868de7980f6944142ecdb849f47ad2cdfb5c.html | X36: corpus1\ade\2.2.1\passed\b5ca868de7980f6944142ecdb849f47ad2cdfb5c.html | Y36: Found 3 rule violation(s) affecting 3 element(s).
A37: b5ca868de7980f6944142ecdb849f47ad2cdfb5c | B37: axe | C37: A | D37: n/a | E37: ade | F37: 2.2.1 | G37: passed | H37: passed | I37: =IF(EXACT(G37,H37),1,0) -> 1 | J37: 2 | K37: N/A | L37: 0 | M37: 1 | N37: axe-core | O37: 1 | P37: 3.57 | S37: Passed Example 3 | T37: bc659a | U37: Meta element has no refresh delay | W37: https://www.w3.org/WAI/content-assets/wcag-act-rules/testcases/bc659a/b5ca868de7980f6944142ecdb849f47ad2cdfb5c.html | X37: corpus1\ade\2.2.1\passed\b5ca868de7980f6944142ecdb849f47ad2cdfb5c.html | Y37: Found 3 rule violation(s) affecting 3 element(s).
A38: ha-2-4-3-fail-01-positive-tabindex | B38: axe | C38: A | D38: n/a | E38: ade | F38: 2.4.3 | G38: failed | H38: passed | I38: =IF(EXACT(G38,H38),1,0) -> 0 | J38: 0 | K38: N/A | L38: 0 | M38: 1 | N38: axe-core | O38: 1 | P38: 4.8 | S38: Positive tabindex values disrupt natural focus order | V38: hand-authored from W3C Understanding | X38: corpus1\ade\2.4.3\failed\ha-2-4-3-fail-01-positive-tabindex.html | Y38: Found 1 rule violation(s) affecting 4 element(s).
A39: ha-2-4-3-fail-01-positive-tabindex | B39: axe | C39: A | D39: n/a | E39: ade | F39: 2.4.3 | G39: failed | H39: passed | I39: =IF(EXACT(G39,H39),1,0) -> 0 | J39: 1 | K39: N/A | L39: 0 | M39: 1 | N39: axe-core | O39: 1 | P39: 4.98 | S39: Positive tabindex values disrupt natural focus order | V39: hand-authored from W3C Understanding | X39: corpus1\ade\2.4.3\failed\ha-2-4-3-fail-01-positive-tabindex.html | Y39: Found 1 rule violation(s) affecting 4 element(s).
A40: ha-2-4-3-fail-01-positive-tabindex | B40: axe | C40: A | D40: n/a | E40: ade | F40: 2.4.3 | G40: failed | H40: passed | I40: =IF(EXACT(G40,H40),1,0) -> 0 | J40: 2 | K40: N/A | L40: 0 | M40: 1 | N40: axe-core | O40: 1 | P40: 4.72 | S40: Positive tabindex values disrupt natural focus order | V40: hand-authored from W3C Understanding | X40: corpus1\ade\2.4.3\failed\ha-2-4-3-fail-01-positive-tabindex.html | Y40: Found 1 rule violation(s) affecting 4 element(s).
A41: ha-2-4-3-fail-02-visual-reorder-css | B41: axe | C41: A | D41: n/a | E41: ade | F41: 2.4.3 | G41: failed | H41: passed | I41: =IF(EXACT(G41,H41),1,0) -> 0 | J41: 0 | K41: N/A | L41: 0 | M41: 1 | N41: axe-core | O41: 1 | P41: 4.89 | S41: CSS flex order does not match DOM order | V41: hand-authored from W3C Understanding | X41: corpus1\ade\2.4.3\failed\ha-2-4-3-fail-02-visual-reorder-css.html | Y41: Found 0 rule violation(s) affecting 0 element(s).
A42: ha-2-4-3-fail-02-visual-reorder-css | B42: axe | C42: A | D42: n/a | E42: ade | F42: 2.4.3 | G42: failed | H42: passed | I42: =IF(EXACT(G42,H42),1,0) -> 0 | J42: 1 | K42: N/A | L42: 0 | M42: 1 | N42: axe-core | O42: 1 | P42: 4.51 | S42: CSS flex order does not match DOM order | V42: hand-authored from W3C Understanding | X42: corpus1\ade\2.4.3\failed\ha-2-4-3-fail-02-visual-reorder-css.html | Y42: Found 0 rule violation(s) affecting 0 element(s).
A43: ha-2-4-3-fail-02-visual-reorder-css | B43: axe | C43: A | D43: n/a | E43: ade | F43: 2.4.3 | G43: failed | H43: passed | I43: =IF(EXACT(G43,H43),1,0) -> 0 | J43: 2 | K43: N/A | L43: 0 | M43: 1 | N43: axe-core | O43: 1 | P43: 4.86 | S43: CSS flex order does not match DOM order | V43: hand-authored from W3C Understanding | X43: corpus1\ade\2.4.3\failed\ha-2-4-3-fail-02-visual-reorder-css.html | Y43: Found 0 rule violation(s) affecting 0 element(s).
A44: ha-2-4-3-inap-01-static-content | B44: axe | C44: A | D44: n/a | E44: ade | F44: 2.4.3 | G44: inapplicable | H44: passed | I44: =IF(EXACT(G44,H44),1,0) -> 0 | J44: 0 | K44: N/A | L44: 0 | M44: 1 | N44: axe-core | O44: 1 | P44: 4.55 | S44: Page has no focusable elements | V44: hand-authored from W3C Understanding | X44: corpus1\ade\2.4.3\inapplicable\ha-2-4-3-inap-01-static-content.html | Y44: Found 0 rule violation(s) affecting 0 element(s).
A45: ha-2-4-3-inap-01-static-content | B45: axe | C45: A | D45: n/a | E45: ade | F45: 2.4.3 | G45: inapplicable | H45: passed | I45: =IF(EXACT(G45,H45),1,0) -> 0 | J45: 1 | K45: N/A | L45: 0 | M45: 1 | N45: axe-core | O45: 1 | P45: 4.64 | S45: Page has no focusable elements | V45: hand-authored from W3C Understanding | X45: corpus1\ade\2.4.3\inapplicable\ha-2-4-3-inap-01-static-content.html | Y45: Found 0 rule violation(s) affecting 0 element(s).
A46: ha-2-4-3-inap-01-static-content | B46: axe | C46: A | D46: n/a | E46: ade | F46: 2.4.3 | G46: inapplicable | H46: passed | I46: =IF(EXACT(G46,H46),1,0) -> 0 | J46: 2 | K46: N/A | L46: 0 | M46: 1 | N46: axe-core | O46: 1 | P46: 5.04 | S46: Page has no focusable elements | V46: hand-authored from W3C Understanding | X46: corpus1\ade\2.4.3\inapplicable\ha-2-4-3-inap-01-static-content.html | Y46: Found 0 rule violation(s) affecting 0 element(s).
A47: ha-2-4-3-inap-02-single-interactive | B47: axe | C47: A | D47: n/a | E47: ade | F47: 2.4.3 | G47: inapplicable | H47: passed | I47: =IF(EXACT(G47,H47),1,0) -> 0 | J47: 0 | K47: N/A | L47: 0 | M47: 1 | N47: axe-core | O47: 1 | P47: 4.51 | S47: Page has only one focusable element | V47: hand-authored from W3C Understanding | X47: corpus1\ade\2.4.3\inapplicable\ha-2-4-3-inap-02-single-interactive.html | Y47: Found 0 rule violation(s) affecting 0 element(s).
A48: ha-2-4-3-inap-02-single-interactive | B48: axe | C48: A | D48: n/a | E48: ade | F48: 2.4.3 | G48: inapplicable | H48: passed | I48: =IF(EXACT(G48,H48),1,0) -> 0 | J48: 1 | K48: N/A | L48: 0 | M48: 1 | N48: axe-core | O48: 1 | P48: 4.44 | S48: Page has only one focusable element | V48: hand-authored from W3C Understanding | X48: corpus1\ade\2.4.3\inapplicable\ha-2-4-3-inap-02-single-interactive.html | Y48: Found 0 rule violation(s) affecting 0 element(s).
A49: ha-2-4-3-inap-02-single-interactive | B49: axe | C49: A | D49: n/a | E49: ade | F49: 2.4.3 | G49: inapplicable | H49: passed | I49: =IF(EXACT(G49,H49),1,0) -> 0 | J49: 2 | K49: N/A | L49: 0 | M49: 1 | N49: axe-core | O49: 1 | P49: 4.66 | S49: Page has only one focusable element | V49: hand-authored from W3C Understanding | X49: corpus1\ade\2.4.3\inapplicable\ha-2-4-3-inap-02-single-interactive.html | Y49: Found 0 rule violation(s) affecting 0 element(s).
... A55: ha-2-4-3-pass-02-modal-focus-trap | B55: axe | C55: A | D55: n/a | E55: ade | F55: 2.4.3 | G55: passed | H55: passed | I55: =IF(EXACT(G55,H55),1,0) -> 1 | J55: 2 | K55: N/A | L55: 0 | M55: 1 | N55: axe-core | O55: 1 | P55: 4.77 | S55: Modal dialog keeps focus inside the dialog | V55: hand-authored from W3C Understanding | X55: corpus1\ade\2.4.3\passed\ha-2-4-3-pass-02-modal-focus-trap.html | Y55: Found 0 rule violation(s) affecting 0 element(s).
A56: 52be6331dc0978990a8b806a9a4a84bf738a43e1 | B56: axe | C56: A | D56: n/a | E56: ade | F56: 2.4.7 | G56: passed | H56: passed | I56: =IF(EXACT(G56,H56),1,0) -> 1 | J56: 0 | K56: N/A | L56: 0 | M56: 1 | N56: axe-core | O56: 1 | P56: 4.77 | S56: Passed Example 1 | T56: oj04fd | U56: Element in sequential focus order has visible focus | W56: https://www.w3.org/WAI/content-assets/wcag-act-rules/testcases/oj04fd/52be6331dc0978990a8b806a9a4a84bf738a43e1.html | X56: corpus1\ade\2.4.7\passed\52be6331dc0978990a8b806a9a4a84bf738a43e1.html | Y56: Found 3 rule violation(s) affecting 3 element(s).
A57: 52be6331dc0978990a8b806a9a4a84bf738a43e1 | B57: axe | C57: A | D57: n/a | E57: ade | F57: 2.4.7 | G57: passed | H57: passed | I57: =IF(EXACT(G57,H57),1,0) -> 1 | J57: 1 | K57: N/A | L57: 0 | M57: 1 | N57: axe-core | O57: 1 | P57: 4.67 | S57: Passed Example 1 | T57: oj04fd | U57: Element in sequential focus order has visible focus | W57: https://www.w3.org/WAI/content-assets/wcag-act-rules/testcases/oj04fd/52be6331dc0978990a8b806a9a4a84bf738a43e1.html | X57: corpus1\ade\2.4.7\passed\52be6331dc0978990a8b806a9a4a84bf738a43e1.html | Y57: Found 3 rule violation(s) affecting 3 element(s).
A58: 52be6331dc0978990a8b806a9a4a84bf738a43e1 | B58: axe | C58: A | D58: n/a | E58: ade | F58: 2.4.7 | G58: passed | H58: passed | I58: =IF(EXACT(G58,H58),1,0) -> 1 | J58: 2 | K58: N/A | L58: 0 | M58: 1 | N58: axe-core | O58: 1 | P58: 4.79 | S58: Passed Example 1 | T58: oj04fd | U58: Element in sequential focus order has visible focus | W58: https://www.w3.org/WAI/content-assets/wcag-act-rules/testcases/oj04fd/52be6331dc0978990a8b806a9a4a84bf738a43e1.html | X58: corpus1\ade\2.4.7\passed\52be6331dc0978990a8b806a9a4a84bf738a43e1.html | Y58: Found 3 rule violation(s) affecting 3 element(s).
A59: 8f296b7a417523e9c769761dd41b703c75d90019 | B59: axe | C59: A | D59: n/a | E59: ade | F59: 2.4.7 | G59: passed | H59: passed | I59: =IF(EXACT(G59,H59),1,0) -> 1 | J59: 0 | K59: N/A | L59: 0 | M59: 1 | N59: axe-core | O59: 1 | P59: 5.35 | S59: Passed Example 4 | T59: oj04fd | U59: Element in sequential focus order has visible focus | W59: https://www.w3.org/WAI/content-assets/wcag-act-rules/testcases/oj04fd/8f296b7a417523e9c769761dd41b703c75d90019.html | X59: corpus1\ade\2.4.7\passed\8f296b7a417523e9c769761dd41b703c75d90019.html | Y59: Found 3 rule violation(s) affecting 5 element(s).
A60: 8f296b7a417523e9c769761dd41b703c75d90019 | B60: axe | C60: A | D60: n/a | E60: ade | F60: 2.4.7 | G60: passed | H60: passed | I60: =IF(EXACT(G60,H60),1,0) -> 1 | J60: 1 | K60: N/A | L60: 0 | M60: 1 | N60: axe-core | O60: 1 | P60: 4.64 | S60: Passed Example 4 | T60: oj04fd | U60: Element in sequential focus order has visible focus | W60: https://www.w3.org/WAI/content-assets/wcag-act-rules/testcases/oj04fd/8f296b7a417523e9c769761dd41b703c75d90019.html | X60: corpus1\ade\2.4.7\passed\8f296b7a417523e9c769761dd41b703c75d90019.html | Y60: Found 3 rule violation(s) affecting 5 element(s).
A61: 8f296b7a417523e9c769761dd41b703c75d90019 | B61: axe | C61: A | D61: n/a | E61: ade | F61: 2.4.7 | G61: passed | H61: passed | I61: =IF(EXACT(G61,H61),1,0) -> 1 | J61: 2 | K61: N/A | L61: 0 | M61: 1 | N61: axe-core | O61: 1 | P61: 5.1 | S61: Passed Example 4 | T61: oj04fd | U61: Element in sequential focus order has visible focus | W61: https://www.w3.org/WAI/content-assets/wcag-act-rules/testcases/oj04fd/8f296b7a417523e9c769761dd41b703c75d90019.html | X61: corpus1\ade\2.4.7\passed\8f296b7a417523e9c769761dd41b703c75d90019.html | Y61: Found 3 rule violation(s) affecting 5 element(s).
A62: 90789ad82a761b7697418e8cb403db103f0925a2 | B62: axe | C62: A | D62: n/a | E62: ade | F62: 2.4.7 | G62: inapplicable | H62: passed | I62: =IF(EXACT(G62,H62),1,0) -> 0 | J62: 0 | K62: N/A | L62: 0 | M62: 1 | N62: axe-core | O62: 1 | P62: 3.53 | S62: Inapplicable Example 1 | T62: oj04fd | U62: Element in sequential focus order has visible focus | W62: https://www.w3.org/WAI/content-assets/wcag-act-rules/testcases/oj04fd/90789ad82a761b7697418e8cb403db103f0925a2.html | X62: corpus1\ade\2.4.7\inapplicable\90789ad82a761b7697418e8cb403db103f0925a2.html | Y62: Found 3 rule violation(s) affecting 3 element(s).
A63: 90789ad82a761b7697418e8cb403db103f0925a2 | B63: axe | C63: A | D63: n/a | E63: ade | F63: 2.4.7 | G63: inapplicable | H63: passed | I63: =IF(EXACT(G63,H63),1,0) -> 0 | J63: 1 | K63: N/A | L63: 0 | M63: 1 | N63: axe-core | O63: 1 | P63: 3.52 | S63: Inapplicable Example 1 | T63: oj04fd | U63: Element in sequential focus order has visible focus | W63: https://www.w3.org/WAI/content-assets/wcag-act-rules/testcases/oj04fd/90789ad82a761b7697418e8cb403db103f0925a2.html | X63: corpus1\ade\2.4.7\inapplicable\90789ad82a761b7697418e8cb403db103f0925a2.html | Y63: Found 3 rule violation(s) affecting 3 element(s).
A64: 90789ad82a761b7697418e8cb403db103f0925a2 | B64: axe | C64: A | D64: n/a | E64: ade | F64: 2.4.7 | G64: inapplicable | H64: passed | I64: =IF(EXACT(G64,H64),1,0) -> 0 | J64: 2 | K64: N/A | L64: 0 | M64: 1 | N64: axe-core | O64: 1 | P64: 3.55 | S64: Inapplicable Example 1 | T64: oj04fd | U64: Element in sequential focus order has visible focus | W64: https://www.w3.org/WAI/content-assets/wcag-act-rules/testcases/oj04fd/90789ad82a761b7697418e8cb403db103f0925a2.html | X64: corpus1\ade\2.4.7\inapplicable\90789ad82a761b7697418e8cb403db103f0925a2.html | Y64: Found 3 rule violation(s) affecting 3 element(s).
A65: b12f1f45eef29c30197ca3bda79d793cd90eeadd | B65: axe | C65: A | D65: n/a | E65: ade | F65: 2.4.7 | G65: inapplicable | H65: passed | I65: =IF(EXACT(G65,H65),1,0) -> 0 | J65: 0 | K65: N/A | L65: 0 | M65: 1 | N65: axe-core | O65: 1 | P65: 3.56 | S65: Inapplicable Example 2 | T65: oj04fd | U65: Element in sequential focus order has visible focus | W65: https://www.w3.org/WAI/content-assets/wcag-act-rules/testcases/oj04fd/b12f1f45eef29c30197ca3bda79d793cd90eeadd.html | X65: corpus1\ade\2.4.7\inapplicable\b12f1f45eef29c30197ca3bda79d793cd90eeadd.html | Y65: Found 3 rule violation(s) affecting 4 element(s).
A66: b12f1f45eef29c30197ca3bda79d793cd90eeadd | B66: axe | C66: A | D66: n/a | E66: ade | F66: 2.4.7 | G66: inapplicable | H66: passed | I66: =IF(EXACT(G66,H66),1,0) -> 0 | J66: 1 | K66: N/A | L66: 0 | M66: 1 | N66: axe-core | O66: 1 | P66: 3.53 | S66: Inapplicable Example 2 | T66: oj04fd | U66: Element in sequential focus order has visible focus | W66: https://www.w3.org/WAI/content-assets/wcag-act-rules/testcases/oj04fd/b12f1f45eef29c30197ca3bda79d793cd90eeadd.html | X66: corpus1\ade\2.4.7\inapplicable\b12f1f45eef29c30197ca3bda79d793cd90eeadd.html | Y66: Found 3 rule violation(s) affecting 4 element(s).
A67: b12f1f45eef29c30197ca3bda79d793cd90eeadd | B67: axe | C67: A | D67: n/a | E67: ade | F67: 2.4.7 | G67: inapplicable | H67: passed | I67: =IF(EXACT(G67,H67),1,0) -> 0 | J67: 2 | K67: N/A | L67: 0 | M67: 1 | N67: axe-core | O67: 1 | P67: 3.67 | S67: Inapplicable Example 2 | T67: oj04fd | U67: Element in sequential focus order has visible focus | W67: https://www.w3.org/WAI/content-assets/wcag-act-rules/testcases/oj04fd/b12f1f45eef29c30197ca3bda79d793cd90eeadd.html | X67: corpus1\ade\2.4.7\inapplicable\b12f1f45eef29c30197ca3bda79d793cd90eeadd.html | Y67: Found 3 rule violation(s) affecting 4 element(s).
... A70: f1c9efb4c8d1b5f7870c693bce2e6ca046dd768d | B70: axe | C70: A | D70: n/a | E70: ade | F70: 2.4.7 | G70: failed | H70: passed | I70: =IF(EXACT(G70,H70),1,0) -> 0 | J70: 2 | K70: N/A | L70: 0 | M70: 1 | N70: axe-core | O70: 1 | P70: 3.52 | S70: Failed Example 1 | T70: oj04fd | U70: Element in sequential focus order has visible focus | W70: https://www.w3.org/WAI/content-assets/wcag-act-rules/testcases/oj04fd/f1c9efb4c8d1b5f7870c693bce2e6ca046dd768d.html | X70: corpus1\ade\2.4.7\failed\f1c9efb4c8d1b5f7870c693bce2e6ca046dd768d.html | Y70: Found 3 rule violation(s) affecting 3 element(s).
A71: ha-2-4-7-fail-01-focus-suppressed | B71: axe | C71: A | D71: n/a | E71: ade | F71: 2.4.7 | G71: failed | H71: passed | I71: =IF(EXACT(G71,H71),1,0) -> 0 | J71: 0 | K71: N/A | L71: 0 | M71: 1 | N71: axe-core | O71: 1 | P71: 3.6 | S71: Focus indicator suppressed via CSS outline removal | V71: hand-authored from W3C Understanding | X71: corpus1\ade\2.4.7\failed\ha-2-4-7-fail-01-focus-suppressed.html | Y71: Found 0 rule violation(s) affecting 0 element(s).
A72: ha-2-4-7-fail-01-focus-suppressed | B72: axe | C72: A | D72: n/a | E72: ade | F72: 2.4.7 | G72: failed | H72: passed | I72: =IF(EXACT(G72,H72),1,0) -> 0 | J72: 1 | K72: N/A | L72: 0 | M72: 1 | N72: axe-core | O72: 1 | P72: 3.55 | S72: Focus indicator suppressed via CSS outline removal | V72: hand-authored from W3C Understanding | X72: corpus1\ade\2.4.7\failed\ha-2-4-7-fail-01-focus-suppressed.html | Y72: Found 0 rule violation(s) affecting 0 element(s).
A73: ha-2-4-7-fail-01-focus-suppressed | B73: axe | C73: A | D73: n/a | E73: ade | F73: 2.4.7 | G73: failed | H73: passed | I73: =IF(EXACT(G73,H73),1,0) -> 0 | J73: 2 | K73: N/A | L73: 0 | M73: 1 | N73: axe-core | O73: 1 | P73: 3.58 | S73: Focus indicator suppressed via CSS outline removal | V73: hand-authored from W3C Understanding | X73: corpus1\ade\2.4.7\failed\ha-2-4-7-fail-01-focus-suppressed.html | Y73: Found 0 rule violation(s) affecting 0 element(s).
A74: ha-2-5-5-fail-01-tiny-icons | B74: axe | C74: A | D74: n/a | E74: ade | F74: 2.5.5 | G74: failed | H74: passed | I74: =IF(EXACT(G74,H74),1,0) -> 0 | J74: 0 | K74: N/A | L74: 0 | M74: 1 | N74: axe-core | O74: 1 | P74: 4.03 | S74: Tightly packed icon buttons well below 44x44 | V74: hand-authored from W3C Understanding | X74: corpus1\ade\2.5.5\failed\ha-2-5-5-fail-01-tiny-icons.html | Y74: Found 2 rule violation(s) affecting 2 element(s).
A75: ha-2-5-5-fail-01-tiny-icons | B75: axe | C75: A | D75: n/a | E75: ade | F75: 2.5.5 | G75: failed | H75: passed | I75: =IF(EXACT(G75,H75),1,0) -> 0 | J75: 1 | K75: N/A | L75: 0 | M75: 1 | N75: axe-core | O75: 1 | P75: 3.53 | S75: Tightly packed icon buttons well below 44x44 | V75: hand-authored from W3C Understanding | X75: corpus1\ade\2.5.5\failed\ha-2-5-5-fail-01-tiny-icons.html | Y75: Found 2 rule violation(s) affecting 2 element(s).
A76: ha-2-5-5-fail-01-tiny-icons | B76: axe | C76: A | D76: n/a | E76: ade | F76: 2.5.5 | G76: failed | H76: passed | I76: =IF(EXACT(G76,H76),1,0) -> 0 | J76: 2 | K76: N/A | L76: 0 | M76: 1 | N76: axe-core | O76: 1 | P76: 3.53 | S76: Tightly packed icon buttons well below 44x44 | V76: hand-authored from W3C Understanding | X76: corpus1\ade\2.5.5\failed\ha-2-5-5-fail-01-tiny-icons.html | Y76: Found 2 rule violation(s) affecting 2 element(s).
A77: ha-2-5-5-fail-02-short-buttons | B77: axe | C77: A | D77: n/a | E77: ade | F77: 2.5.5 | G77: failed | H77: passed | I77: =IF(EXACT(G77,H77),1,0) -> 0 | J77: 0 | K77: N/A | L77: 0 | M77: 1 | N77: axe-core | O77: 1 | P77: 3.69 | S77: Standard buttons styled below 44px height | V77: hand-authored from W3C Understanding | X77: corpus1\ade\2.5.5\failed\ha-2-5-5-fail-02-short-buttons.html | Y77: Found 0 rule violation(s) affecting 0 element(s).
A78: ha-2-5-5-fail-02-short-buttons | B78: axe | C78: A | D78: n/a | E78: ade | F78: 2.5.5 | G78: failed | H78: passed | I78: =IF(EXACT(G78,H78),1,0) -> 0 | J78: 1 | K78: N/A | L78: 0 | M78: 1 | N78: axe-core | O78: 1 | P78: 3.72 | S78: Standard buttons styled below 44px height | V78: hand-authored from W3C Understanding | X78: corpus1\ade\2.5.5\failed\ha-2-5-5-fail-02-short-buttons.html | Y78: Found 0 rule violation(s) affecting 0 element(s).
A79: ha-2-5-5-fail-02-short-buttons | B79: axe | C79: A | D79: n/a | E79: ade | F79: 2.5.5 | G79: failed | H79: passed | I79: =IF(EXACT(G79,H79),1,0) -> 0 | J79: 2 | K79: N/A | L79: 0 | M79: 1 | N79: axe-core | O79: 1 | P79: 3.67 | S79: Standard buttons styled below 44px height | V79: hand-authored from W3C Understanding | X79: corpus1\ade\2.5.5\failed\ha-2-5-5-fail-02-short-buttons.html | Y79: Found 0 rule violation(s) affecting 0 element(s).
A80: ha-2-5-5-inap-01-inline-link-in-text | B80: axe | C80: A | D80: n/a | E80: ade | F80: 2.5.5 | G80: inapplicable | H80: passed | I80: =IF(EXACT(G80,H80),1,0) -> 0 | J80: 0 | K80: N/A | L80: 0 | M80: 1 | N80: axe-core | O80: 1 | P80: 3.54 | S80: Only interactive element is an inline link within text | V80: hand-authored from W3C Understanding | X80: corpus1\ade\2.5.5\inapplicable\ha-2-5-5-inap-01-inline-link-in-text.html | Y80: Found 0 rule violation(s) affecting 0 element(s).
A81: ha-2-5-5-inap-01-inline-link-in-text | B81: axe | C81: A | D81: n/a | E81: ade | F81: 2.5.5 | G81: inapplicable | H81: passed | I81: =IF(EXACT(G81,H81),1,0) -> 0 | J81: 1 | K81: N/A | L81: 0 | M81: 1 | N81: axe-core | O81: 1 | P81: 3.55 | S81: Only interactive element is an inline link within text | V81: hand-authored from W3C Understanding | X81: corpus1\ade\2.5.5\inapplicable\ha-2-5-5-inap-01-inline-link-in-text.html | Y81: Found 0 rule violation(s) affecting 0 element(s).
A82: ha-2-5-5-inap-01-inline-link-in-text | B82: axe | C82: A | D82: n/a | E82: ade | F82: 2.5.5 | G82: inapplicable | H82: passed | I82: =IF(EXACT(G82,H82),1,0) -> 0 | J82: 2 | K82: N/A | L82: 0 | M82: 1 | N82: axe-core | O82: 1 | P82: 3.56 | S82: Only interactive element is an inline link within text | V82: hand-authored from W3C Understanding | X82: corpus1\ade\2.5.5\inapplicable\ha-2-5-5-inap-01-inline-link-in-text.html | Y82: Found 0 rule violation(s) affecting 0 element(s).
... A91: ha-2-5-5-pass-02-icon-with-padding | B91: axe | C91: A | D91: n/a | E91: ade | F91: 2.5.5 | G91: passed | H91: passed | I91: =IF(EXACT(G91,H91),1,0) -> 1 | J91: 2 | K91: N/A | L91: 0 | M91: 1 | N91: axe-core | O91: 1 | P91: 3.52 | S91: Small icon with generous touch padding reaches 44x44 | V91: hand-authored from W3C Understanding | X91: corpus1\ade\2.5.5\passed\ha-2-5-5-pass-02-icon-with-padding.html | Y91: Found 2 rule violation(s) affecting 2 element(s).
A92: 0411dce372604b1c0b14fe48aae6190882e8110c | B92: axe | C92: A | D92: n/a | E92: elias | F92: 1.3.5 | G92: passed | H92: passed | I92: =IF(EXACT(G92,H92),1,0) -> 1 | J92: 0 | K92: N/A | L92: 0 | M92: 1 | N92: axe-core | O92: 1 | P92: 3.8 | S92: Passed Example 6 | T92: 73f2c2 | U92: `autocomplete` attribute has valid value | W92: https://www.w3.org/WAI/content-assets/wcag-act-rules/testcases/73f2c2/0411dce372604b1c0b14fe48aae6190882e8110c.html | X92: corpus1\elias\1.3.5\passed\0411dce372604b1c0b14fe48aae6190882e8110c.html | Y92: Found 3 rule violation(s) affecting 3 element(s).
A93: 0411dce372604b1c0b14fe48aae6190882e8110c | B93: axe | C93: A | D93: n/a | E93: elias | F93: 1.3.5 | G93: passed | H93: passed | I93: =IF(EXACT(G93,H93),1,0) -> 1 | J93: 1 | K93: N/A | L93: 0 | M93: 1 | N93: axe-core | O93: 1 | P93: 3.95 | S93: Passed Example 6 | T93: 73f2c2 | U93: `autocomplete` attribute has valid value | W93: https://www.w3.org/WAI/content-assets/wcag-act-rules/testcases/73f2c2/0411dce372604b1c0b14fe48aae6190882e8110c.html | X93: corpus1\elias\1.3.5\passed\0411dce372604b1c0b14fe48aae6190882e8110c.html | Y93: Found 3 rule violation(s) affecting 3 element(s).
A94: 0411dce372604b1c0b14fe48aae6190882e8110c | B94: axe | C94: A | D94: n/a | E94: elias | F94: 1.3.5 | G94: passed | H94: passed | I94: =IF(EXACT(G94,H94),1,0) -> 1 | J94: 2 | K94: N/A | L94: 0 | M94: 1 | N94: axe-core | O94: 1 | P94: 3.79 | S94: Passed Example 6 | T94: 73f2c2 | U94: `autocomplete` attribute has valid value | W94: https://www.w3.org/WAI/content-assets/wcag-act-rules/testcases/73f2c2/0411dce372604b1c0b14fe48aae6190882e8110c.html | X94: corpus1\elias\1.3.5\passed\0411dce372604b1c0b14fe48aae6190882e8110c.html | Y94: Found 3 rule violation(s) affecting 3 element(s).
A95: 130d7f761a6a43b896b2f1d0ded311da6a7aebf1 | B95: axe | C95: A | D95: n/a | E95: elias | F95: 1.3.5 | G95: failed | H95: failed | I95: =IF(EXACT(G95,H95),1,0) -> 1 | J95: 0 | K95: serious | L95: 1 | M95: 1 | N95: axe-core | O95: 1 | P95: 3.57 | S95: Failed Example 8 | T95: 73f2c2 | U95: Autocomplete attribute has valid value | W95: https://www.w3.org/WAI/content-assets/wcag-act-rules/testcases/73f2c2/130d7f761a6a43b896b2f1d0ded311da6a7aebf1.html | X95: corpus1\elias\1.3.5\failed\130d7f761a6a43b896b2f1d0ded311da6a7aebf1.html | Y95: Found 4 rule violation(s) affecting 4 element(s). | Z95: [wcag21aa, wcag135] Ensure the autocomplete attribute is correct and suitable for the form field autocomplete attribute must be used correctly
A96: 130d7f761a6a43b896b2f1d0ded311da6a7aebf1 | B96: axe | C96: A | D96: n/a | E96: elias | F96: 1.3.5 | G96: failed | H96: failed | I96: =IF(EXACT(G96,H96),1,0) -> 1 | J96: 1 | K96: serious | L96: 1 | M96: 1 | N96: axe-core | O96: 1 | P96: 3.56 | S96: Failed Example 8 | T96: 73f2c2 | U96: Autocomplete attribute has valid value | W96: https://www.w3.org/WAI/content-assets/wcag-act-rules/testcases/73f2c2/130d7f761a6a43b896b2f1d0ded311da6a7aebf1.html | X96: corpus1\elias\1.3.5\failed\130d7f761a6a43b896b2f1d0ded311da6a7aebf1.html | Y96: Found 4 rule violation(s) affecting 4 element(s). | Z96: [wcag21aa, wcag135] Ensure the autocomplete attribute is correct and suitable for the form field autocomplete attribute must be used correctly
A97: 130d7f761a6a43b896b2f1d0ded311da6a7aebf1 | B97: axe | C97: A | D97: n/a | E97: elias | F97: 1.3.5 | G97: failed | H97: failed | I97: =IF(EXACT(G97,H97),1,0) -> 1 | J97: 2 | K97: serious | L97: 1 | M97: 1 | N97: axe-core | O97: 1 | P97: 3.54 | S97: Failed Example 8 | T97: 73f2c2 | U97: Autocomplete attribute has valid value | W97: https://www.w3.org/WAI/content-assets/wcag-act-rules/testcases/73f2c2/130d7f761a6a43b896b2f1d0ded311da6a7aebf1.html | X97: corpus1\elias\1.3.5\failed\130d7f761a6a43b896b2f1d0ded311da6a7aebf1.html | Y97: Found 4 rule violation(s) affecting 4 element(s). | Z97: [wcag21aa, wcag135] Ensure the autocomplete attribute is correct and suitable for the form field autocomplete attribute must be used correctly
A98: 2512c24c9a793fa8a30958e203090f955a3fc262 | B98: axe | C98: A | D98: n/a | E98: elias | F98: 1.3.5 | G98: failed | H98: failed | I98: =IF(EXACT(G98,H98),1,0) -> 1 | J98: 0 | K98: serious | L98: 1 | M98: 1 | N98: axe-core | O98: 1 | P98: 3.68 | S98: Failed Example 6 | T98: 73f2c2 | U98: Autocomplete attribute has valid value | W98: https://www.w3.org/WAI/content-assets/wcag-act-rules/testcases/73f2c2/2512c24c9a793fa8a30958e203090f955a3fc262.html | X98: corpus1\elias\1.3.5\failed\2512c24c9a793fa8a30958e203090f955a3fc262.html | Y98: Found 4 rule violation(s) affecting 4 element(s). | Z98: [wcag21aa, wcag135] Ensure the autocomplete attribute is correct and suitable for the form field autocomplete attribute must be used correctly
A99: 2512c24c9a793fa8a30958e203090f955a3fc262 | B99: axe | C99: A | D99: n/a | E99: elias | F99: 1.3.5 | G99: failed | H99: failed | I99: =IF(EXACT(G99,H99),1,0) -> 1 | J99: 1 | K99: serious | L99: 1 | M99: 1 | N99: axe-core | O99: 1 | P99: 3.67 | S99: Failed Example 6 | T99: 73f2c2 | U99: Autocomplete attribute has valid value | W99: https://www.w3.org/WAI/content-assets/wcag-act-rules/testcases/73f2c2/2512c24c9a793fa8a30958e203090f955a3fc262.html | X99: corpus1\elias\1.3.5\failed\2512c24c9a793fa8a30958e203090f955a3fc262.html | Y99: Found 4 rule violation(s) affecting 4 element(s). | Z99: [wcag21aa, wcag135] Ensure the autocomplete attribute is correct and suitable for the form field autocomplete attribute must be used correctly
A100: 2512c24c9a793fa8a30958e203090f955a3fc262 | B100: axe | C100: A | D100: n/a | E100: elias | F100: 1.3.5 | G100: failed | H100: failed | I100: =IF(EXACT(G100,H100),1,0) -> 1 | J100: 2 | K100: serious | L100: 1 | M100: 1 | N100: axe-core | O100: 1 | P100: 3.66 | S100: Failed Example 6 | T100: 73f2c2 | U100: Autocomplete attribute has valid value | W100: https://www.w3.org/WAI/content-assets/wcag-act-rules/testcases/73f2c2/2512c24c9a793fa8a30958e203090f955a3fc262.html | X100: corpus1\elias\1.3.5\failed\2512c24c9a793fa8a30958e203090f955a3fc262.html | Y100: Found 4 rule violation(s) affecting 4 element(s). | Z100: [wcag21aa, wcag135] Ensure the autocomplete attribute is correct and suitable for the form field autocomplete attribute must be used correctly
A101: 35d0948a2cb309923e9a7cc5dd99a8ffc975088b | B101: axe | C101: A | D101: n/a | E101: elias | F101: 1.3.5 | G101: passed | H101: passed | I101: =IF(EXACT(G101,H101),1,0) -> 1 | J101: 0 | K101: N/A | L101: 0 | M101: 1 | N101: axe-core | O101: 1 | P101: 3.64 | S101: Passed Example 8 | T101: 73f2c2 | U101: `autocomplete` attribute has valid value | W101: https://www.w3.org/WAI/content-assets/wcag-act-rules/testcases/73f2c2/35d0948a2cb309923e9a7cc5dd99a8ffc975088b.html | X101: corpus1\elias\1.3.5\passed\35d0948a2cb309923e9a7cc5dd99a8ffc975088b.html | Y101: Found 3 rule violation(s) affecting 3 element(s).
A102: 35d0948a2cb309923e9a7cc5dd99a8ffc975088b | B102: axe | C102: A | D102: n/a | E102: elias | F102: 1.3.5 | G102: passed | H102: passed | I102: =IF(EXACT(G102,H102),1,0) -> 1 | J102: 1 | K102: N/A | L102: 0 | M102: 1 | N102: axe-core | O102: 1 | P102: 3.55 | S102: Passed Example 8 | T102: 73f2c2 | U102: `autocomplete` attribute has valid value | W102: https://www.w3.org/WAI/content-assets/wcag-act-rules/testcases/73f2c2/35d0948a2cb309923e9a7cc5dd99a8ffc975088b.html | X102: corpus1\elias\1.3.5\passed\35d0948a2cb309923e9a7cc5dd99a8ffc975088b.html | Y102: Found 3 rule violation(s) affecting 3 element(s).
A103: 35d0948a2cb309923e9a7cc5dd99a8ffc975088b | B103: axe | C103: A | D103: n/a | E103: elias | F103: 1.3.5 | G103: passed | H103: passed | I103: =IF(EXACT(G103,H103),1,0) -> 1 | J103: 2 | K103: N/A | L103: 0 | M103: 1 | N103: axe-core | O103: 1 | P103: 3.56 | S103: Passed Example 8 | T103: 73f2c2 | U103: `autocomplete` attribute has valid value | W103: https://www.w3.org/WAI/content-assets/wcag-act-rules/testcases/73f2c2/35d0948a2cb309923e9a7cc5dd99a8ffc975088b.html | X103: corpus1\elias\1.3.5\passed\35d0948a2cb309923e9a7cc5dd99a8ffc975088b.html | Y103: Found 3 rule violation(s) affecting 3 element(s).
A104: 3a6b86ed813d4c34e566641e9fcd571e16aeae6f | B104: axe | C104: A | D104: n/a | E104: elias | F104: 1.3.5 | G104: inapplicable | H104: passed | I104: =IF(EXACT(G104,H104),1,0) -> 0 | J104: 0 | K104: N/A | L104: 0 | M104: 1 | N104: axe-core | O104: 1 | P104: 3.7 | S104: Inapplicable Example 7 | T104: 73f2c2 | U104: `autocomplete` attribute has valid value | W104: https://www.w3.org/WAI/content-assets/wcag-act-rules/testcases/73f2c2/3a6b86ed813d4c34e566641e9fcd571e16aeae6f.html | X104: corpus1\elias\1.3.5\inapplicable\3a6b86ed813d4c34e566641e9fcd571e16aeae6f.html | Y104: Found 3 rule violation(s) affecting 3 element(s).
A105: 3a6b86ed813d4c34e566641e9fcd571e16aeae6f | B105: axe | C105: A | D105: n/a | E105: elias | F105: 1.3.5 | G105: inapplicable | H105: passed | I105: =IF(EXACT(G105,H105),1,0) -> 0 | J105: 1 | K105: N/A | L105: 0 | M105: 1 | N105: axe-core | O105: 1 | P105: 3.68 | S105: Inapplicable Example 7 | T105: 73f2c2 | U105: `autocomplete` attribute has valid value | W105: https://www.w3.org/WAI/content-assets/wcag-act-rules/testcases/73f2c2/3a6b86ed813d4c34e566641e9fcd571e16aeae6f.html | X105: corpus1\elias\1.3.5\inapplicable\3a6b86ed813d4c34e566641e9fcd571e16aeae6f.html | Y105: Found 3 rule violation(s) affecting 3 element(s).
A106: 3a6b86ed813d4c34e566641e9fcd571e16aeae6f | B106: axe | C106: A | D106: n/a | E106: elias | F106: 1.3.5 | G106: inapplicable | H106: passed | I106: =IF(EXACT(G106,H106),1,0) -> 0 | J106: 2 | K106: N/A | L106: 0 | M106: 1 | N106: axe-core | O106: 1 | P106: 3.7 | S106: Inapplicable Example 7 | T106: 73f2c2 | U106: `autocomplete` attribute has valid value | W106: https://www.w3.org/WAI/content-assets/wcag-act-rules/testcases/73f2c2/3a6b86ed813d4c34e566641e9fcd571e16aeae6f.html | X106: corpus1\elias\1.3.5\inapplicable\3a6b86ed813d4c34e566641e9fcd571e16aeae6f.html | Y106: Found 3 rule violation(s) affecting 3 element(s).
A107: 41c0b66bc0208aef009343935649f2bec3ae778d | B107: axe | C107: A | D107: n/a | E107: elias | F107: 1.3.5 | G107: inapplicable | H107: passed | I107: =IF(EXACT(G107,H107),1,0) -> 0 | J107: 0 | K107: N/A | L107: 0 | M107: 1 | N107: axe-core | O107: 1 | P107: 3.62 | S107: Inapplicable Example 8 | T107: 73f2c2 | U107: Autocomplete attribute has valid value | W107: https://www.w3.org/WAI/content-assets/wcag-act-rules/testcases/73f2c2/41c0b66bc0208aef009343935649f2bec3ae778d.html | X107: corpus1\elias\1.3.5\inapplicable\41c0b66bc0208aef009343935649f2bec3ae778d.html | Y107: Found 2 rule violation(s) affecting 2 element(s).
A108: 41c0b66bc0208aef009343935649f2bec3ae778d | B108: axe | C108: A | D108: n/a | E108: elias | F108: 1.3.5 | G108: inapplicable | H108: passed | I108: =IF(EXACT(G108,H108),1,0) -> 0 | J108: 1 | K108: N/A | L108: 0 | M108: 1 | N108: axe-core | O108: 1 | P108: 3.59 | S108: Inapplicable Example 8 | T108: 73f2c2 | U108: Autocomplete attribute has valid value | W108: https://www.w3.org/WAI/content-assets/wcag-act-rules/testcases/73f2c2/41c0b66bc0208aef009343935649f2bec3ae778d.html | X108: corpus1\elias\1.3.5\inapplicable\41c0b66bc0208aef009343935649f2bec3ae778d.html | Y108: Found 2 rule violation(s) affecting 2 element(s).
A109: 41c0b66bc0208aef009343935649f2bec3ae778d | B109: axe | C109: A | D109: n/a | E109: elias | F109: 1.3.5 | G109: inapplicable | H109: passed | I109: =IF(EXACT(G109,H109),1,0) -> 0 | J109: 2 | K109: N/A | L109: 0 | M109: 1 | N109: axe-core | O109: 1 | P109: 3.57 | S109: Inapplicable Example 8 | T109: 73f2c2 | U109: Autocomplete attribute has valid value | W109: https://www.w3.org/WAI/content-assets/wcag-act-rules/testcases/73f2c2/41c0b66bc0208aef009343935649f2bec3ae778d.html | X109: corpus1\elias\1.3.5\inapplicable\41c0b66bc0208aef009343935649f2bec3ae778d.html | Y109: Found 2 rule violation(s) affecting 2 element(s).
A110: 0128de1beb7862298366680f6920bd3b3874d752 | B110: axe | C110: A | D110: n/a | E110: elias | F110: 1.4.12 | G110: inapplicable | H110: passed | I110: =IF(EXACT(G110,H110),1,0) -> 0 | J110: 0 | K110: N/A | L110: 0 | M110: 1 | N110: axe-core | O110: 1 | P110: 3.52 | S110: Inapplicable Example 2 | T110: 78fd32 | U110: Important line height in style attributes is wide enough | W110: https://www.w3.org/WAI/content-assets/wcag-act-rules/testcases/78fd32/0128de1beb7862298366680f6920bd3b3874d752.html | X110: corpus1\elias\1.4.12\inapplicable\0128de1beb7862298366680f6920bd3b3874d752.html | Y110: Found 2 rule violation(s) affecting 2 element(s).
A111: 0128de1beb7862298366680f6920bd3b3874d752 | B111: axe | C111: A | D111: n/a | E111: elias | F111: 1.4.12 | G111: inapplicable | H111: passed | I111: =IF(EXACT(G111,H111),1,0) -> 0 | J111: 1 | K111: N/A | L111: 0 | M111: 1 | N111: axe-core | O111: 1 | P111: 3.54 | S111: Inapplicable Example 2 | T111: 78fd32 | U111: Important line height in style attributes is wide enough | W111: https://www.w3.org/WAI/content-assets/wcag-act-rules/testcases/78fd32/0128de1beb7862298366680f6920bd3b3874d752.html | X111: corpus1\elias\1.4.12\inapplicable\0128de1beb7862298366680f6920bd3b3874d752.html | Y111: Found 2 rule violation(s) affecting 2 element(s).
A112: 0128de1beb7862298366680f6920bd3b3874d752 | B112: axe | C112: A | D112: n/a | E112: elias | F112: 1.4.12 | G112: inapplicable | H112: passed | I112: =IF(EXACT(G112,H112),1,0) -> 0 | J112: 2 | K112: N/A | L112: 0 | M112: 1 | N112: axe-core | O112: 1 | P112: 3.51 | S112: Inapplicable Example 2 | T112: 78fd32 | U112: Important line height in style attributes is wide enough | W112: https://www.w3.org/WAI/content-assets/wcag-act-rules/testcases/78fd32/0128de1beb7862298366680f6920bd3b3874d752.html | X112: corpus1\elias\1.4.12\inapplicable\0128de1beb7862298366680f6920bd3b3874d752.html | Y112: Found 2 rule violation(s) affecting 2 element(s).
... A118: 0f8063a09807c4bf8d5f7c796cbf0f2aa20e7e57 | B118: axe | C118: A | D118: n/a | E118: elias | F118: 1.4.12 | G118: inapplicable | H118: passed | I118: =IF(EXACT(G118,H118),1,0) -> 0 | J118: 2 | K118: N/A | L118: 0 | M118: 1 | N118: axe-core | O118: 1 | P118: 3.61 | S118: Inapplicable Example 10 | T118: 78fd32 | U118: Important line height in style attributes is wide enough | W118: https://www.w3.org/WAI/content-assets/wcag-act-rules/testcases/78fd32/0f8063a09807c4bf8d5f7c796cbf0f2aa20e7e57.html | X118: corpus1\elias\1.4.12\inapplicable\0f8063a09807c4bf8d5f7c796cbf0f2aa20e7e57.html | Y118: Found 3 rule violation(s) affecting 3 element(s).
A119: 1134eadf72b2a40c03b8bbf486ebfd3bb34cf986 | B119: axe | C119: A | D119: n/a | E119: elias | F119: 1.4.12 | G119: failed | H119: failed | I119: =IF(EXACT(G119,H119),1,0) -> 1 | J119: 0 | K119: serious | L119: 1 | M119: 1 | N119: axe-core | O119: 1 | P119: 3.66 | S119: Failed Example 2 | T119: 9e45ec | U119: Important word spacing in style attributes is wide enough | W119: https://www.w3.org/WAI/content-assets/wcag-act-rules/testcases/9e45ec/1134eadf72b2a40c03b8bbf486ebfd3bb34cf986.html | X119: corpus1\elias\1.4.12\failed\1134eadf72b2a40c03b8bbf486ebfd3bb34cf986.html | Y119: Found 4 rule violation(s) affecting 4 element(s). | Z119: [wcag21aa, wcag1412] Ensure that text spacing set through style attributes can be adjusted with custom stylesheets Inline text spacing must be adjustable with custom stylesheets
A120: 1134eadf72b2a40c03b8bbf486ebfd3bb34cf986 | B120: axe | C120: A | D120: n/a | E120: elias | F120: 1.4.12 | G120: failed | H120: failed | I120: =IF(EXACT(G120,H120),1,0) -> 1 | J120: 1 | K120: serious | L120: 1 | M120: 1 | N120: axe-core | O120: 1 | P120: 3.67 | S120: Failed Example 2 | T120: 9e45ec | U120: Important word spacing in style attributes is wide enough | W120: https://www.w3.org/WAI/content-assets/wcag-act-rules/testcases/9e45ec/1134eadf72b2a40c03b8bbf486ebfd3bb34cf986.html | X120: corpus1\elias\1.4.12\failed\1134eadf72b2a40c03b8bbf486ebfd3bb34cf986.html | Y120: Found 4 rule violation(s) affecting 4 element(s). | Z120: [wcag21aa, wcag1412] Ensure that text spacing set through style attributes can be adjusted with custom stylesheets Inline text spacing must be adjustable with custom stylesheets
...

Sheet B_persona_llm
A1: snippet_id | B1: condition | C1: condition_key | D1: model | E1: persona | F1: wcag_criterion | G1: expected | H1: evaluated | I1: correct | J1: repetition | K1: severity | L1: issue_count | M1: tool_call_count | N1: tools_called | O1: iteration_count | P1: total_time_seconds | Q1: input_tokens | R1: output_tokens | S1: testcase_title | T1: rule_id | U1: rule_name | V1: corpus_source | W1: rule_url | X1: html_path | Y1: overall_assessment | Z1: issues_detail
A2: 033e04cced5973596d9aa724feacb027d23b4c53 | B2: persona_llm | C2: B | D2: claude-sonnet-4-6 | E2: ade | F2: 2.1.1 | G2: inapplicable | H2: inapplicable | I2: =IF(EXACT(G2,H2),1,0) -> 1 | J2: 0 | K2: N/A | L2: 0 | M2: 0 | O2: 1 | P2: 3.11 | Q2: 1277 | R2: 91 | S2: Inapplicable Example 2 | T2: akn7bn | U2: Iframe with interactive elements is not excluded from tab-order | W2: https://www.w3.org/WAI/content-assets/wcag-act-rules/testcases/akn7bn/033e04cced5973596d9aa724feacb027d23b4c53.html | X2: corpus1\ade\2.1.1\inapplicable\033e04cced5973596d9aa724feacb027d23b4c53.html | Y2: This page has no visible interactive elements — the only interactive content is an iframe with tabindex='-1' and the hidden attribute, making it completely unreachable and invisible, so there is nothing here for me to navigate to or interact with.
A3: 033e04cced5973596d9aa724feacb027d23b4c53 | B3: persona_llm | C3: B | D3: claude-sonnet-4-6 | E3: ade | F3: 2.1.1 | G3: inapplicable | H3: inapplicable | I3: =IF(EXACT(G3,H3),1,0) -> 1 | J3: 1 | K3: N/A | L3: 0 | M3: 0 | O3: 1 | P3: 2.82 | Q3: 1277 | R3: 92 | S3: Inapplicable Example 2 | T3: akn7bn | U3: Iframe with interactive elements is not excluded from tab-order | W3: https://www.w3.org/WAI/content-assets/wcag-act-rules/testcases/akn7bn/033e04cced5973596d9aa724feacb027d23b4c53.html | X3: corpus1\ade\2.1.1\inapplicable\033e04cced5973596d9aa724feacb027d23b4c53.html | Y3: This page has no visible interactive elements whatsoever — the only interactive content is an iframe with tabindex='-1' and hidden attributes, making it completely unreachable and invisible, so there is nothing here for me to navigate or interact with.
A4: 033e04cced5973596d9aa724feacb027d23b4c53 | B4: persona_llm | C4: B | D4: claude-sonnet-4-6 | E4: ade | F4: 2.1.1 | G4: inapplicable | H4: inapplicable | I4: =IF(EXACT(G4,H4),1,0) -> 1 | J4: 2 | K4: N/A | L4: 0 | M4: 0 | O4: 1 | P4: 2.97 | Q4: 1277 | R4: 90 | S4: Inapplicable Example 2 | T4: akn7bn | U4: Iframe with interactive elements is not excluded from tab-order | W4: https://www.w3.org/WAI/content-assets/wcag-act-rules/testcases/akn7bn/033e04cced5973596d9aa724feacb027d23b4c53.html | X4: corpus1\ade\2.1.1\inapplicable\033e04cced5973596d9aa724feacb027d23b4c53.html | Y4: This page has no visible interactive elements — the only interactive content is an iframe with tabindex='-1' and the hidden attribute, making it completely unreachable and invisible, so there is nothing here for me to navigate or interact with.
A5: 17a371c470316dc29e424101065ebfe9f7b2e990 | B5: persona_llm | C5: B | D5: claude-sonnet-4-6 | E5: ade | F5: 2.1.1 | G5: inapplicable | H5: inapplicable | I5: =IF(EXACT(G5,H5),1,0) -> 1 | J5: 0 | K5: N/A | L5: 0 | M5: 0 | O5: 1 | P5: 3.22 | Q5: 1278 | R5: 95 | S5: Inapplicable Example 5 | T5: akn7bn | U5: Iframe with interactive elements is not excluded from tab-order | W5: https://www.w3.org/WAI/content-assets/wcag-act-rules/testcases/akn7bn/17a371c470316dc29e424101065ebfe9f7b2e990.html | X5: corpus1\ade\2.1.1\inapplicable\17a371c470316dc29e424101065ebfe9f7b2e990.html | Y5: There are no interactive elements reachable by keyboard on this page — the only element is an iframe with tabindex='-1' and the inert attribute, which removes it and its contents entirely from keyboard interaction, so there is nothing here for me to evaluate.
A6: 17a371c470316dc29e424101065ebfe9f7b2e990 | B6: persona_llm | C6: B | D6: claude-sonnet-4-6 | E6: ade | F6: 2.1.1 | G6: inapplicable | H6: inapplicable | I6: =IF(EXACT(G6,H6),1,0) -> 1 | J6: 1 | K6: N/A | L6: 0 | M6: 0 | O6: 1 | P6: 2.83 | Q6: 1278 | R6: 97 | S6: Inapplicable Example 5 | T6: akn7bn | U6: Iframe with interactive elements is not excluded from tab-order | W6: https://www.w3.org/WAI/content-assets/wcag-act-rules/testcases/akn7bn/17a371c470316dc29e424101065ebfe9f7b2e990.html | X6: corpus1\ade\2.1.1\inapplicable\17a371c470316dc29e424101065ebfe9f7b2e990.html | Y6: This page has no interactive elements reachable by keyboard — the only element is an iframe with tabindex='-1' and the inert attribute, making it and its contents completely removed from the tab order and interaction model, so there is nothing here for me to evaluate.
A7: 17a371c470316dc29e424101065ebfe9f7b2e990 | B7: persona_llm | C7: B | D7: claude-sonnet-4-6 | E7: ade | F7: 2.1.1 | G7: inapplicable | H7: inapplicable | I7: =IF(EXACT(G7,H7),1,0) -> 1 | J7: 2 | K7: N/A | L7: 0 | M7: 0 | O7: 1 | P7: 2.9 | Q7: 1278 | R7: 92 | S7: Inapplicable Example 5 | T7: akn7bn | U7: Iframe with interactive elements is not excluded from tab-order | W7: https://www.w3.org/WAI/content-assets/wcag-act-rules/testcases/akn7bn/17a371c470316dc29e424101065ebfe9f7b2e990.html | X7: corpus1\ade\2.1.1\inapplicable\17a371c470316dc29e424101065ebfe9f7b2e990.html | Y7: This page has no interactive elements reachable by keyboard — the only element is an iframe with tabindex='-1' and the inert attribute, making it completely excluded from interaction, so there's nothing here for me to navigate to or operate.
A8: 1e3939d9f8e0f78f9c564ec6feb12cc5635c0acb | B8: persona_llm | C8: B | D8: claude-sonnet-4-6 | E8: ade | F8: 2.1.1 | G8: passed | H8: passed | I8: =IF(EXACT(G8,H8),1,0) -> 1 | J8: 0 | K8: N/A | L8: 0 | M8: 0 | O8: 1 | P8: 4.18 | Q8: 1267 | R8: 78 | S8: Passed Example 1 | T8: akn7bn | U8: Iframe with interactive elements is not excluded from tab-order | W8: https://www.w3.org/WAI/content-assets/wcag-act-rules/testcases/akn7bn/1e3939d9f8e0f78f9c564ec6feb12cc5635c0acb.html | X8: corpus1\ade\2.1.1\passed\1e3939d9f8e0f78f9c564ec6feb12cc5635c0acb.html | Y8: The page contains a single iframe with a native anchor link that is fully keyboard accessible, has a logical focus order, and native browser focus indicators apply — nothing here blocks me from navigating with Tab.
A9: 1e3939d9f8e0f78f9c564ec6feb12cc5635c0acb | B9: persona_llm | C9: B | D9: claude-sonnet-4-6 | E9: ade | F9: 2.1.1 | G9: passed | H9: passed | I9: =IF(EXACT(G9,H9),1,0) -> 1 | J9: 1 | K9: N/A | L9: 0 | M9: 0 | O9: 1 | P9: 4.79 | Q9: 1267 | R9: 92 | S9: Passed Example 1 | T9: akn7bn | U9: Iframe with interactive elements is not excluded from tab-order | W9: https://www.w3.org/WAI/content-assets/wcag-act-rules/testcases/akn7bn/1e3939d9f8e0f78f9c564ec6feb12cc5635c0acb.html | X9: corpus1\ade\2.1.1\passed\1e3939d9f8e0f78f9c564ec6feb12cc5635c0acb.html | Y9: The page contains a single iframe with a standard anchor link that is keyboard focusable, has no timing issues, follows a logical focus order, and while focus visibility depends on the browser default, there are no explicit violations — this page passes all five criteria I evaluate.
A10: 1e3939d9f8e0f78f9c564ec6feb12cc5635c0acb | B10: persona_llm | C10: B | D10: claude-sonnet-4-6 | E10: ade | F10: 2.1.1 | G10: passed | H10: passed | I10: =IF(EXACT(G10,H10),1,0) -> 1 | J10: 2 | K10: N/A | L10: 0 | M10: 0 | O10: 1 | P10: 3.38 | Q10: 1267 | R10: 90 | S10: Passed Example 1 | T10: akn7bn | U10: Iframe with interactive elements is not excluded from tab-order | W10: https://www.w3.org/WAI/content-assets/wcag-act-rules/testcases/akn7bn/1e3939d9f8e0f78f9c564ec6feb12cc5635c0acb.html | X10: corpus1\ade\2.1.1\passed\1e3939d9f8e0f78f9c564ec6feb12cc5635c0acb.html | Y10: The page contains a single iframe with an anchor link that is keyboard focusable, has no timing issues, follows a logical focus order, and while there is no explicit focus style the browser default should apply — overall this page passes all five criteria I evaluate.
A11: 270a22a8e4ce4d9f073e1484a0d807705207a1d7 | B11: persona_llm | C11: B | D11: claude-sonnet-4-6 | E11: ade | F11: 2.1.1 | G11: passed | H11: passed | I11: =IF(EXACT(G11,H11),1,0) -> 1 | J11: 0 | K11: N/A | L11: 0 | M11: 0 | O11: 1 | P11: 4.98 | Q11: 1490 | R11: 119 | S11: Passed Example 2 | T11: 0ssw9k | U11: Scrollable content can be reached with sequential focus navigation | W11: https://www.w3.org/WAI/content-assets/wcag-act-rules/testcases/0ssw9k/270a22a8e4ce4d9f073e1484a0d807705207a1d7.html | X11: corpus1\ade\2.1.1\passed\270a22a8e4ce4d9f073e1484a0d807705207a1d7.html | Y11: This page has a single scrollable section with one link and a paragraph — the link is a standard anchor element that I can reach with Tab, focus is handled by the browser natively, there are no time limits, no focus order issues, and while the link may be inline text (exempt from 2.5.5 target size), everything here works fine for me as a keyboard user.
A12: 270a22a8e4ce4d9f073e1484a0d807705207a1d7 | B12: persona_llm | C12: B | D12: claude-sonnet-4-6 | E12: ade | F12: 2.1.1 | G12: passed | H12: passed | I12: =IF(EXACT(G12,H12),1,0) -> 1 | J12: 1 | K12: N/A | L12: 0 | M12: 0 | O12: 1 | P12: 3.75 | Q12: 1490 | R12: 107 | S12: Passed Example 2 | T12: 0ssw9k | U12: Scrollable content can be reached with sequential focus navigation | W12: https://www.w3.org/WAI/content-assets/wcag-act-rules/testcases/0ssw9k/270a22a8e4ce4d9f073e1484a0d807705207a1d7.html | X12: corpus1\ade\2.1.1\passed\270a22a8e4ce4d9f073e1484a0d807705207a1d7.html | Y12: This page has a single scrollable section with a standard anchor link and paragraph text — the link is keyboard-focusable, there are no time limits, no focus order issues, no missing focus indicators in native rendering, and the link is inline text so target size exceptions apply; everything checks out for me as a keyboard-only user.
A13: 270a22a8e4ce4d9f073e1484a0d807705207a1d7 | B13: persona_llm | C13: B | D13: claude-sonnet-4-6 | E13: ade | F13: 2.1.1 | G13: passed | H13: passed | I13: =IF(EXACT(G13,H13),1,0) -> 1 | J13: 2 | K13: N/A | L13: 0 | M13: 0 | O13: 1 | P13: 4.33 | Q13: 1490 | R13: 122 | S13: Passed Example 2 | T13: 0ssw9k | U13: Scrollable content can be reached with sequential focus navigation | W13: https://www.w3.org/WAI/content-assets/wcag-act-rules/testcases/0ssw9k/270a22a8e4ce4d9f073e1484a0d807705207a1d7.html | X13: corpus1\ade\2.1.1\passed\270a22a8e4ce4d9f073e1484a0d807705207a1d7.html | Y13: This page has a single scrollable section with one link and a paragraph — the link is a standard native anchor element that I can reach with Tab, focus is handled by the browser's default styles, there are no time limits, no focus order issues, and while the target size of the link may be modest it is inline text so it falls under the native/inline exception — overall this page works fine for me.
A14: 5fa34d0a7eea03109cd12c0e7c21fce793c268db | B14: persona_llm | C14: B | D14: claude-sonnet-4-6 | E14: ade | F14: 2.1.1 | G14: failed | H14: inapplicable | I14: =IF(EXACT(G14,H14),1,0) -> 0 | J14: 0 | K14: N/A | L14: 0 | M14: 0 | O14: 1 | P14: 2.97 | Q14: 1458 | R14: 75 | S14: Failed Example 1 | T14: 0ssw9k | U14: Scrollable content can be reached with sequential focus navigation | W14: https://www.w3.org/WAI/content-assets/wcag-act-rules/testcases/0ssw9k/5fa34d0a7eea03109cd12c0e7c21fce793c268db.html | X14: corpus1\ade\2.1.1\failed\5fa34d0a7eea03109cd12c0e7c21fce793c268db.html | Y14: This page has no interactive elements whatsoever — just a scrollable section with a heading and paragraph text — so none of my five keyboard and timing criteria apply here.
A15: 5fa34d0a7eea03109cd12c0e7c21fce793c268db | B15: persona_llm | C15: B | D15: claude-sonnet-4-6 | E15: ade | F15: 2.1.1 | G15: failed | H15: failed | I15: =IF(EXACT(G15,H15),1,0) -> 1 | J15: 1 | K15: critical | L15: 1 | M15: 0 | O15: 1 | P15: 6.09 | Q15: 1458 | R15: 241 | S15: Failed Example 1 | T15: 0ssw9k | U15: Scrollable content can be reached with sequential focus navigation | W15: https://www.w3.org/WAI/content-assets/wcag-act-rules/testcases/0ssw9k/5fa34d0a7eea03109cd12c0e7c21fce793c268db.html | X15: corpus1\ade\2.1.1\failed\5fa34d0a7eea03109cd12c0e7c21fce793c268db.html | Y15: This page fails me completely — there's a scrollable section I can't reach with Tab, so a chunk of the content is locked away and I have no way to read it. | Z15: [2.1.1] As Ade, I cannot reach this scrollable region with Tab at all. The overflowing text is effectively hidden from me — it simply does not exist in my world. Add tabindex="0" to the scrollable <section> element so keyboard users can focus it and scroll with arrow keys.
A16: 5fa34d0a7eea03109cd12c0e7c21fce793c268db | B16: persona_llm | C16: B | D16: claude-sonnet-4-6 | E16: ade | F16: 2.1.1 | G16: failed | H16: failed | I16: =IF(EXACT(G16,H16),1,0) -> 1 | J16: 2 | K16: critical | L16: 1 | M16: 0 | O16: 1 | P16: 6.86 | Q16: 1458 | R16: 300 | S16: Failed Example 1 | T16: 0ssw9k | U16: Scrollable content can be reached with sequential focus navigation | W16: https://www.w3.org/WAI/content-assets/wcag-act-rules/testcases/0ssw9k/5fa34d0a7eea03109cd12c0e7c21fce793c268db.html | X16: corpus1\ade\2.1.1\failed\5fa34d0a7eea03109cd12c0e7c21fce793c268db.html | Y16: This page has a scrollable container that I can't reach with Tab — the content is locked away from me, and since I use the keyboard for everything, that overflow text simply doesn't exist for me. | Z16: [2.1.1] As Ade, I cannot reach this scrollable region with Tab at all — it simply doesn't exist for me. The text is clipped at 100px and I have no way to read the rest of the WCAG abstract without a mouse to scroll it. Add tabindex="0" to the scrollable <section> element so keyboard users can focus it and use arrow keys to scroll: <section tabindex="0" style="height: 100px; width: 500px; overflow-y: scroll">
A17: 62673162e22ee1e95e962522b1d1c3b549dbfc49 | B17: persona_llm | C17: B | D17: claude-sonnet-4-6 | E17: ade | F17: 2.1.1 | G17: failed | H17: failed | I17: =IF(EXACT(G17,H17),1,0) -> 1 | J17: 0 | K17: critical | L17: 2 | M17: 0 | O17: 1 | P17: 11.14 | Q17: 1272 | R17: 444 | S17: Failed Example 1 | T17: akn7bn | U17: Iframe with interactive elements is not excluded from tab-order | W17: https://www.w3.org/WAI/content-assets/wcag-act-rules/testcases/akn7bn/62673162e22ee1e95e962522b1d1c3b549dbfc49.html | X17: corpus1\ade\2.1.1\failed\62673162e22ee1e95e962522b1d1c3b549dbfc49.html | Y17: This page is completely broken for me — the only interactive element, a Home link, is locked inside an iframe with tabindex='-1', which means it literally does not exist as far as my keyboard is concerned. | Z17: [2.1.1] As Ade, I use Tab for everything. If the iframe is excluded from the tab order with tabindex='-1', the Home link inside it simply does not exist for me — I can never reach it by keyboard. Remove tabindex='-1' from the iframe so it enters the natural tab order, or restructure the content so the link is in the main document and reachable via Tab without needing to enter an iframe. || [2.4.7] Even if I could somehow reach the link, there is no focus styling defined anywhere in this page, so I would have no visible indicator of where my keyboard focus is. Add a visible :focus style (e.g., outline: 2px solid #005fcc) for all interactive elements, and ensure those elements are actually reachable by keyboard first.
A18: 62673162e22ee1e95e962522b1d1c3b549dbfc49 | B18: persona_llm | C18: B | D18: claude-sonnet-4-6 | E18: ade | F18: 2.1.1 | G18: failed | H18: failed | I18: =IF(EXACT(G18,H18),1,0) -> 1 | J18: 1 | K18: critical | L18: 2 | M18: 0 | O18: 1 | P18: 10.43 | Q18: 1272 | R18: 429 | S18: Failed Example 1 | T18: akn7bn | U18: Iframe with interactive elements is not excluded from tab-order | W18: https://www.w3.org/WAI/content-assets/wcag-act-rules/testcases/akn7bn/62673162e22ee1e95e962522b1d1c3b549dbfc49.html | X18: corpus1\ade\2.1.1\failed\62673162e22ee1e95e962522b1d1c3b549dbfc49.html | Y18: This page is completely unusable for me — the only interactive element, a link inside an iframe, is locked away behind tabindex='-1' and I can never reach it with my keyboard. | Z18: [2.1.1] As Ade, I use Tab for everything. If the iframe is excluded from the tab order with tabindex='-1', the link inside it simply does not exist for me — I can never reach or activate it. Remove tabindex='-1' from the iframe so it can receive keyboard focus, or restructure the content so the link exists in the main document where it is naturally keyboard-reachable. || [2.4.7] I need to see where focus is at all times. With no focusable elements reachable via Tab, I have no visible focus indicator anywhere on the page, leaving me completely disoriented. Ensure all focusable elements have a clearly visible focus indicator via CSS :focus or :focus-visible styles.
A19: 62673162e22ee1e95e962522b1d1c3b549dbfc49 | B19: persona_llm | C19: B | D19: claude-sonnet-4-6 | E19: ade | F19: 2.1.1 | G19: failed | H19: failed | I19: =IF(EXACT(G19,H19),1,0) -> 1 | J19: 2 | K19: critical | L19: 2 | M19: 0 | O19: 1 | P19: 10.15 | Q19: 1272 | R19: 435 | S19: Failed Example 1 | T19: akn7bn | U19: Iframe with interactive elements is not excluded from tab-order | W19: https://www.w3.org/WAI/content-assets/wcag-act-rules/testcases/akn7bn/62673162e22ee1e95e962522b1d1c3b549dbfc49.html | X19: corpus1\ade\2.1.1\failed\62673162e22ee1e95e962522b1d1c3b549dbfc49.html | Y19: This page is completely broken for me — the only interactive element is locked behind a tabindex='-1' iframe, so Tab skips it entirely and it simply doesn't exist in my world. | Z19: [2.1.1] As Ade, I use Tab for everything. If the iframe is excluded from the tab order with tabindex='-1', the Home link inside it simply does not exist for me. I cannot reach it, period. Remove tabindex='-1' from the iframe so it enters the natural tab order, or restructure the content so the link is directly in the main document and reachable via Tab. || [2.4.7] Even if I somehow reached the link, there is no stylesheet providing a visible focus ring, and the iframe's tabindex='-1' means keyboard focus never lands there. I would have no visual cue of where I am. Ensure the link is keyboard-reachable and add a clearly visible :focus style (e.g., outline: 3px solid #005fcc) so focus is always visible.
A20: 0bf30cdf02ff26dfca5aa705b7023227da221e05 | B20: persona_llm | C20: B | D20: claude-sonnet-4-6 | E20: ade | F20: 2.2.1 | G20: inapplicable | H20: failed | I20: =IF(EXACT(G20,H20),1,0) -> 0 | J20: 0 | K20: critical | L20: 1 | M20: 0 | O20: 1 | P20: 7.09 | Q20: 1270 | R20: 269 | S20: Inapplicable Example 7 | T20: bc659a | U20: Meta element has no refresh delay | W20: https://www.w3.org/WAI/content-assets/wcag-act-rules/testcases/bc659a/0bf30cdf02ff26dfca5aa705b7023227da221e05.html | X20: corpus1\ade\2.2.1\inapplicable\0bf30cdf02ff26dfca5aa705b7023227da221e05.html | Y20: This page fails immediately because a 5-second forced redirect gives me no time to react with my keyboard or voice control, and there is absolutely no way for me to stop or extend it. | Z20: [2.2.1] Five seconds is nowhere near enough time for me to orient myself using voice control or keyboard navigation. By the time I've even started reading the page, I'm yanked away to a new location with no warning and no way to stop it. Remove the meta refresh redirect entirely, or replace it with a user-initiated link/button. If a timed redirect is truly necessary, provide a visible countdown with keyboard-accessible controls to pause or cancel it, and set the timeout to at least 20 hours per WCAG guidance.
A21: 0bf30cdf02ff26dfca5aa705b7023227da221e05 | B21: persona_llm | C21: B | D21: claude-sonnet-4-6 | E21: ade | F21: 2.2.1 | G21: inapplicable | H21: failed | I21: =IF(EXACT(G21,H21),1,0) -> 0 | J21: 1 | K21: critical | L21: 1 | M21: 0 | O21: 1 | P21: 6.95 | Q21: 1270 | R21: 286 | S21: Inapplicable Example 7 | T21: bc659a | U21: Meta element has no refresh delay | W21: https://www.w3.org/WAI/content-assets/wcag-act-rules/testcases/bc659a/0bf30cdf02ff26dfca5aa705b7023227da221e05.html | X21: corpus1\ade\2.2.1\inapplicable\0bf30cdf02ff26dfca5aa705b7023227da221e05.html | Y21: This page kicks me off to another URL after just 5 seconds with no way to stop it — that's a critical barrier for me because voice control and keyboard navigation simply can't keep up with that kind of time pressure. | Z21: [2.2.1] Five seconds is nowhere near enough time for me to orient myself on a page using keyboard navigation or voice control. By the time I've even found where focus is, the page has already redirected me somewhere else without my consent. Remove the meta refresh redirect entirely, or replace it with a user-initiated control (e.g., a clearly labelled button or link) that lets the user choose when to navigate. If a timed redirect is truly necessary, provide a visible countdown with keyboard-accessible controls to cancel or extend the time limit by at least 10x the original duration.
A22: 0bf30cdf02ff26dfca5aa705b7023227da221e05 | B22: persona_llm | C22: B | D22: claude-sonnet-4-6 | E22: ade | F22: 2.2.1 | G22: inapplicable | H22: failed | I22: =IF(EXACT(G22,H22),1,0) -> 0 | J22: 2 | K22: critical | L22: 1 | M22: 0 | O22: 1 | P22: 7.24 | Q22: 1270 | R22: 296 | S22: Inapplicable Example 7 | T22: bc659a | U22: Meta element has no refresh delay | W22: https://www.w3.org/WAI/content-assets/wcag-act-rules/testcases/bc659a/0bf30cdf02ff26dfca5aa705b7023227da221e05.html | X22: corpus1\ade\2.2.1\inapplicable\0bf30cdf02ff26dfca5aa705b7023227da221e05.html | Y22: This page yanks me away after just 5 seconds with no way to stop it — that's a critical blocker for me because voice control and keyboard navigation simply can't keep up with that kind of time pressure. | Z22: [2.2.1] Five seconds is nowhere near enough time for me to orient myself on a page using keyboard navigation or voice control. By the time I've even found where focus is, the page has already redirected me somewhere else without my consent. Remove the meta refresh redirect entirely, or replace it with a user-initiated control (e.g., a keyboard-focusable button or link) that lets the user choose when to navigate. If a redirect is truly necessary, provide a visible, keyboard-accessible mechanism to cancel or extend the time limit to at least 20 hours, per WCAG 2.2.1 exception criteria.
A23: 48a600254c0883cd5a72471420b1ac5a532ca6c3 | B23: persona_llm | C23: B | D23: claude-sonnet-4-6 | E23: ade | F23: 2.2.1 | G23: inapplicable | H23: inapplicable | I23: =IF(EXACT(G23,H23),1,0) -> 1 | J23: 0 | K23: N/A | L23: 0 | M23: 0 | O23: 1 | P23: 2.61 | Q23: 1258 | R23: 65 | S23: Inapplicable Example 1 | T23: bc659a | U23: Meta element has no refresh delay | W23: https://www.w3.org/WAI/content-assets/wcag-act-rules/testcases/bc659a/48a600254c0883cd5a72471420b1ac5a532ca6c3.html | X23: corpus1\ade\2.2.1\inapplicable\48a600254c0883cd5a72471420b1ac5a532ca6c3.html | Y23: This page has no interactive elements and no active time limits, so none of my five keyboard and timing criteria apply here.
A24: 48a600254c0883cd5a72471420b1ac5a532ca6c3 | B24: persona_llm | C24: B | D24: claude-sonnet-4-6 | E24: ade | F24: 2.2.1 | G24: inapplicable | H24: inapplicable | I24: =IF(EXACT(G24,H24),1,0) -> 1 | J24: 1 | K24: N/A | L24: 0 | M24: 0 | O24: 1 | P24: 2.45 | Q24: 1258 | R24: 65 | S24: Inapplicable Example 1 | T24: bc659a | U24: Meta element has no refresh delay | W24: https://www.w3.org/WAI/content-assets/wcag-act-rules/testcases/bc659a/48a600254c0883cd5a72471420b1ac5a532ca6c3.html | X24: corpus1\ade\2.2.1\inapplicable\48a600254c0883cd5a72471420b1ac5a532ca6c3.html | Y24: This page has no interactive elements and no active time limits, so none of my five keyboard and timing criteria apply here.
A25: 48a600254c0883cd5a72471420b1ac5a532ca6c3 | B25: persona_llm | C25: B | D25: claude-sonnet-4-6 | E25: ade | F25: 2.2.1 | G25: inapplicable | H25: inapplicable | I25: =IF(EXACT(G25,H25),1,0) -> 1 | J25: 2 | K25: N/A | L25: 0 | M25: 0 | O25: 1 | P25: 2.45 | Q25: 1258 | R25: 65 | S25: Inapplicable Example 1 | T25: bc659a | U25: Meta element has no refresh delay | W25: https://www.w3.org/WAI/content-assets/wcag-act-rules/testcases/bc659a/48a600254c0883cd5a72471420b1ac5a532ca6c3.html | X25: corpus1\ade\2.2.1\inapplicable\48a600254c0883cd5a72471420b1ac5a532ca6c3.html | Y25: This page has no interactive elements and no active time limit, so none of my five keyboard and timing criteria apply here.
A26: 49d79a4e4e4a994a8eb7cf2eaf59c99d2251cac5 | B26: persona_llm | C26: B | D26: claude-sonnet-4-6 | E26: ade | F26: 2.2.1 | G26: passed | H26: inapplicable | I26: =IF(EXACT(G26,H26),1,0) -> 0 | J26: 0 | K26: N/A | L26: 0 | M26: 0 | O26: 1 | P26: 2.74 | Q26: 1249 | R26: 72 | S26: Passed Example 1 | T26: bc659a | U26: Meta element has no refresh delay | W26: https://www.w3.org/WAI/content-assets/wcag-act-rules/testcases/bc659a/49d79a4e4e4a994a8eb7cf2eaf59c99d2251cac5.html | X26: corpus1\ade\2.2.1\passed\49d79a4e4e4a994a8eb7cf2eaf59c99d2251cac5.html | Y26: This page is just an instant meta-refresh redirect with no interactive elements whatsoever, so there is nothing for me to tab to or interact with.
A27: 49d79a4e4e4a994a8eb7cf2eaf59c99d2251cac5 | B27: persona_llm | C27: B | D27: claude-sonnet-4-6 | E27: ade | F27: 2.2.1 | G27: passed | H27: inapplicable | I27: =IF(EXACT(G27,H27),1,0) -> 0 | J27: 1 | K27: N/A | L27: 0 | M27: 0 | O27: 1 | P27: 2.63 | Q27: 1249 | R27: 72 | S27: Passed Example 1 | T27: bc659a | U27: Meta element has no refresh delay | W27: https://www.w3.org/WAI/content-assets/wcag-act-rules/testcases/bc659a/49d79a4e4e4a994a8eb7cf2eaf59c99d2251cac5.html | X27: corpus1\ade\2.2.1\passed\49d79a4e4e4a994a8eb7cf2eaf59c99d2251cac5.html | Y27: This page is just an instant meta-refresh redirect with no interactive elements whatsoever, so there is nothing for me to tab to or interact with.
A28: 49d79a4e4e4a994a8eb7cf2eaf59c99d2251cac5 | B28: persona_llm | C28: B | D28: claude-sonnet-4-6 | E28: ade | F28: 2.2.1 | G28: passed | H28: inapplicable | I28: =IF(EXACT(G28,H28),1,0) -> 0 | J28: 2 | K28: N/A | L28: 0 | M28: 0 | O28: 1 | P28: 2.98 | Q28: 1249 | R28: 72 | S28: Passed Example 1 | T28: bc659a | U28: Meta element has no refresh delay | W28: https://www.w3.org/WAI/content-assets/wcag-act-rules/testcases/bc659a/49d79a4e4e4a994a8eb7cf2eaf59c99d2251cac5.html | X28: corpus1\ade\2.2.1\passed\49d79a4e4e4a994a8eb7cf2eaf59c99d2251cac5.html | Y28: This page is just an instant meta-refresh redirect with no interactive elements whatsoever, so there is nothing for me to tab to or interact with.
A29: 56857820788db21498e95a5cbba65d59a9a2b892 | B29: persona_llm | C29: B | D29: claude-sonnet-4-6 | E29: ade | F29: 2.2.1 | G29: failed | H29: failed | I29: =IF(EXACT(G29,H29),1,0) -> 1 | J29: 0 | K29: critical | L29: 1 | M29: 0 | O29: 1 | P29: 6.96 | Q29: 1266 | R29: 278 | S29: Failed Example 1 | T29: bc659a | U29: Meta element has no refresh delay | W29: https://www.w3.org/WAI/content-assets/wcag-act-rules/testcases/bc659a/56857820788db21498e95a5cbba65d59a9a2b892.html | X29: corpus1\ade\2.2.1\failed\56857820788db21498e95a5cbba65d59a9a2b892.html | Y29: This page fails immediately because the 30-second auto-refresh gives me no way to stop or extend it — with voice control, 30 seconds vanishes before I can do anything meaningful, and I'm left constantly losing my place. | Z29: [2.2.1] Voice control is slow — 30 seconds is nowhere near enough time for me to complete a task before the page resets and I lose my place entirely. There is no way for me to disable or extend this limit. Remove the meta refresh entirely, or provide a clearly labelled, keyboard-accessible control that lets users turn off, adjust, or extend the time limit before it expires. If the refresh is necessary, the timeout must be at least 20 hours, or the user must be warned and given at least 20 seconds to extend it.
A30: 56857820788db21498e95a5cbba65d59a9a2b892 | B30: persona_llm | C30: B | D30: claude-sonnet-4-6 | E30: ade | F30: 2.2.1 | G30: failed | H30: failed | I30: =IF(EXACT(G30,H30),1,0) -> 1 | J30: 1 | K30: critical | L30: 1 | M30: 0 | O30: 1 | P30: 6.43 | Q30: 1266 | R30: 252 | S30: Failed Example 1 | T30: bc659a | U30: Meta element has no refresh delay | W30: https://www.w3.org/WAI/content-assets/wcag-act-rules/testcases/bc659a/56857820788db21498e95a5cbba65d59a9a2b892.html | X30: corpus1\ade\2.2.1\failed\56857820788db21498e95a5cbba65d59a9a2b892.html | Y30: This page auto-refreshes every 30 seconds with no way to stop it — as someone who relies on voice control and keyboard navigation, that timer will constantly reset my work before I can finish anything. | Z30: [2.2.1] Voice control is slow — 30 seconds is not enough time for me to complete a task before the page resets, losing my place and any progress I've made. There is no way for me to turn this off. Remove the meta refresh entirely, or provide a clearly keyboard-accessible control that allows the user to disable, pause, or extend the time limit to at least 20 times the default (i.e., 10 minutes or more).
A31: 56857820788db21498e95a5cbba65d59a9a2b892 | B31: persona_llm | C31: B | D31: claude-sonnet-4-6 | E31: ade | F31: 2.2.1 | G31: failed | H31: failed | I31: =IF(EXACT(G31,H31),1,0) -> 1 | J31: 2 | K31: critical | L31: 1 | M31: 0 | O31: 1 | P31: 6.72 | Q31: 1266 | R31: 281 | S31: Failed Example 1 | T31: bc659a | U31: Meta element has no refresh delay | W31: https://www.w3.org/WAI/content-assets/wcag-act-rules/testcases/bc659a/56857820788db21498e95a5cbba65d59a9a2b892.html | X31: corpus1\ade\2.2.1\failed\56857820788db21498e95a5cbba65d59a9a2b892.html | Y31: This page is inaccessible to me — a 30-second auto-refresh with no way to stop it means I'll constantly lose my place and any work in progress before I can even finish navigating the page with my keyboard or voice control. | Z31: [2.2.1] Voice control is slow for me. If the page reloads every 30 seconds, I lose my place mid-task — any form I'm filling in, any navigation I'm working through, just vanishes. I cannot complete anything in time. Remove the meta refresh entirely, or provide a user-controlled mechanism to disable, extend, or pause the time limit before it triggers. If the refresh is necessary, the timeout must be at least 20 hours, or the user must be warned and given at least 20 seconds to extend it.
A32: 5d4d5b214459c8a0779600ab39a5668003271c62 | B32: persona_llm | C32: B | D32: claude-sonnet-4-6 | E32: ade | F32: 2.2.1 | G32: failed | H32: failed | I32: =IF(EXACT(G32,H32),1,0) -> 1 | J32: 0 | K32: critical | L32: 1 | M32: 0 | O32: 1 | P32: 8.46 | Q32: 1275 | R32: 311 | S32: Failed Example 4 | T32: bc659a | U32: Meta element has no refresh delay | W32: https://www.w3.org/WAI/content-assets/wcag-act-rules/testcases/bc659a/5d4d5b214459c8a0779600ab39a5668003271c62.html | X32: corpus1\ade\2.2.1\failed\5d4d5b214459c8a0779600ab39a5668003271c62.html | Y32: This page fails because the meta-refresh time limit gives me no way to turn it off or extend it — as someone who works slowly with voice control and keyboard navigation, losing control of when a page redirects is a real barrier I cannot work around. | Z32: [2.2.1] As Ade, voice control is slow and I work at my own pace. Even a 20-hour limit is a problem if there is absolutely no way for me to disable or extend it — I have zero control over when this page will vanish from under me, and no warning or option is provided. Remove the meta-refresh redirect entirely, or provide a clearly keyboard-accessible control that lets the user disable, extend, or adjust the time limit before it expires. If the redirect is essential, display a visible, keyboard-focusable warning well in advance with an option to cancel or postpone.
A33: 5d4d5b214459c8a0779600ab39a5668003271c62 | B33: persona_llm | C33: B | D33: claude-sonnet-4-6 | E33: ade | F33: 2.2.1 | G33: failed | H33: failed | I33: =IF(EXACT(G33,H33),1,0) -> 1 | J33: 1 | K33: critical | L33: 2 | M33: 0 | O33: 1 | P33: 10.76 | Q33: 1275 | R33: 444 | S33: Failed Example 4 | T33: bc659a | U33: Meta element has no refresh delay | W33: https://www.w3.org/WAI/content-assets/wcag-act-rules/testcases/bc659a/5d4d5b214459c8a0779600ab39a5668003271c62.html | X33: corpus1\ade\2.2.1\failed\5d4d5b214459c8a0779600ab39a5668003271c62.html | Y33: This page fails because the meta-refresh timer gives me absolutely no way to stop or extend the automatic redirect — no button, no dialog, nothing I can reach with Tab — and that loss of control is unacceptable when I'm navigating slowly with voice and keyboard. | Z33: [2.2.1] As Ade, I rely on voice control which is slow. Even though 20 hours sounds like a lot, there is absolutely no way for me to disable or extend this timer — it will fire without warning and without my consent, potentially interrupting my work mid-task with no recourse. Remove the meta-refresh redirect entirely, or replace it with a server-side mechanism that provides a visible, keyboard-accessible control allowing users to cancel, extend, or disable the time limit before it expires. If a redirect is truly necessary, provide at minimum a prominent, focusable warning with options to stop or postpone it. || [2.1.1] Not applicable as a failure — there are no interactive controls to reach. However, the meta-refresh itself is an automated action with no keyboard-accessible override control provided. If a redirect or session timeout is needed, provide a keyboard-accessible dialog or control to manage it.
A34: 5d4d5b214459c8a0779600ab39a5668003271c62 | B34: persona_llm | C34: B | D34: claude-sonnet-4-6 | E34: ade | F34: 2.2.1 | G34: failed | H34: failed | I34: =IF(EXACT(G34,H34),1,0) -> 1 | J34: 2 | K34: critical | L34: 2 | M34: 0 | O34: 1 | P34: 11.05 | Q34: 1275 | R34: 464 | S34: Failed Example 4 | T34: bc659a | U34: Meta element has no refresh delay | W34: https://www.w3.org/WAI/content-assets/wcag-act-rules/testcases/bc659a/5d4d5b214459c8a0779600ab39a5668003271c62.html | X34: corpus1\ade\2.2.1\failed\5d4d5b214459c8a0779600ab39a5668003271c62.html | Y34: This page fails because the automatic meta-refresh redirect gives me absolutely no way to stop, extend, or disable it — as someone using slow voice control, losing control of page navigation without warning is unacceptable. | Z34: [2.2.1] As Ade, I rely on voice control which is slow. Even though 20 hours sounds like a lot, there is absolutely no way for me to disable or extend this timer — it will fire without warning and without my consent, potentially interrupting a long working session or an assistive-technology workflow I have open. I have no control whatsoever. Remove the meta-refresh redirect entirely, or replace it with a user-initiated control (e.g., a button or link the user clicks to navigate). If a timed redirect is truly necessary, provide a visible countdown with options to extend or cancel the timer before it fires, per WCAG 2.2.1 Success Criterion. || [2.1.1] Not applicable as a failure — there is nothing to interact with via keyboard. However, the meta-refresh itself is not keyboard-controllable, reinforcing the 2.2.1 issue. N/A for this criterion in isolation; addressed by fixing 2.2.1.
A35: b5ca868de7980f6944142ecdb849f47ad2cdfb5c | B35: persona_llm | C35: B | D35: claude-sonnet-4-6 | E35: ade | F35: 2.2.1 | G35: passed | H35: inapplicable | I35: =IF(EXACT(G35,H35),1,0) -> 0 | J35: 0 | K35: N/A | L35: 0 | M35: 0 | O35: 1 | P35: 3.42 | Q35: 1249 | R35: 111 | S35: Passed Example 3 | T35: bc659a | U35: Meta element has no refresh delay | W35: https://www.w3.org/WAI/content-assets/wcag-act-rules/testcases/bc659a/b5ca868de7980f6944142ecdb849f47ad2cdfb5c.html | X35: corpus1\ade\2.2.1\passed\b5ca868de7980f6944142ecdb849f47ad2cdfb5c.html | Y35: This page has no interactive elements whatsoever, so there is nothing for me to navigate with my keyboard — all five criteria are inapplicable, though I do note the meta refresh timer of 72001 seconds is well above the 20-hour threshold that would trigger a WCAG 2.2.1 concern.
A36: b5ca868de7980f6944142ecdb849f47ad2cdfb5c | B36: persona_llm | C36: B | D36: claude-sonnet-4-6 | E36: ade | F36: 2.2.1 | G36: passed | H36: inapplicable | I36: =IF(EXACT(G36,H36),1,0) -> 0 | J36: 1 | K36: N/A | L36: 0 | M36: 0 | O36: 1 | P36: 3.11 | Q36: 1249 | R36: 105 | S36: Passed Example 3 | T36: bc659a | U36: Meta element has no refresh delay | W36: https://www.w3.org/WAI/content-assets/wcag-act-rules/testcases/bc659a/b5ca868de7980f6944142ecdb849f47ad2cdfb5c.html | X36: corpus1\ade\2.2.1\passed\b5ca868de7980f6944142ecdb849f47ad2cdfb5c.html | Y36: This page has no interactive elements whatsoever, so there is nothing for me to navigate or operate — all five criteria are inapplicable, and the meta-refresh timeout of 72001 seconds is well above the 20-hour threshold that would trigger a 2.2.1 concern.
A37: b5ca868de7980f6944142ecdb849f47ad2cdfb5c | B37: persona_llm | C37: B | D37: claude-sonnet-4-6 | E37: ade | F37: 2.2.1 | G37: passed | H37: inapplicable | I37: =IF(EXACT(G37,H37),1,0) -> 0 | J37: 2 | K37: N/A | L37: 0 | M37: 0 | O37: 1 | P37: 3.18 | Q37: 1249 | R37: 105 | S37: Passed Example 3 | T37: bc659a | U37: Meta element has no refresh delay | W37: https://www.w3.org/WAI/content-assets/wcag-act-rules/testcases/bc659a/b5ca868de7980f6944142ecdb849f47ad2cdfb5c.html | X37: corpus1\ade\2.2.1\passed\b5ca868de7980f6944142ecdb849f47ad2cdfb5c.html | Y37: This page has no interactive elements whatsoever, so there is nothing for me to navigate or operate — all five criteria are inapplicable, and the meta-refresh timeout of 72001 seconds is well above the 20-hour threshold that would trigger a 2.2.1 concern.
A38: ha-2-4-3-fail-01-positive-tabindex | B38: persona_llm | C38: B | D38: claude-sonnet-4-6 | E38: ade | F38: 2.4.3 | G38: failed | H38: failed | I38: =IF(EXACT(G38,H38),1,0) -> 1 | J38: 0 | K38: serious | L38: 1 | M38: 0 | O38: 1 | P38: 9.75 | Q38: 1420 | R38: 359 | S38: Positive tabindex values disrupt natural focus order | V38: hand-authored from W3C Understanding | X38: corpus1\ade\2.4.3\failed\ha-2-4-3-fail-01-positive-tabindex.html | Y38: This form's scrambled tab order — jumping to Question 2, then Question 3, then back up to Question 1 — completely disorients me as a keyboard-only user; I lose my place and can't trust that I've answered questions in the right sequence. | Z38: [2.4.3] As Ade, I Tab through the form expecting to fill in Question 1, then 2, then 3 — but instead I land on Question 2 first, then Question 3, then jump back up to Question 1. This completely disorients me and I lose track of which fields I've already filled in. Remove the explicit tabindex attributes entirely (or set them all to tabindex='0') so the browser uses the natural DOM order: q1 → q2 → q3 → Submit. Only use positive tabindex values when there is a genuine, intentional reason to override visual order.
A39: ha-2-4-3-fail-01-positive-tabindex | B39: persona_llm | C39: B | D39: claude-sonnet-4-6 | E39: ade | F39: 2.4.3 | G39: failed | H39: failed | I39: =IF(EXACT(G39,H39),1,0) -> 1 | J39: 1 | K39: serious | L39: 1 | M39: 0 | O39: 1 | P39: 7.38 | Q39: 1420 | R39: 323 | S39: Positive tabindex values disrupt natural focus order | V39: hand-authored from W3C Understanding | X39: corpus1\ade\2.4.3\failed\ha-2-4-3-fail-01-positive-tabindex.html | Y39: The scrambled tabindex values send my keyboard focus jumping out of visual order — q2 before q1 — which disorients me completely and makes this survey unreliable to complete by keyboard. | Z39: [2.4.3] As Ade, I Tab through the form expecting to answer Question 1 first, but focus jumps to Question 2 instead. By the time I reach Question 1 it's the third field — I've lost my place and may fill in answers against the wrong questions without realising it. Remove all explicit tabindex attributes from these form controls (or set them all to tabindex='0'). Native DOM order already provides a logical top-to-bottom sequence: q1 → q2 → q3 → Submit.
A40: ha-2-4-3-fail-01-positive-tabindex | B40: persona_llm | C40: B | D40: claude-sonnet-4-6 | E40: ade | F40: 2.4.3 | G40: failed | H40: failed | I40: =IF(EXACT(G40,H40),1,0) -> 1 | J40: 2 | K40: serious | L40: 1 | M40: 0 | O40: 1 | P40: 8.9 | Q40: 1420 | R40: 371 | S40: Positive tabindex values disrupt natural focus order | V40: hand-authored from W3C Understanding | X40: corpus1\ade\2.4.3\failed\ha-2-4-3-fail-01-positive-tabindex.html | Y40: This survey form scrambles my Tab key journey — focus jumps to Question 2, then Question 3, then back up to Question 1, which completely disorients me and makes filling out even a simple three-question form a confusing ordeal. | Z40: [2.4.3] As Ade, I Tab through forms in the order I see them on screen. When focus jumps to Question 2 first, then Question 3, then leaps back up to Question 1, I completely lose my place and have no idea which field I just filled in. This disorientation is exhausting and error-prone when I cannot use a mouse to reorient myself. Remove all explicit tabindex attributes from the form fields and the submit button, or set them all to tabindex='0'. The natural DOM order (q1 → q2 → q3 → Submit) already matches the visual order and will produce a logical, predictable tab sequence without any tabindex manipulation.
A41: ha-2-4-3-fail-02-visual-reorder-css | B41: persona_llm | C41: B | D41: claude-sonnet-4-6 | E41: ade | F41: 2.4.3 | G41: failed | H41: failed | I41: =IF(EXACT(G41,H41),1,0) -> 1 | J41: 0 | K41: serious | L41: 1 | M41: 0 | O41: 1 | P41: 8.77 | Q41: 1421 | R41: 361 | S41: CSS flex order does not match DOM order | V41: hand-authored from W3C Understanding | X41: corpus1\ade\2.4.3\failed\ha-2-4-3-fail-02-visual-reorder-css.html | Y41: This form breaks my ability to navigate predictably — the CSS flexbox reordering makes the tab sequence jump around the page in a way that completely disconnects what I see from where my keyboard focus actually lands. | Z41: [2.4.3] As Ade, I tab through the form expecting to fill in what I see left-to-right: City, then State, then Street. Instead focus jumps to Street first (invisible to me as the third visual field), then City, then State. I lose my place immediately and have no idea which field I am actually editing. Align DOM order with visual order. Either reorder the HTML elements to match the intended visual sequence (City, State, Street), or remove the CSS `order` overrides so visual and DOM order are identical. Do not use CSS `order` to create a visual sequence that diverges from the tab sequence.
A42: ha-2-4-3-fail-02-visual-reorder-css | B42: persona_llm | C42: B | D42: claude-sonnet-4-6 | E42: ade | F42: 2.4.3 | G42: failed | H42: failed | I42: =IF(EXACT(G42,H42),1,0) -> 1 | J42: 1 | K42: serious | L42: 1 | M42: 0 | O42: 1 | P42: 8.08 | Q42: 1421 | R42: 353 | S42: CSS flex order does not match DOM order | V42: hand-authored from W3C Understanding | X42: corpus1\ade\2.4.3\failed\ha-2-4-3-fail-02-visual-reorder-css.html | Y42: This form fails because CSS flex `order` makes the visual field sequence (City, State, Street) completely different from the tab order (Street, City, State), which disorients me every time I press Tab. | Z42: [2.4.3] As Ade, I tab through the fields in an order that doesn't match what I see on screen. I press Tab expecting to move to the next visible field but instead jump to a field that appears to be in a completely different position. This disorients me and makes it very hard to know where I am in the form. Align the DOM order with the intended visual order. Either reorder the HTML elements so Street, City, State match the desired visual sequence, or remove the CSS `order` manipulation and use a layout that preserves DOM order. Do not use CSS `order` to create a visual sequence that contradicts the tab sequence.
A43: ha-2-4-3-fail-02-visual-reorder-css | B43: persona_llm | C43: B | D43: claude-sonnet-4-6 | E43: ade | F43: 2.4.3 | G43: failed | H43: failed | I43: =IF(EXACT(G43,H43),1,0) -> 1 | J43: 2 | K43: serious | L43: 1 | M43: 0 | O43: 1 | P43: 7.78 | Q43: 1421 | R43: 323 | S43: CSS flex order does not match DOM order | V43: hand-authored from W3C Understanding | X43: corpus1\ade\2.4.3\failed\ha-2-4-3-fail-02-visual-reorder-css.html | Y43: This form fails me completely — the CSS flex `order` trick makes my Tab key jump around the screen in the wrong direction, and I lose track of where I am every single keystroke. | Z43: [2.4.3] As Ade, I tab through fields in DOM order (Street → City → State) but the visible layout shows City → State → Street. My focus indicator jumps backwards across the screen with every Tab press, completely disorienting me and making it impossible to reliably fill in the form. Reorder the elements in the DOM to match the intended visual order (City, State, Street), or remove the CSS `order` reordering so visual and DOM order are consistent. Do not rely on CSS `order` to reorder content that has a meaningful sequence for keyboard users.
A44: ha-2-4-3-inap-01-static-content | B44: persona_llm | C44: B | D44: claude-sonnet-4-6 | E44: ade | F44: 2.4.3 | G44: inapplicable | H44: inapplicable | I44: =IF(EXACT(G44,H44),1,0) -> 1 | J44: 0 | K44: N/A | L44: 0 | M44: 0 | O44: 1 | P44: 2.96 | Q44: 1315 | R44: 78 | S44: Page has no focusable elements | V44: hand-authored from W3C Understanding | X44: corpus1\ade\2.4.3\inapplicable\ha-2-4-3-inap-01-static-content.html | Y44: This page has no interactive elements whatsoever — just static headings and paragraphs — so none of my keyboard, timing, focus, or target-size criteria apply here.
A45: ha-2-4-3-inap-01-static-content | B45: persona_llm | C45: B | D45: claude-sonnet-4-6 | E45: ade | F45: 2.4.3 | G45: inapplicable | H45: inapplicable | I45: =IF(EXACT(G45,H45),1,0) -> 1 | J45: 1 | K45: N/A | L45: 0 | M45: 0 | O45: 1 | P45: 2.76 | Q45: 1315 | R45: 72 | S45: Page has no focusable elements | V45: hand-authored from W3C Understanding | X45: corpus1\ade\2.4.3\inapplicable\ha-2-4-3-inap-01-static-content.html | Y45: This page has no interactive elements whatsoever — no links, buttons, or form controls — so none of my five keyboard and interaction criteria apply here.
A46: ha-2-4-3-inap-01-static-content | B46: persona_llm | C46: B | D46: claude-sonnet-4-6 | E46: ade | F46: 2.4.3 | G46: inapplicable | H46: inapplicable | I46: =IF(EXACT(G46,H46),1,0) -> 1 | J46: 2 | K46: N/A | L46: 0 | M46: 0 | O46: 1 | P46: 2.66 | Q46: 1315 | R46: 78 | S46: Page has no focusable elements | V46: hand-authored from W3C Understanding | X46: corpus1\ade\2.4.3\inapplicable\ha-2-4-3-inap-01-static-content.html | Y46: This page has no interactive elements whatsoever — just static headings and paragraphs — so none of my keyboard, timing, focus, or target-size criteria apply here.
A47: ha-2-4-3-inap-02-single-interactive | B47: persona_llm | C47: B | D47: claude-sonnet-4-6 | E47: ade | F47: 2.4.3 | G47: inapplicable | H47: passed | I47: =IF(EXACT(G47,H47),1,0) -> 0 | J47: 0 | K47: N/A | L47: 0 | M47: 0 | O47: 1 | P47: 3.46 | Q47: 1310 | R47: 81 | S47: Page has only one focusable element | V47: hand-authored from W3C Understanding | X47: corpus1\ade\2.4.3\inapplicable\ha-2-4-3-inap-02-single-interactive.html | Y47: This simple maintenance page has a single native button that is fully keyboard accessible, has no time limits, follows a logical tab order, and renders a visible focus indicator by default — nothing here blocks me from using it.
A48: ha-2-4-3-inap-02-single-interactive | B48: persona_llm | C48: B | D48: claude-sonnet-4-6 | E48: ade | F48: 2.4.3 | G48: inapplicable | H48: passed | I48: =IF(EXACT(G48,H48),1,0) -> 0 | J48: 1 | K48: N/A | L48: 0 | M48: 0 | O48: 1 | P48: 3.48 | Q48: 1310 | R48: 81 | S48: Page has only one focusable element | V48: hand-authored from W3C Understanding | X48: corpus1\ade\2.4.3\inapplicable\ha-2-4-3-inap-02-single-interactive.html | Y48: This simple maintenance page has a single native button that is fully keyboard accessible, has no time limits, follows a logical tab order, and renders a visible focus indicator by default — nothing here blocks me from using it.
A49: ha-2-4-3-inap-02-single-interactive | B49: persona_llm | C49: B | D49: claude-sonnet-4-6 | E49: ade | F49: 2.4.3 | G49: inapplicable | H49: passed | I49: =IF(EXACT(G49,H49),1,0) -> 0 | J49: 2 | K49: N/A | L49: 0 | M49: 0 | O49: 1 | P49: 3.1 | Q49: 1310 | R49: 82 | S49: Page has only one focusable element | V49: hand-authored from W3C Understanding | X49: corpus1\ade\2.4.3\inapplicable\ha-2-4-3-inap-02-single-interactive.html | Y49: This simple maintenance page has a single native button that is fully keyboard accessible, has no time limits, follows a logical tab order, and should display a visible focus indicator by default — nothing here blocks me from using it.
A50: ha-2-4-3-pass-01-natural-dom-order | B50: persona_llm | C50: B | D50: claude-sonnet-4-6 | E50: ade | F50: 2.4.3 | G50: passed | H50: passed | I50: =IF(EXACT(G50,H50),1,0) -> 1 | J50: 0 | K50: N/A | L50: 0 | M50: 0 | O50: 1 | P50: 4.23 | Q50: 1432 | R50: 118 | S50: Form follows natural DOM order matching visual order | V50: hand-authored from W3C Understanding | X50: corpus1\ade\2.4.3\passed\ha-2-4-3-pass-01-natural-dom-order.html | Y50: This straightforward sign-up form uses native HTML inputs and a button — everything is keyboard-reachable, focus order follows the visual layout top-to-bottom, browsers render default focus rings, there are no time limits, and the submit button is a full-width block element well above 44px in most default stylesheets, so I can navigate this page without any barriers.
A51: ha-2-4-3-pass-01-natural-dom-order | B51: persona_llm | C51: B | D51: claude-sonnet-4-6 | E51: ade | F51: 2.4.3 | G51: passed | H51: passed | I51: =IF(EXACT(G51,H51),1,0) -> 1 | J51: 1 | K51: N/A | L51: 0 | M51: 0 | O51: 1 | P51: 3.87 | Q51: 1432 | R51: 126 | S51: Form follows natural DOM order matching visual order | V51: hand-authored from W3C Understanding | X51: corpus1\ade\2.4.3\passed\ha-2-4-3-pass-01-natural-dom-order.html | Y51: This sign-up form is clean and straightforward — all inputs and the submit button are native HTML elements that I can reach with Tab, focus is visible by default, the tab order follows the logical top-to-bottom DOM sequence, there are no time limits, and while the submit button may be on the smaller side it is a standard browser-rendered control exempt from the 44×44 AAA target-size rule.
A52: ha-2-4-3-pass-01-natural-dom-order | B52: persona_llm | C52: B | D52: claude-sonnet-4-6 | E52: ade | F52: 2.4.3 | G52: passed | H52: passed | I52: =IF(EXACT(G52,H52),1,0) -> 1 | J52: 2 | K52: N/A | L52: 0 | M52: 0 | O52: 1 | P52: 4.52 | Q52: 1432 | R52: 118 | S52: Form follows natural DOM order matching visual order | V52: hand-authored from W3C Understanding | X52: corpus1\ade\2.4.3\passed\ha-2-4-3-pass-01-natural-dom-order.html | Y52: This straightforward sign-up form uses native HTML inputs and a button — everything is keyboard-reachable, focus order follows the visual layout top-to-bottom, browsers render default focus rings, there are no time limits, and the submit button is a full-width block element well above 44px in most default stylesheets, so I can navigate this page without any barriers.
A53: ha-2-4-3-pass-02-modal-focus-trap | B53: persona_llm | C53: B | D53: claude-sonnet-4-6 | E53: ade | F53: 2.4.3 | G53: passed | H53: failed | I53: =IF(EXACT(G53,H53),1,0) -> 0 | J53: 0 | K53: critical | L53: 4 | M53: 0 | O53: 1 | P53: 19.4 | Q53: 1384 | R53: 863 | S53: Modal dialog keeps focus inside the dialog | V53: hand-authored from W3C Understanding | X53: corpus1\ade\2.4.3\passed\ha-2-4-3-pass-02-modal-focus-trap.html | Y53: This dialog is essentially unreachable for me — there's no focus management to bring me into it, no visible focus indicator, and no focus trap, so as Ade I'd be completely lost the moment this modal opens. | Z53: [2.4.7] As Ade, if focus isn't moved into the dialog when it opens, I have no idea where I am. I can't see a focus ring on the dialog or its buttons, so I've completely lost my place on the page. Add `autofocus` to the Cancel button (or the dialog's first focusable element), and ensure a visible `:focus` outline is defined in CSS for all interactive elements. || [2.1.1] As Ade, I rely entirely on Tab to navigate. If focus isn't placed inside the dialog, I can't reach Cancel or Delete — those buttons effectively don't exist for me. Add a focus management script that moves focus to the first interactive element inside the dialog when it opens, and implement a focus trap so Tab cycles only within the dialog while it is open. || [2.4.3] As Ade, unpredictable Tab behaviour inside a modal disorients me. I need to know Tab will cycle Cancel → Delete → Cancel without escaping the dialog. Implement a focus trap within the dialog: intercept Tab and Shift+Tab keydown events to keep focus cycling between the dialog's focusable children only. || [2.5.5] As Ade, my adaptive pointing device struggles to land on small targets. Unstyled default buttons are often too small for me to activate reliably. Apply CSS to ensure both buttons have a minimum height and width of 44px, e.g. `min-height: 44px; min-width: 44px; padding: 10px 16px;`.
A54: ha-2-4-3-pass-02-modal-focus-trap | B54: persona_llm | C54: B | D54: claude-sonnet-4-6 | E54: ade | F54: 2.4.3 | G54: passed | H54: failed | I54: =IF(EXACT(G54,H54),1,0) -> 0 | J54: 1 | K54: critical | L54: 3 | M54: 0 | O54: 1 | P54: 18.52 | Q54: 1384 | R54: 784 | S54: Modal dialog keeps focus inside the dialog | V54: hand-authored from W3C Understanding | X54: corpus1\ade\2.4.3\passed\ha-2-4-3-pass-02-modal-focus-trap.html | Y54: This dialog is a keyboard trap in the worst sense — no autofocus, no explicit focus styles, and undersized buttons mean I can't reliably reach, see, or activate the controls I need to either cancel or confirm an irreversible action. | Z54: [2.4.7] If the focus ring disappears or is invisible on any of the two buttons, I completely lose my place inside the dialog. With only two focusable elements I could get stuck not knowing which button is active. Add explicit CSS focus styles, e.g. button:focus-visible { outline: 3px solid #005fcc; outline-offset: 2px; } to guarantee a visible indicator in all browsers. || [2.1.1] When the dialog opens I need focus to land inside it automatically. If it doesn't, I'm stuck — Tab won't reach the buttons because the main content is inert and there's nothing else to tab to, leaving me unable to Cancel or Delete. Add autofocus to the Cancel button (<button type="button" autofocus>Cancel</button>) or use a script to call focus() on the first interactive element when the dialog is rendered. Also ensure focus is trapped within the dialog while it is open. || [2.5.5] My adaptive pointing device needs at least 44×44 px targets. Undersized buttons mean I frequently miss and activate the wrong action — especially dangerous here where 'Delete account' is irreversible. Add CSS: button { min-height: 44px; min-width: 44px; padding: 10px 16px; } to ensure both buttons meet the minimum target size.
A55: ha-2-4-3-pass-02-modal-focus-trap | B55: persona_llm | C55: B | D55: claude-sonnet-4-6 | E55: ade | F55: 2.4.3 | G55: passed | H55: failed | I55: =IF(EXACT(G55,H55),1,0) -> 0 | J55: 2 | K55: critical | L55: 3 | M55: 0 | O55: 1 | P55: 18.65 | Q55: 1384 | R55: 831 | S55: Modal dialog keeps focus inside the dialog | V55: hand-authored from W3C Understanding | X55: corpus1\ade\2.4.3\passed\ha-2-4-3-pass-02-modal-focus-trap.html | Y55: This dialog is inaccessible to me as Ade: focus is never moved into it when it opens, so I'm left stranded with no visible focus indicator and a disorienting tab order, and the unstyled buttons are too small for my adaptive device to reliably hit. | Z55: [2.4.7] As Ade, if focus is not moved into the dialog when it opens, I have no idea where I am on the page. The main content is inert so Tab does nothing there, and I can't see where focus landed — I've completely lost my place. Add focus management: on dialog open, programmatically move focus to the dialog container (add `tabindex="-1"` to the `<div role="dialog">`) or to the first interactive element (Cancel button). Ensure a visible focus ring is present via CSS (e.g., `outline: 2px solid #005fcc`). || [2.4.3] As Ade, Tab order starts somewhere outside the dialog, then jumps into the Cancel button. That disorienting jump makes me unsure whether I'm interacting with the dialog or something else entirely. On dialog activation, call `document.querySelector('[role="dialog"]').focus()` (with `tabindex="-1"` on the div) or `cancelButton.focus()` to establish a logical, predictable focus entry point inside the dialog. || [2.5.5] As Ade, my adaptive pointing device struggles to land on small targets. A 'Delete account' button that is only as tall as a line of text is very easy to miss, and a misclick here could be catastrophic — it deletes my account. Apply CSS to ensure both buttons meet 44×44 px minimum: e.g., `button { min-height: 44px; min-width: 44px; padding: 10px 16px; }`.
A56: 52be6331dc0978990a8b806a9a4a84bf738a43e1 | B56: persona_llm | C56: B | D56: claude-sonnet-4-6 | E56: ade | F56: 2.4.7 | G56: passed | H56: passed | I56: =IF(EXACT(G56,H56),1,0) -> 1 | J56: 0 | K56: N/A | L56: 0 | M56: 0 | O56: 1 | P56: 4.5 | Q56: 1269 | R56: 99 | S56: Passed Example 1 | T56: oj04fd | U56: Element in sequential focus order has visible focus | W56: https://www.w3.org/WAI/content-assets/wcag-act-rules/testcases/oj04fd/52be6331dc0978990a8b806a9a4a84bf738a43e1.html | X56: corpus1\ade\2.4.7\passed\52be6331dc0978990a8b806a9a4a84bf738a43e1.html | Y56: This page has a single native anchor link with an href, which is fully keyboard accessible, has a visible default focus indicator, follows a trivial tab order, has no time limits, and as a text link is exempt from the 44px target size requirement — nothing here blocks me from using it.
A57: 52be6331dc0978990a8b806a9a4a84bf738a43e1 | B57: persona_llm | C57: B | D57: claude-sonnet-4-6 | E57: ade | F57: 2.4.7 | G57: passed | H57: passed | I57: =IF(EXACT(G57,H57),1,0) -> 1 | J57: 1 | K57: N/A | L57: 0 | M57: 0 | O57: 1 | P57: 3.33 | Q57: 1269 | R57: 99 | S57: Passed Example 1 | T57: oj04fd | U57: Element in sequential focus order has visible focus | W57: https://www.w3.org/WAI/content-assets/wcag-act-rules/testcases/oj04fd/52be6331dc0978990a8b806a9a4a84bf738a43e1.html | X57: corpus1\ade\2.4.7\passed\52be6331dc0978990a8b806a9a4a84bf738a43e1.html | Y57: This page has a single native anchor link with an href, which is fully keyboard accessible, has a visible default focus indicator, follows a trivial tab order, has no time limits, and as a text link is exempt from the 44px target size requirement — I can navigate it without any problems.
A58: 52be6331dc0978990a8b806a9a4a84bf738a43e1 | B58: persona_llm | C58: B | D58: claude-sonnet-4-6 | E58: ade | F58: 2.4.7 | G58: passed | H58: passed | I58: =IF(EXACT(G58,H58),1,0) -> 1 | J58: 2 | K58: N/A | L58: 0 | M58: 0 | O58: 1 | P58: 3.7 | Q58: 1269 | R58: 105 | S58: Passed Example 1 | T58: oj04fd | U58: Element in sequential focus order has visible focus | W58: https://www.w3.org/WAI/content-assets/wcag-act-rules/testcases/oj04fd/52be6331dc0978990a8b806a9a4a84bf738a43e1.html | X58: corpus1\ade\2.4.7\passed\52be6331dc0978990a8b806a9a4a84bf738a43e1.html | Y58: This page has a single native anchor link with an href, which is fully keyboard accessible, has a visible focus indicator from the browser default, has no timing issues, follows a trivial but logical tab order, and as an inline text link is exempt from the 44px target size requirement — I can navigate this without any problems.
A59: 8f296b7a417523e9c769761dd41b703c75d90019 | B59: persona_llm | C59: B | D59: claude-sonnet-4-6 | E59: ade | F59: 2.4.7 | G59: passed | H59: passed | I59: =IF(EXACT(G59,H59),1,0) -> 1 | J59: 0 | K59: N/A | L59: 0 | M59: 0 | O59: 1 | P59: 3.95 | Q59: 1694 | R59: 100 | S59: Passed Example 4 | T59: oj04fd | U59: Element in sequential focus order has visible focus | W59: https://www.w3.org/WAI/content-assets/wcag-act-rules/testcases/oj04fd/8f296b7a417523e9c769761dd41b703c75d90019.html | X59: corpus1\ade\2.4.7\passed\8f296b7a417523e9c769761dd41b703c75d90019.html | Y59: This page has three standard anchor links that are keyboard-reachable via Tab, and the custom focus indicator mechanism (toggling 'solid' class on adjacent span elements via onfocus/onblur) provides visible focus indication, so I can navigate and see where I am without getting lost.
A60: 8f296b7a417523e9c769761dd41b703c75d90019 | B60: persona_llm | C60: B | D60: claude-sonnet-4-6 | E60: ade | F60: 2.4.7 | G60: passed | H60: passed | I60: =IF(EXACT(G60,H60),1,0) -> 1 | J60: 1 | K60: N/A | L60: 0 | M60: 0 | O60: 1 | P60: 3.37 | Q60: 1694 | R60: 95 | S60: Passed Example 4 | T60: oj04fd | U60: Element in sequential focus order has visible focus | W60: https://www.w3.org/WAI/content-assets/wcag-act-rules/testcases/oj04fd/8f296b7a417523e9c769761dd41b703c75d90019.html | X60: corpus1\ade\2.4.7\passed\8f296b7a417523e9c769761dd41b703c75d90019.html | Y60: This page has three standard anchor links that are keyboard-focusable by default, and the onfocus/onblur JavaScript toggles custom visual indicators to show focus state, so I can tab through all links and always see where I am — no barriers for me here.
A61: 8f296b7a417523e9c769761dd41b703c75d90019 | B61: persona_llm | C61: B | D61: claude-sonnet-4-6 | E61: ade | F61: 2.4.7 | G61: passed | H61: passed | I61: =IF(EXACT(G61,H61),1,0) -> 1 | J61: 2 | K61: N/A | L61: 0 | M61: 0 | O61: 1 | P61: 3.69 | Q61: 1694 | R61: 94 | S61: Passed Example 4 | T61: oj04fd | U61: Element in sequential focus order has visible focus | W61: https://www.w3.org/WAI/content-assets/wcag-act-rules/testcases/oj04fd/8f296b7a417523e9c769761dd41b703c75d90019.html | X61: corpus1\ade\2.4.7\passed\8f296b7a417523e9c769761dd41b703c75d90019.html | Y61: This page has three standard anchor links that are keyboard-focusable by default, and the onfocus/onblur handlers toggle visible indicator spans to show focus state, so I can tab through all links and always see where I am — no barriers for me here.
A62: 90789ad82a761b7697418e8cb403db103f0925a2 | B62: persona_llm | C62: B | D62: claude-sonnet-4-6 | E62: ade | F62: 2.4.7 | G62: inapplicable | H62: inapplicable | I62: =IF(EXACT(G62,H62),1,0) -> 1 | J62: 0 | K62: N/A | L62: 0 | M62: 0 | O62: 1 | P62: 3.81 | Q62: 1261 | R62: 83 | S62: Inapplicable Example 1 | T62: oj04fd | U62: Element in sequential focus order has visible focus | W62: https://www.w3.org/WAI/content-assets/wcag-act-rules/testcases/oj04fd/90789ad82a761b7697418e8cb403db103f0925a2.html | X62: corpus1\ade\2.4.7\inapplicable\90789ad82a761b7697418e8cb403db103f0925a2.html | Y62: This page has no interactive elements whatsoever — just a plain text span — so there is nothing for me to tab to, focus on, or interact with, making all five criteria inapplicable.
A63: 90789ad82a761b7697418e8cb403db103f0925a2 | B63: persona_llm | C63: B | D63: claude-sonnet-4-6 | E63: ade | F63: 2.4.7 | G63: inapplicable | H63: inapplicable | I63: =IF(EXACT(G63,H63),1,0) -> 1 | J63: 1 | K63: N/A | L63: 0 | M63: 0 | O63: 1 | P63: 2.7 | Q63: 1261 | R63: 77 | S63: Inapplicable Example 1 | T63: oj04fd | U63: Element in sequential focus order has visible focus | W63: https://www.w3.org/WAI/content-assets/wcag-act-rules/testcases/oj04fd/90789ad82a761b7697418e8cb403db103f0925a2.html | X63: corpus1\ade\2.4.7\inapplicable\90789ad82a761b7697418e8cb403db103f0925a2.html | Y63: There are no interactive elements on this page whatsoever — just a plain text span — so none of my keyboard, timing, focus, or target-size concerns apply here.
A64: 90789ad82a761b7697418e8cb403db103f0925a2 | B64: persona_llm | C64: B | D64: claude-sonnet-4-6 | E64: ade | F64: 2.4.7 | G64: inapplicable | H64: inapplicable | I64: =IF(EXACT(G64,H64),1,0) -> 1 | J64: 2 | K64: N/A | L64: 0 | M64: 0 | O64: 1 | P64: 2.76 | Q64: 1261 | R64: 83 | S64: Inapplicable Example 1 | T64: oj04fd | U64: Element in sequential focus order has visible focus | W64: https://www.w3.org/WAI/content-assets/wcag-act-rules/testcases/oj04fd/90789ad82a761b7697418e8cb403db103f0925a2.html | X64: corpus1\ade\2.4.7\inapplicable\90789ad82a761b7697418e8cb403db103f0925a2.html | Y64: This page has no interactive elements whatsoever — just a plain text span — so there's nothing for me to tab to, focus on, or interact with, making all five criteria inapplicable.
A65: b12f1f45eef29c30197ca3bda79d793cd90eeadd | B65: persona_llm | C65: B | D65: claude-sonnet-4-6 | E65: ade | F65: 2.4.7 | G65: inapplicable | H65: failed | I65: =IF(EXACT(G65,H65),1,0) -> 0 | J65: 0 | K65: critical | L65: 2 | M65: 0 | O65: 1 | P65: 11.97 | Q65: 1312 | R65: 506 | S65: Inapplicable Example 2 | T65: oj04fd | U65: Element in sequential focus order has visible focus | W65: https://www.w3.org/WAI/content-assets/wcag-act-rules/testcases/oj04fd/b12f1f45eef29c30197ca3bda79d793cd90eeadd.html | X65: corpus1\ade\2.4.7\inapplicable\b12f1f45eef29c30197ca3bda79d793cd90eeadd.html | Y65: This page has two links I can see but can never reach — tabindex='-1' has locked me out of both of them, and as someone who relies entirely on keyboard navigation, this page is effectively non-functional for me. | Z65: [2.1.1] As Ade, I use Tab for everything. If it can't be reached with Tab, it doesn't exist for me. Both links on this page are completely invisible to my keyboard navigation — I cannot activate either of them. Remove tabindex='-1' from both anchor elements, or change to tabindex='0' if a custom tab order is needed. Native links should remain in the natural tab order unless there is a specific, justified reason to exclude them. || [2.4.7] As Ade, I need to see where focus is at all times. With tabindex='-1' removing these links from tab order entirely, there is no focus indicator to observe, meaning I have no visual feedback about my position on the page. Restore the links to the tab order and add a clear :focus style (e.g., outline: 3px solid #005fcc) to ensure focus is always visible.
A66: b12f1f45eef29c30197ca3bda79d793cd90eeadd | B66: persona_llm | C66: B | D66: claude-sonnet-4-6 | E66: ade | F66: 2.4.7 | G66: inapplicable | H66: failed | I66: =IF(EXACT(G66,H66),1,0) -> 0 | J66: 1 | K66: critical | L66: 2 | M66: 0 | O66: 1 | P66: 10.59 | Q66: 1312 | R66: 488 | S66: Inapplicable Example 2 | T66: oj04fd | U66: Element in sequential focus order has visible focus | W66: https://www.w3.org/WAI/content-assets/wcag-act-rules/testcases/oj04fd/b12f1f45eef29c30197ca3bda79d793cd90eeadd.html | X66: corpus1\ade\2.4.7\inapplicable\b12f1f45eef29c30197ca3bda79d793cd90eeadd.html | Y66: This page has two links I simply cannot reach — they've been deliberately pulled out of the tab order with tabindex='-1', which means as Ade, who relies entirely on keyboard navigation, these links do not exist for me. | Z66: [2.1.1] As Ade, I use Tab for everything. If it can't be reached with Tab, it doesn't exist for me. Both links on this page are completely unreachable by keyboard navigation — I cannot activate either link at all. Remove the tabindex='-1' attribute from both anchor elements, or change to tabindex='0' if a positive tab order is needed. Native anchor elements with href are keyboard focusable by default and should not be excluded from the tab order unless they are intentionally hidden or decorative. || [2.4.7] Even if I somehow reached these links, there is no focus style defined anywhere in the page, so I would have no visible indicator of where I am. Restore keyboard focusability and add a visible :focus style (e.g., outline: 2px solid #005fcc) to all interactive elements.
A67: b12f1f45eef29c30197ca3bda79d793cd90eeadd | B67: persona_llm | C67: B | D67: claude-sonnet-4-6 | E67: ade | F67: 2.4.7 | G67: inapplicable | H67: failed | I67: =IF(EXACT(G67,H67),1,0) -> 0 | J67: 2 | K67: critical | L67: 2 | M67: 0 | O67: 1 | P67: 10.68 | Q67: 1312 | R67: 488 | S67: Inapplicable Example 2 | T67: oj04fd | U67: Element in sequential focus order has visible focus | W67: https://www.w3.org/WAI/content-assets/wcag-act-rules/testcases/oj04fd/b12f1f45eef29c30197ca3bda79d793cd90eeadd.html | X67: corpus1\ade\2.4.7\inapplicable\b12f1f45eef29c30197ca3bda79d793cd90eeadd.html | Y67: This page is completely broken for me — both links are hidden from the Tab key with tabindex='-1', so I have zero keyboard-accessible interactive elements and no visible focus indicator anywhere on the page. | Z67: [2.1.1] As Ade, I use Tab for everything — if it can't be reached by Tab, it doesn't exist for me. Both links on this page are completely unreachable by keyboard navigation. I cannot activate either link. Remove the tabindex='-1' attribute from both anchor elements, or change it to tabindex='0' if a specific tab order is needed. Native anchor elements with href are keyboard focusable by default and should not be excluded from the tab order. || [2.4.7] I need to see where focus is at all times. Since neither link can receive focus via Tab, there is never a visible focus indicator on any interactive element — I have no visual anchor on this page. Restore these links to the tab order (remove tabindex='-1') and add a visible :focus style, e.g. a:focus { outline: 3px solid #005fcc; }.
A68: f1c9efb4c8d1b5f7870c693bce2e6ca046dd768d | B68: persona_llm | C68: B | D68: claude-sonnet-4-6 | E68: ade | F68: 2.4.7 | G68: failed | H68: failed | I68: =IF(EXACT(G68,H68),1,0) -> 1 | J68: 0 | K68: critical | L68: 1 | M68: 0 | O68: 1 | P68: 8.96 | Q68: 1318 | R68: 354 | S68: Failed Example 1 | T68: oj04fd | U68: Element in sequential focus order has visible focus | W68: https://www.w3.org/WAI/content-assets/wcag-act-rules/testcases/oj04fd/f1c9efb4c8d1b5f7870c693bce2e6ca046dd768d.html | X68: corpus1\ade\2.4.7\failed\f1c9efb4c8d1b5f7870c693bce2e6ca046dd768d.html | Y68: This page fails because the link's focus indicator has been deliberately suppressed via the 'no-focus-default' stylesheet class, meaning I have no way to see where my keyboard focus is — that's a showstopper for me. | Z68: [2.4.7] As Ade, if I Tab to this link I have no visible cue that focus is on it. I completely lose my place on the page — it's as if the keyboard cursor has vanished. I cannot tell where I am or what will activate if I press Enter. Remove any CSS rule that sets `outline: none` or `outline: 0` on this element (or its :focus/:focus-visible pseudo-class). Provide a clearly visible focus indicator, such as `outline: 3px solid #005fcc; outline-offset: 2px;` on `:focus-visible`.
A69: f1c9efb4c8d1b5f7870c693bce2e6ca046dd768d | B69: persona_llm | C69: B | D69: claude-sonnet-4-6 | E69: ade | F69: 2.4.7 | G69: failed | H69: failed | I69: =IF(EXACT(G69,H69),1,0) -> 1 | J69: 1 | K69: critical | L69: 1 | M69: 0 | O69: 1 | P69: 7.58 | Q69: 1318 | R69: 335 | S69: Failed Example 1 | T69: oj04fd | U69: Element in sequential focus order has visible focus | W69: https://www.w3.org/WAI/content-assets/wcag-act-rules/testcases/oj04fd/f1c9efb4c8d1b5f7870c693bce2e6ca046dd768d.html | X69: corpus1\ade\2.4.7\failed\f1c9efb4c8d1b5f7870c693bce2e6ca046dd768d.html | Y69: This page fails me completely — the one interactive element has its focus ring stripped away, so the moment I Tab to it, I'm flying blind with no idea where I am on the page. | Z69: [2.4.7] As Ade, when I Tab to this link I have absolutely no idea where keyboard focus is. The focus indicator disappears entirely, meaning I lose my place on the page and cannot tell whether I've reached the link or moved past it. Remove any CSS rule that sets `outline: none` or `outline: 0` on focused elements. Instead, provide a clearly visible focus style, such as `a:focus { outline: 3px solid #005fcc; outline-offset: 2px; }`, ensuring the indicator meets at least a 3:1 contrast ratio against the surrounding background.
A70: f1c9efb4c8d1b5f7870c693bce2e6ca046dd768d | B70: persona_llm | C70: B | D70: claude-sonnet-4-6 | E70: ade | F70: 2.4.7 | G70: failed | H70: failed | I70: =IF(EXACT(G70,H70),1,0) -> 1 | J70: 2 | K70: critical | L70: 1 | M70: 0 | O70: 1 | P70: 8.2 | Q70: 1318 | R70: 349 | S70: Failed Example 1 | T70: oj04fd | U70: Element in sequential focus order has visible focus | W70: https://www.w3.org/WAI/content-assets/wcag-act-rules/testcases/oj04fd/f1c9efb4c8d1b5f7870c693bce2e6ca046dd768d.html | X70: corpus1\ade\2.4.7\failed\f1c9efb4c8d1b5f7870c693bce2e6ca046dd768d.html | Y70: This page fails because the link's focus indicator appears to be deliberately suppressed via the 'no-focus-default' stylesheet class, meaning I have no visible cue when I Tab to it — I'm navigating blind. | Z70: [2.4.7] As Ade, if the focus indicator is removed from this link I have absolutely no way to tell where I am on the page when I Tab to it. I lose my place completely — it's as if the keyboard cursor vanishes. Remove any CSS rule that sets `outline: none` or `outline: 0` on focused elements, or replace it with a clearly visible custom focus style (e.g., `outline: 3px solid #005fcc; outline-offset: 2px`) that meets the 2.4.11 minimum contrast and area requirements.
A71: ha-2-4-7-fail-01-focus-suppressed | B71: persona_llm | C71: B | D71: claude-sonnet-4-6 | E71: ade | F71: 2.4.7 | G71: failed | H71: failed | I71: =IF(EXACT(G71,H71),1,0) -> 1 | J71: 0 | K71: critical | L71: 2 | M71: 0 | O71: 1 | P71: 12.81 | Q71: 1400 | R71: 547 | S71: Focus indicator suppressed via CSS outline removal | V71: hand-authored from W3C Understanding | X71: corpus1\ade\2.4.7\failed\ha-2-4-7-fail-01-focus-suppressed.html | Y71: This page is completely unusable for me as Ade — the deliberate removal of every focus indicator means I cannot see where my keyboard focus is at any point, which is a showstopper, and the unstyled controls are likely too small for my adaptive device to hit reliably. | Z71: [2.4.7] As Ade, I rely entirely on the visible focus ring to know where I am on the page. With outline and box-shadow both suppressed and no replacement indicator, focus is completely invisible. When I Tab through the email field, Subscribe button, and Privacy policy link, I have no idea which element is active — I am completely lost. Remove the `outline: none` rules entirely, or replace them with a high-contrast custom focus style, e.g. `outline: 3px solid #005fcc; outline-offset: 2px;` applied to all interactive elements on :focus or :focus-visible. || [2.5.5] My adaptive pointing device struggles to land on small targets. A Subscribe button that is only ~24 px tall is very easy to miss, forcing repeated attempts and increasing fatigue. Add CSS to ensure all interactive controls meet 44×44 px minimum: e.g. `button, input[type='email'] { min-height: 44px; padding: 0 12px; }` and ensure the button is at least 44 px wide.
A72: ha-2-4-7-fail-01-focus-suppressed | B72: persona_llm | C72: B | D72: claude-sonnet-4-6 | E72: ade | F72: 2.4.7 | G72: failed | H72: failed | I72: =IF(EXACT(G72,H72),1,0) -> 1 | J72: 1 | K72: critical | L72: 1 | M72: 0 | O72: 1 | P72: 7.04 | Q72: 1400 | R72: 309 | S72: Focus indicator suppressed via CSS outline removal | V72: hand-authored from W3C Understanding | X72: corpus1\ade\2.4.7\failed\ha-2-4-7-fail-01-focus-suppressed.html | Y72: This page is a critical failure for me — the CSS deliberately kills every focus indicator, so the moment I press Tab I'm navigating blind with no way to see where I am. | Z72: [2.4.7] As Ade, when I Tab through this form I have absolutely no idea where keyboard focus is. The cursor is invisible. I cannot tell if I'm on the email field, the button, or the link — I've completely lost my place and cannot operate the page reliably. Remove the `outline: none` and `box-shadow: none` declarations from focus styles. Provide a clearly visible focus indicator (e.g., `outline: 3px solid #005fcc; outline-offset: 2px;`) for all interactive elements.
A73: ha-2-4-7-fail-01-focus-suppressed | B73: persona_llm | C73: B | D73: claude-sonnet-4-6 | E73: ade | F73: 2.4.7 | G73: failed | H73: failed | I73: =IF(EXACT(G73,H73),1,0) -> 1 | J73: 2 | K73: critical | L73: 1 | M73: 0 | O73: 1 | P73: 7.52 | Q73: 1400 | R73: 317 | S73: Focus indicator suppressed via CSS outline removal | V73: hand-authored from W3C Understanding | X73: corpus1\ade\2.4.7\failed\ha-2-4-7-fail-01-focus-suppressed.html | Y73: This page is unusable for me — every focus indicator has been deliberately stripped away, so tabbing through the form is like navigating in the dark with no landmarks. | Z73: [2.4.7] As Ade, I rely entirely on the visible focus ring to know where I am on the page. With outline and box-shadow both suppressed and no replacement indicator, focus is completely invisible. When I Tab through the email field, Subscribe button, and Privacy policy link, I have no idea which element is active — I am completely lost. Remove the `outline: none` and `box-shadow: none` declarations from focus states, or replace them with a clearly visible custom focus indicator (e.g., `outline: 3px solid #005fcc; outline-offset: 2px;`) that meets at least a 3:1 contrast ratio against the surrounding background.
A74: ha-2-5-5-fail-01-tiny-icons | B74: persona_llm | C74: B | D74: claude-sonnet-4-6 | E74: ade | F74: 2.5.5 | G74: failed | H74: failed | I74: =IF(EXACT(G74,H74),1,0) -> 1 | J74: 0 | K74: serious | L74: 1 | M74: 0 | O74: 1 | P74: 8.09 | Q74: 1439 | R74: 318 | S74: Tightly packed icon buttons well below 44x44 | V74: hand-authored from W3C Understanding | X74: corpus1\ade\2.5.5\failed\ha-2-5-5-fail-01-tiny-icons.html | Y74: The gallery controls are keyboard-reachable and focus order looks fine, but every button is a tiny 20×20 px target — my adaptive device can't land on them reliably, making this page effectively unusable for me without pure keyboard-only operation. | Z74: [2.5.5] My adaptive pointing device cannot reliably land on a 20×20 px target. I will constantly mis-click or miss entirely, forcing me to fall back to Tab navigation for every single action — and even then, activating them with a pointer is essentially impossible for me. Increase each button to at least 44×44 CSS pixels (e.g., `width: 44px; height: 44px; padding: 10px;`). If the visual icon must stay small, use padding to expand the clickable area while keeping the icon centred.
A75: ha-2-5-5-fail-01-tiny-icons | B75: persona_llm | C75: B | D75: claude-sonnet-4-6 | E75: ade | F75: 2.5.5 | G75: failed | H75: failed | I75: =IF(EXACT(G75,H75),1,0) -> 1 | J75: 1 | K75: serious | L75: 1 | M75: 0 | O75: 1 | P75: 6.45 | Q75: 1439 | R75: 290 | S75: Tightly packed icon buttons well below 44x44 | V75: hand-authored from W3C Understanding | X75: corpus1\ade\2.5.5\failed\ha-2-5-5-fail-01-tiny-icons.html | Y75: The gallery controls are keyboard-reachable and focus order looks fine, but every button is a tiny 20×20 px target — my adaptive device can't reliably hit them, so this page fails for me. | Z75: [2.5.5] My adaptive pointing device cannot reliably land on a 20×20 px target. I will constantly mis-click or miss entirely, making the gallery unusable without keyboard-only navigation. Increase each button's clickable area to at least 44×44 CSS pixels, e.g. `width: 44px; height: 44px;` with appropriate padding, or use a transparent padding/pseudo-element technique to expand the hit area without changing the visual design.
A76: ha-2-5-5-fail-01-tiny-icons | B76: persona_llm | C76: B | D76: claude-sonnet-4-6 | E76: ade | F76: 2.5.5 | G76: failed | H76: failed | I76: =IF(EXACT(G76,H76),1,0) -> 1 | J76: 2 | K76: serious | L76: 1 | M76: 0 | O76: 1 | P76: 6.61 | Q76: 1439 | R76: 293 | S76: Tightly packed icon buttons well below 44x44 | V76: hand-authored from W3C Understanding | X76: corpus1\ade\2.5.5\failed\ha-2-5-5-fail-01-tiny-icons.html | Y76: The gallery controls are keyboard-reachable and focus order looks fine, but every button is only 20×20 pixels — far too small for my adaptive pointing device to hit reliably, making this page effectively unusable for me. | Z76: [2.5.5] My adaptive pointing device cannot reliably land on a 20×20 pixel target. I will constantly mis-click or miss entirely, making the gallery controls effectively unusable with my device. Increase each button's width and height to at least 44px (e.g., `width: 44px; height: 44px;`). If visual size must stay small, use transparent padding to expand the hit area to 44×44 while keeping the visible icon compact.
A77: ha-2-5-5-fail-02-short-buttons | B77: persona_llm | C77: B | D77: claude-sonnet-4-6 | E77: ade | F77: 2.5.5 | G77: failed | H77: failed | I77: =IF(EXACT(G77,H77),1,0) -> 1 | J77: 0 | K77: serious | L77: 1 | M77: 0 | O77: 1 | P77: 7.67 | Q77: 1359 | R77: 315 | S77: Standard buttons styled below 44px height | V77: hand-authored from W3C Understanding | X77: corpus1\ade\2.5.5\failed\ha-2-5-5-fail-02-short-buttons.html | Y77: The page is keyboard-accessible and focus order is fine, but all three buttons are only 28px tall — my adaptive device regularly misses targets that small, and one wrong click on 'Discard' could wipe out my work. | Z77: [2.5.5] My adaptive pointing device struggles to land precisely on small targets. At only 28px tall these buttons are easy to miss, causing accidental clicks on the wrong action — like hitting Discard instead of Save and losing my work. Set `min-height: 44px; min-width: 44px;` on the buttons (or increase padding to achieve at least 44px in both dimensions), for example `padding: 10px 16px;` with the existing font size.
A78: ha-2-5-5-fail-02-short-buttons | B78: persona_llm | C78: B | D78: claude-sonnet-4-6 | E78: ade | F78: 2.5.5 | G78: failed | H78: failed | I78: =IF(EXACT(G78,H78),1,0) -> 1 | J78: 1 | K78: serious | L78: 2 | M78: 0 | O78: 1 | P78: 9.86 | Q78: 1359 | R78: 454 | S78: Standard buttons styled below 44px height | V78: hand-authored from W3C Understanding | X78: corpus1\ade\2.5.5\failed\ha-2-5-5-fail-02-short-buttons.html | Y78: These buttons are too small for my adaptive device to hit reliably, and without explicit focus styles I can't tell where I am on the page — both of which make this form genuinely difficult for me to use. | Z78: [2.4.7] As Ade, if I can't see where keyboard focus is, I lose my place entirely among the three buttons. I have no way to know which button I'm about to activate. Add explicit :focus-visible styles with a high-contrast outline, e.g. button:focus-visible { outline: 3px solid #005fcc; outline-offset: 2px; } || [2.5.5] As Ade, my adaptive pointing device struggles to land on small targets. A 28px-tall button is very easy to miss, causing accidental activations or repeated failed attempts. Increase button height to at least 44px: button { height: 44px; min-width: 44px; padding: 0 16px; }
A79: ha-2-5-5-fail-02-short-buttons | B79: persona_llm | C79: B | D79: claude-sonnet-4-6 | E79: ade | F79: 2.5.5 | G79: failed | H79: failed | I79: =IF(EXACT(G79,H79),1,0) -> 1 | J79: 2 | K79: serious | L79: 2 | M79: 0 | O79: 1 | P79: 12.85 | Q79: 1359 | R79: 574 | S79: Standard buttons styled below 44px height | V79: hand-authored from W3C Understanding | X79: corpus1\ade\2.5.5\failed\ha-2-5-5-fail-02-short-buttons.html | Y79: The page's buttons are keyboard-reachable but fail me on two fronts: there's no guaranteed visible focus indicator so I lose track of where I am, and at only 28px tall the buttons are too small for my adaptive pointing device to reliably hit. | Z79: [2.4.7] As Ade, I rely entirely on the keyboard focus ring to know where I am. If the default outline is suppressed or inconsistent across browsers, I lose my place the moment I Tab between Save, Discard, and Preview — and I have no way to recover without tabbing blindly. Add an explicit :focus-visible rule, e.g. button:focus-visible { outline: 3px solid #005fcc; outline-offset: 2px; } to guarantee a high-contrast, always-visible focus indicator regardless of browser defaults. || [2.5.5] My adaptive pointing device needs a large landing zone. A 28px-tall button is very easy to miss or activate the wrong one, especially when three buttons are packed close together with only 4px margin between them. Remove the fixed height: 28px and instead set min-height: 44px; min-width: 44px on buttons, and increase padding to ensure the tap/click target meets the 44×44 CSS pixel requirement.
A80: ha-2-5-5-inap-01-inline-link-in-text | B80: persona_llm | C80: B | D80: claude-sonnet-4-6 | E80: ade | F80: 2.5.5 | G80: inapplicable | H80: inapplicable | I80: =IF(EXACT(G80,H80),1,0) -> 1 | J80: 0 | K80: N/A | L80: 0 | M80: 0 | O80: 1 | P80: 2.74 | Q80: 1310 | R80: 77 | S80: Only interactive element is an inline link within text | V80: hand-authored from W3C Understanding | X80: corpus1\ade\2.5.5\inapplicable\ha-2-5-5-inap-01-inline-link-in-text.html | Y80: This page has only a single inline text link and no other interactive elements, so none of my keyboard, timing, focus order, focus visibility, or target size concerns apply here.
A81: ha-2-5-5-inap-01-inline-link-in-text | B81: persona_llm | C81: B | D81: claude-sonnet-4-6 | E81: ade | F81: 2.5.5 | G81: inapplicable | H81: inapplicable | I81: =IF(EXACT(G81,H81),1,0) -> 1 | J81: 1 | K81: N/A | L81: 0 | M81: 0 | O81: 1 | P81: 2.92 | Q81: 1310 | R81: 89 | S81: Only interactive element is an inline link within text | V81: hand-authored from W3C Understanding | X81: corpus1\ade\2.5.5\inapplicable\ha-2-5-5-inap-01-inline-link-in-text.html | Y81: This page has only a single inline text link and no other interactive elements, so none of my keyboard, timing, focus order, focus visibility, or target size concerns are meaningfully triggered — there's simply nothing here that could block me.
A82: ha-2-5-5-inap-01-inline-link-in-text | B82: persona_llm | C82: B | D82: claude-sonnet-4-6 | E82: ade | F82: 2.5.5 | G82: inapplicable | H82: inapplicable | I82: =IF(EXACT(G82,H82),1,0) -> 1 | J82: 2 | K82: N/A | L82: 0 | M82: 0 | O82: 1 | P82: 3.07 | Q82: 1310 | R82: 77 | S82: Only interactive element is an inline link within text | V82: hand-authored from W3C Understanding | X82: corpus1\ade\2.5.5\inapplicable\ha-2-5-5-inap-01-inline-link-in-text.html | Y82: This page has only a single inline text link and no other interactive elements, so none of my keyboard, timing, focus order, focus visibility, or target size concerns apply here.
A83: ha-2-5-5-inap-02-no-interactive | B83: persona_llm | C83: B | D83: claude-sonnet-4-6 | E83: ade | F83: 2.5.5 | G83: inapplicable | H83: inapplicable | I83: =IF(EXACT(G83,H83),1,0) -> 1 | J83: 0 | K83: N/A | L83: 0 | M83: 0 | O83: 1 | P83: 4.3 | Q83: 1301 | R83: 79 | S83: Page has no interactive targets at all | V83: hand-authored from W3C Understanding | X83: corpus1\ade\2.5.5\inapplicable\ha-2-5-5-inap-02-no-interactive.html | Y83: This page is a static notice with no interactive elements whatsoever — no links, buttons, forms, or timed content — so none of my five keyboard and interaction criteria apply here.
A84: ha-2-5-5-inap-02-no-interactive | B84: persona_llm | C84: B | D84: claude-sonnet-4-6 | E84: ade | F84: 2.5.5 | G84: inapplicable | H84: inapplicable | I84: =IF(EXACT(G84,H84),1,0) -> 1 | J84: 1 | K84: N/A | L84: 0 | M84: 0 | O84: 1 | P84: 2.93 | Q84: 1301 | R84: 79 | S84: Page has no interactive targets at all | V84: hand-authored from W3C Understanding | X84: corpus1\ade\2.5.5\inapplicable\ha-2-5-5-inap-02-no-interactive.html | Y84: This page is a static notice with no interactive elements whatsoever — no links, buttons, forms, or timed content — so none of my five keyboard and interaction criteria apply here.
A85: ha-2-5-5-inap-02-no-interactive | B85: persona_llm | C85: B | D85: claude-sonnet-4-6 | E85: ade | F85: 2.5.5 | G85: inapplicable | H85: inapplicable | I85: =IF(EXACT(G85,H85),1,0) -> 1 | J85: 2 | K85: N/A | L85: 0 | M85: 0 | O85: 1 | P85: 2.7 | Q85: 1301 | R85: 79 | S85: Page has no interactive targets at all | V85: hand-authored from W3C Understanding | X85: corpus1\ade\2.5.5\inapplicable\ha-2-5-5-inap-02-no-interactive.html | Y85: This page is a static notice with no interactive elements whatsoever — no links, buttons, forms, or timed content — so none of my five keyboard and interaction criteria apply here.
A86: ha-2-5-5-pass-01-large-buttons | B86: persona_llm | C86: B | D86: claude-sonnet-4-6 | E86: ade | F86: 2.5.5 | G86: passed | H86: passed | I86: =IF(EXACT(G86,H86),1,0) -> 1 | J86: 0 | K86: N/A | L86: 0 | M86: 0 | O86: 1 | P86: 3.24 | Q86: 1366 | R86: 85 | S86: Buttons sized at or above 44x44 CSS pixels | V86: hand-authored from W3C Understanding | X86: corpus1\ade\2.5.5\passed\ha-2-5-5-pass-01-large-buttons.html | Y86: This settings page is clean and straightforward — both buttons are native HTML elements with generous sizing (min 48×48px), no time limits, no focus order issues, and keyboard access works as expected with default browser focus indicators.
A87: ha-2-5-5-pass-01-large-buttons | B87: persona_llm | C87: B | D87: claude-sonnet-4-6 | E87: ade | F87: 2.5.5 | G87: passed | H87: passed | I87: =IF(EXACT(G87,H87),1,0) -> 1 | J87: 1 | K87: N/A | L87: 0 | M87: 0 | O87: 1 | P87: 2.9 | Q87: 1366 | R87: 86 | S87: Buttons sized at or above 44x44 CSS pixels | V87: hand-authored from W3C Understanding | X87: corpus1\ade\2.5.5\passed\ha-2-5-5-pass-01-large-buttons.html | Y87: This settings page is clean and straightforward — both buttons are native HTML elements with generous sizing (min 48×48px), no time limits, no focus order issues, and keyboard access works as expected with default browser focus styling intact.
A88: ha-2-5-5-pass-01-large-buttons | B88: persona_llm | C88: B | D88: claude-sonnet-4-6 | E88: ade | F88: 2.5.5 | G88: passed | H88: passed | I88: =IF(EXACT(G88,H88),1,0) -> 1 | J88: 2 | K88: N/A | L88: 0 | M88: 0 | O88: 1 | P88: 2.89 | Q88: 1366 | R88: 86 | S88: Buttons sized at or above 44x44 CSS pixels | V88: hand-authored from W3C Understanding | X88: corpus1\ade\2.5.5\passed\ha-2-5-5-pass-01-large-buttons.html | Y88: This simple settings page with two well-sized, keyboard-accessible buttons passes all five criteria — I can Tab to both buttons, see where I am, and the 48×48px targets are easy for my adaptive device to hit.
A89: ha-2-5-5-pass-02-icon-with-padding | B89: persona_llm | C89: B | D89: claude-sonnet-4-6 | E89: ade | F89: 2.5.5 | G89: passed | H89: passed | I89: =IF(EXACT(G89,H89),1,0) -> 1 | J89: 0 | K89: N/A | L89: 0 | M89: 0 | O89: 1 | P89: 3.29 | Q89: 1434 | R89: 85 | S89: Small icon with generous touch padding reaches 44x44 | V89: hand-authored from W3C Understanding | X89: corpus1\ade\2.5.5\passed\ha-2-5-5-pass-02-icon-with-padding.html | Y89: Both toolbar buttons are native HTML button elements with proper aria-labels, 48×48px hit targets, no time limits, and no focus order or visibility concerns — this page works well for me as a keyboard-only user.
A90: ha-2-5-5-pass-02-icon-with-padding | B90: persona_llm | C90: B | D90: claude-sonnet-4-6 | E90: ade | F90: 2.5.5 | G90: passed | H90: passed | I90: =IF(EXACT(G90,H90),1,0) -> 1 | J90: 1 | K90: N/A | L90: 0 | M90: 0 | O90: 1 | P90: 2.82 | Q90: 1434 | R90: 83 | S90: Small icon with generous touch padding reaches 44x44 | V90: hand-authored from W3C Understanding | X90: corpus1\ade\2.5.5\passed\ha-2-5-5-pass-02-icon-with-padding.html | Y90: Both toolbar buttons are native HTML button elements with proper aria-labels, 48×48px sizing, no time limits, and standard keyboard focusability — this page works well for me as a keyboard-only user.
A91: ha-2-5-5-pass-02-icon-with-padding | B91: persona_llm | C91: B | D91: claude-sonnet-4-6 | E91: ade | F91: 2.5.5 | G91: passed | H91: passed | I91: =IF(EXACT(G91,H91),1,0) -> 1 | J91: 2 | K91: N/A | L91: 0 | M91: 0 | O91: 1 | P91: 3.46 | Q91: 1434 | R91: 89 | S91: Small icon with generous touch padding reaches 44x44 | V91: hand-authored from W3C Understanding | X91: corpus1\ade\2.5.5\passed\ha-2-5-5-pass-02-icon-with-padding.html | Y91: Both toolbar buttons are native HTML button elements with proper aria-labels, 48×48px sizing well above the 44px threshold, and no timing or focus-order concerns — this page works cleanly for me as a keyboard-only user.
A92: 0411dce372604b1c0b14fe48aae6190882e8110c | B92: persona_llm | C92: B | D92: claude-sonnet-4-6 | E92: elias | F92: 1.3.5 | G92: passed | H92: passed | I92: =IF(EXACT(G92,H92),1,0) -> 1 | J92: 0 | K92: N/A | L92: 0 | M92: 0 | O92: 1 | P92: 4.88 | Q92: 1338 | R92: 87 | S92: Passed Example 6 | T92: 73f2c2 | U92: `autocomplete` attribute has valid value | W92: https://www.w3.org/WAI/content-assets/wcag-act-rules/testcases/73f2c2/0411dce372604b1c0b14fe48aae6190882e8110c.html | X92: corpus1\elias\1.3.5\passed\0411dce372604b1c0b14fe48aae6190882e8110c.html | Y92: This minimal page has a single billing address field with a proper autocomplete attribute, no animations, no contrast issues with default browser text, no complex layout to clip, and no navigation structure requiring breadcrumbs — it passes all applicable criteria.
A93: 0411dce372604b1c0b14fe48aae6190882e8110c | B93: persona_llm | C93: B | D93: claude-sonnet-4-6 | E93: elias | F93: 1.3.5 | G93: passed | H93: passed | I93: =IF(EXACT(G93,H93),1,0) -> 1 | J93: 1 | K93: N/A | L93: 0 | M93: 0 | O93: 1 | P93: 2.95 | Q93: 1338 | R93: 88 | S93: Passed Example 6 | T93: 73f2c2 | U93: `autocomplete` attribute has valid value | W93: https://www.w3.org/WAI/content-assets/wcag-act-rules/testcases/73f2c2/0411dce372604b1c0b14fe48aae6190882e8110c.html | X93: corpus1\elias\1.3.5\passed\0411dce372604b1c0b14fe48aae6190882e8110c.html | Y93: This simple single-field page passes all applicable criteria — the autocomplete attribute is properly set, there's no moving content, no contrast issues with default black-on-white text, and as a standalone page breadcrumbs are not needed.
A94: 0411dce372604b1c0b14fe48aae6190882e8110c | B94: persona_llm | C94: B | D94: claude-sonnet-4-6 | E94: elias | F94: 1.3.5 | G94: passed | H94: passed | I94: =IF(EXACT(G94,H94),1,0) -> 1 | J94: 2 | K94: N/A | L94: 0 | M94: 0 | O94: 1 | P94: 2.95 | Q94: 1338 | R94: 90 | S94: Passed Example 6 | T94: 73f2c2 | U94: `autocomplete` attribute has valid value | W94: https://www.w3.org/WAI/content-assets/wcag-act-rules/testcases/73f2c2/0411dce372604b1c0b14fe48aae6190882e8110c.html | X94: corpus1\elias\1.3.5\passed\0411dce372604b1c0b14fe48aae6190882e8110c.html | Y94: This minimal single-field page passes all applicable criteria — the input has a proper autocomplete attribute, there's no moving content, no contrast issues with the default black-on-white text, and as a standalone page breadcrumbs are not needed.
A95: 130d7f761a6a43b896b2f1d0ded311da6a7aebf1 | B95: persona_llm | C95: B | D95: claude-sonnet-4-6 | E95: elias | F95: 1.3.5 | G95: failed | H95: failed | I95: =IF(EXACT(G95,H95),1,0) -> 1 | J95: 0 | K95: moderate | L95: 1 | M95: 0 | O95: 1 | P95: 7.91 | Q95: 1321 | R95: 305 | S95: Failed Example 8 | T95: 73f2c2 | U95: Autocomplete attribute has valid value | W95: https://www.w3.org/WAI/content-assets/wcag-act-rules/testcases/73f2c2/130d7f761a6a43b896b2f1d0ded311da6a7aebf1.html | X95: corpus1\elias\1.3.5\failed\130d7f761a6a43b896b2f1d0ded311da6a7aebf1.html | Y95: This page fails because the email field uses an invalid autocomplete value ('work' alone), which means my browser won't auto-fill it and I'm stuck typing my email address by hand — a real hardship with my tremor. | Z95: [1.3.5] As Elias, typing is exhausting due to my tremor. I depend on autocomplete to pre-fill fields like email. An invalid autocomplete value means the browser won't offer to fill this field automatically, forcing me to type my full email address by hand every time. Change the autocomplete attribute to a valid token: autocomplete="email" or, if a work-specific email is intended, autocomplete="work email".
A96: 130d7f761a6a43b896b2f1d0ded311da6a7aebf1 | B96: persona_llm | C96: B | D96: claude-sonnet-4-6 | E96: elias | F96: 1.3.5 | G96: failed | H96: failed | I96: =IF(EXACT(G96,H96),1,0) -> 1 | J96: 1 | K96: moderate | L96: 2 | M96: 0 | O96: 1 | P96: 10.94 | Q96: 1321 | R96: 502 | S96: Failed Example 8 | T96: 73f2c2 | U96: Autocomplete attribute has valid value | W96: https://www.w3.org/WAI/content-assets/wcag-act-rules/testcases/73f2c2/130d7f761a6a43b896b2f1d0ded311da6a7aebf1.html | X96: corpus1\elias\1.3.5\failed\130d7f761a6a43b896b2f1d0ded311da6a7aebf1.html | Y96: This page fails primarily because the autocomplete attribute on the email field uses an invalid token ('work' alone), which means my browser won't auto-fill my email address and I'll have to type it out by hand — a real hardship with my tremor. | Z96: [1.3.5] As Elias, typing is exhausting due to my tremor. I rely on autocomplete to fill in my email address without having to laboriously type every character. An invalid autocomplete value means the browser won't offer to fill in my email, forcing me to type it all out myself. Change the autocomplete attribute to a valid token: autocomplete="email" for a personal email field, or autocomplete="work email" if a work email is specifically required. || [2.4.8] If this form is part of a larger site, I would have no way to know where I am when zoomed in at 200–300%, as there are no breadcrumbs or location indicators visible. If this page is part of a multi-page site, add a breadcrumb navigation element (e.g., <nav aria-label="breadcrumb">) to help users orient themselves.
A97: 130d7f761a6a43b896b2f1d0ded311da6a7aebf1 | B97: persona_llm | C97: B | D97: claude-sonnet-4-6 | E97: elias | F97: 1.3.5 | G97: failed | H97: failed | I97: =IF(EXACT(G97,H97),1,0) -> 1 | J97: 2 | K97: moderate | L97: 1 | M97: 0 | O97: 1 | P97: 7.64 | Q97: 1321 | R97: 276 | S97: Failed Example 8 | T97: 73f2c2 | U97: Autocomplete attribute has valid value | W97: https://www.w3.org/WAI/content-assets/wcag-act-rules/testcases/73f2c2/130d7f761a6a43b896b2f1d0ded311da6a7aebf1.html | X97: corpus1\elias\1.3.5\failed\130d7f761a6a43b896b2f1d0ded311da6a7aebf1.html | Y97: This page fails because the email field uses an invalid autocomplete token ('work' alone is not a recognized purpose token), robbing me of the browser autocomplete assistance I depend on to avoid painful, error-prone typing. | Z97: [1.3.5] My tremor makes typing exhausting. I rely on autocomplete to fill in my email address without having to laboriously type every character. An invalid autocomplete value means the browser cannot offer me the correct suggestion, so I'm forced to type the whole thing myself. Change the autocomplete attribute to a valid value that identifies the field's purpose, e.g., autocomplete="email" or autocomplete="work email".
A98: 2512c24c9a793fa8a30958e203090f955a3fc262 | B98: persona_llm | C98: B | D98: claude-sonnet-4-6 | E98: elias | F98: 1.3.5 | G98: failed | H98: failed | I98: =IF(EXACT(G98,H98),1,0) -> 1 | J98: 0 | K98: moderate | L98: 1 | M98: 0 | O98: 1 | P98: 8.35 | Q98: 1321 | R98: 290 | S98: Failed Example 6 | T98: 73f2c2 | U98: Autocomplete attribute has valid value | W98: https://www.w3.org/WAI/content-assets/wcag-act-rules/testcases/73f2c2/2512c24c9a793fa8a30958e203090f955a3fc262.html | X98: corpus1\elias\1.3.5\failed\2512c24c9a793fa8a30958e203090f955a3fc262.html | Y98: This address field uses an incomplete autocomplete value that prevents my browser from autofilling it, which means my tremor forces me to laboriously type out my full address by hand. | Z98: [1.3.5] As Elias, my tremor makes typing exhausting. I depend on autocomplete to fill in address fields automatically. With only 'shipping' as the token, the browser cannot identify what specific data to autofill, so I'm forced to type the full address by hand — character by character, with shaking hands. Add a specific field token after the grouping token, e.g., autocomplete="shipping street-address", so browsers and assistive technologies can correctly identify and autofill the field.
A99: 2512c24c9a793fa8a30958e203090f955a3fc262 | B99: persona_llm | C99: B | D99: claude-sonnet-4-6 | E99: elias | F99: 1.3.5 | G99: failed | H99: failed | I99: =IF(EXACT(G99,H99),1,0) -> 1 | J99: 1 | K99: moderate | L99: 1 | M99: 0 | O99: 1 | P99: 7.84 | Q99: 1321 | R99: 307 | S99: Failed Example 6 | T99: 73f2c2 | U99: Autocomplete attribute has valid value | W99: https://www.w3.org/WAI/content-assets/wcag-act-rules/testcases/73f2c2/2512c24c9a793fa8a30958e203090f955a3fc262.html | X99: corpus1\elias\1.3.5\failed\2512c24c9a793fa8a30958e203090f955a3fc262.html | Y99: This address field uses an incomplete autocomplete token that prevents my browser from autofilling it, which means my trembling hands have to type every character of my address manually — a small oversight with a real cost for me. | Z99: [1.3.5] As Elias, my tremor makes typing exhausting. I depend on autocomplete to fill in address fields automatically. With only 'shipping' as the token, the browser cannot identify what specific data to autofill, so I'm forced to type the full address by hand — letter by letter, which is painful and slow. Replace autocomplete="shipping" with a valid combination such as autocomplete="shipping street-address" (or the appropriate named token like 'address-line1') so browsers and assistive technologies can correctly identify and autofill the field.
A100: 2512c24c9a793fa8a30958e203090f955a3fc262 | B100: persona_llm | C100: B | D100: claude-sonnet-4-6 | E100: elias | F100: 1.3.5 | G100: failed | H100: failed | I100: =IF(EXACT(G100,H100),1,0) -> 1 | J100: 2 | K100: moderate | L100: 5 | M100: 0 | O100: 1 | P100: 15.66 | Q100: 1321 | R100: 747 | S100: Failed Example 6 | T100: 73f2c2 | U100: Autocomplete attribute has valid value | W100: https://www.w3.org/WAI/content-assets/wcag-act-rules/testcases/73f2c2/2512c24c9a793fa8a30958e203090f955a3fc262.html | X100: corpus1\elias\1.3.5\failed\2512c24c9a793fa8a30958e203090f955a3fc262.html | Y100: This page fails because the autocomplete attribute on the address field uses only the grouping token 'shipping' without a valid field name, which means my browser won't auto-fill it and I'll have to type the whole address myself with my trembling hands. | Z100: [1.3.5] As Elias, my tremor makes typing exhausting. I depend on autocomplete to fill in address fields without having to laboriously type every character. A malformed autocomplete value means the browser won't offer suggestions, so I'm forced to type the full address by hand. Replace autocomplete="shipping" with a valid combination such as autocomplete="shipping street-address" or autocomplete="shipping address-line1" per the HTML specification's list of autofill field names. || [1.4.3] N/A — default contrast is generally adequate for my magnified reading. When styling is added, ensure all text meets at least 4.5:1 contrast ratio. || [1.4.12] N/A — no restrictive spacing rules detected. Continue to avoid fixed-height containers and overflow:hidden when styling is added. || [2.2.2] N/A — no autoplay or moving content to trigger nausea. No action needed for this criterion. || [2.4.8] N/A — page appears standalone; location indicators are inapplicable. If this form is embedded within a larger site, add breadcrumb navigation so I can orient myself when zoomed in.
...

Sheet C_persona_agent
A1: snippet_id | B1: condition | C1: condition_key | D1: model | E1: persona | F1: wcag_criterion | G1: expected | H1: evaluated | I1: correct | J1: repetition | K1: severity | L1: issue_count | M1: tool_call_count | N1: tools_called | O1: iteration_count | P1: total_time_seconds | Q1: input_tokens | R1: output_tokens | S1: testcase_title | T1: rule_id | U1: rule_name | V1: corpus_source | W1: rule_url | X1: html_path | Y1: overall_assessment | Z1: issues_detail
A2: 033e04cced5973596d9aa724feacb027d23b4c53 | B2: persona_agent | C2: C | D2: claude-sonnet-4-6 | E2: ade | F2: 2.1.1 | G2: inapplicable | H2: inapplicable | I2: =IF(EXACT(G2,H2),1,0) -> 1 | J2: 0 | K2: N/A | L2: 0 | M2: 6 | N2: check_keyboard_focusables, detect_keyboard_violations, check_timing_and_timeouts, validate_focus_order, validate_focus_visible, validate_target_size | O2: 2 | P2: 34.84 | Q2: 9844 | R2: 1082 | S2: Inapplicable Example 2 | T2: akn7bn | U2: Iframe with interactive elements is not excluded from tab-order | W2: https://www.w3.org/WAI/content-assets/wcag-act-rules/testcases/akn7bn/033e04cced5973596d9aa724feacb027d23b4c53.html | X2: corpus1\ade\2.1.1\inapplicable\033e04cced5973596d9aa724feacb027d23b4c53.html | Y2: This page has no interactive elements I can actually reach — the only thing here is a hidden iframe with tabindex='-1', so there's nothing for me to keyboard-navigate, focus, or interact with, making all five WCAG criteria inapplicable.
A3: 033e04cced5973596d9aa724feacb027d23b4c53 | B3: persona_agent | C3: C | D3: claude-sonnet-4-6 | E3: ade | F3: 2.1.1 | G3: inapplicable | H3: inapplicable | I3: =IF(EXACT(G3,H3),1,0) -> 1 | J3: 1 | K3: N/A | L3: 0 | M3: 6 | N3: check_keyboard_focusables, detect_keyboard_violations, check_timing_and_timeouts, validate_focus_order, validate_focus_visible, validate_target_size | O3: 2 | P3: 30.99 | Q3: 9884 | R3: 926 | S3: Inapplicable Example 2 | T3: akn7bn | U3: Iframe with interactive elements is not excluded from tab-order | W3: https://www.w3.org/WAI/content-assets/wcag-act-rules/testcases/akn7bn/033e04cced5973596d9aa724feacb027d23b4c53.html | X3: corpus1\ade\2.1.1\inapplicable\033e04cced5973596d9aa724feacb027d23b4c53.html | Y3: This page has no visible or keyboard-reachable interactive elements whatsoever — the only link is buried inside a hidden, tabindex=-1 iframe, so none of my five WCAG criteria even apply here.
A4: 033e04cced5973596d9aa724feacb027d23b4c53 | B4: persona_agent | C4: C | D4: claude-sonnet-4-6 | E4: ade | F4: 2.1.1 | G4: inapplicable | H4: inapplicable | I4: =IF(EXACT(G4,H4),1,0) -> 1 | J4: 2 | K4: N/A | L4: 0 | M4: 6 | N4: check_keyboard_focusables, detect_keyboard_violations, check_timing_and_timeouts, validate_focus_order, validate_focus_visible, validate_target_size | O4: 2 | P4: 34.62 | Q4: 9884 | R4: 1144 | S4: Inapplicable Example 2 | T4: akn7bn | U4: Iframe with interactive elements is not excluded from tab-order | W4: https://www.w3.org/WAI/content-assets/wcag-act-rules/testcases/akn7bn/033e04cced5973596d9aa724feacb027d23b4c53.html | X4: corpus1\ade\2.1.1\inapplicable\033e04cced5973596d9aa724feacb027d23b4c53.html | Y4: There's nothing on this page I can interact with — the only element is a hidden iframe with tabindex='-1', so its embedded link is completely invisible to me and to every accessibility check; all five WCAG criteria are inapplicable.
A5: 17a371c470316dc29e424101065ebfe9f7b2e990 | B5: persona_agent | C5: C | D5: claude-sonnet-4-6 | E5: ade | F5: 2.1.1 | G5: inapplicable | H5: inapplicable | I5: =IF(EXACT(G5,H5),1,0) -> 1 | J5: 0 | K5: N/A | L5: 0 | M5: 6 | N5: check_keyboard_focusables, detect_keyboard_violations, check_timing_and_timeouts, validate_focus_order, validate_focus_visible, validate_target_size | O5: 2 | P5: 27.22 | Q5: 9893 | R5: 1160 | S5: Inapplicable Example 5 | T5: akn7bn | U5: Iframe with interactive elements is not excluded from tab-order | W5: https://www.w3.org/WAI/content-assets/wcag-act-rules/testcases/akn7bn/17a371c470316dc29e424101065ebfe9f7b2e990.html | X5: corpus1\ade\2.1.1\inapplicable\17a371c470316dc29e424101065ebfe9f7b2e990.html | Y5: This page has no keyboard-reachable interactive elements — the only content is an iframe with tabindex='-1' and the inert attribute, which removes both it and its inner link from the tab sequence entirely, so there's nothing here for me to navigate to or interact with.
A6: 17a371c470316dc29e424101065ebfe9f7b2e990 | B6: persona_agent | C6: C | D6: claude-sonnet-4-6 | E6: ade | F6: 2.1.1 | G6: inapplicable | H6: inapplicable | I6: =IF(EXACT(G6,H6),1,0) -> 1 | J6: 1 | K6: N/A | L6: 0 | M6: 6 | N6: check_keyboard_focusables, detect_keyboard_violations, check_timing_and_timeouts, validate_focus_order, validate_focus_visible, validate_target_size | O6: 2 | P6: 25.7 | Q6: 9892 | R6: 1039 | S6: Inapplicable Example 5 | T6: akn7bn | U6: Iframe with interactive elements is not excluded from tab-order | W6: https://www.w3.org/WAI/content-assets/wcag-act-rules/testcases/akn7bn/17a371c470316dc29e424101065ebfe9f7b2e990.html | X6: corpus1\ade\2.1.1\inapplicable\17a371c470316dc29e424101065ebfe9f7b2e990.html | Y6: This page has no keyboard-reachable interactive elements — the only thing here is an iframe that's explicitly excluded from tab order with tabindex='-1' and made fully inert, so none of my five WCAG criteria even apply.
A7: 17a371c470316dc29e424101065ebfe9f7b2e990 | B7: persona_agent | C7: C | D7: claude-sonnet-4-6 | E7: ade | F7: 2.1.1 | G7: inapplicable | H7: inapplicable | I7: =IF(EXACT(G7,H7),1,0) -> 1 | J7: 2 | K7: N/A | L7: 0 | M7: 6 | N7: check_keyboard_focusables, detect_keyboard_violations, check_timing_and_timeouts, validate_focus_order, validate_focus_visible, validate_target_size | O7: 2 | P7: 25.77 | Q7: 9893 | R7: 1027 | S7: Inapplicable Example 5 | T7: akn7bn | U7: Iframe with interactive elements is not excluded from tab-order | W7: https://www.w3.org/WAI/content-assets/wcag-act-rules/testcases/akn7bn/17a371c470316dc29e424101065ebfe9f7b2e990.html | X7: corpus1\ade\2.1.1\inapplicable\17a371c470316dc29e424101065ebfe9f7b2e990.html | Y7: There's nothing on this page I can interact with — the only element is an iframe that's been explicitly removed from the tab order with tabindex='-1' and made fully inert, so none of my five WCAG criteria even apply here.
